Workbook

Sheet Фин.модель
B2: Выручка за год план | C2: =D9+F9+H9+J9+L9+N9+P9+R9+T9+V9+X9+Z9 -> 1.9495234e+08
B3: Чистая прибыль за год план | C3: =Z114 -> 53778632
B4: Рентабельность по чистой прибыли | C4: =C3/C2 -> 0.27585528
D5: план | E5: факт | F5: план | G5: факт | H5: план | I5: факт | J5: план | K5: факт | L5: план | M5: план | N5: план | O5: факт | P5: план | Q5: факт | R5: план | S5: факт | T5: план | U5: факт | V5: план | W5: факт | X5: план | Y5: факт | Z5: план | AA5: факт | AB5: итого план | AC5: итого факт | AD5: ср. за 12 мес.
B6: Периоды | D6: 1 | E6: 1 | F6: 2 | G6: 2 | H6: 3 | I6: 3 | J6: 4 | K6: 4 | L6: 5 | M6: 5 | N6: 6 | O6: 6 | P6: 7 | Q6: 7 | R6: 8 | S6: 8 | T6: 9 | U6: 9 | V6: 10 | W6: 10 | X6: 11 | Y6: 11 | Z6: 12 | AA6: 12
B7: Выручка всего, в т.ч. НДС | E7: =E9+E8 -> 10102615 | G7: =G8+G9 -> 12029194 | I7: =I8+I9 -> 11360493 | K7: =K8+K9 -> 12078469 | M7: =M9+M8 -> 12503715 | O7: =O8+O9 -> 10971089 | Q7: =Q8+Q9 -> 11716150 | S7: =S9+S8 -> 10843120 | U7: =U8+U9 -> 12070447 | W7: =W8+W9 -> 12434280 | Y7: =Y9+Y8 -> 12148776 | AA7: =AA8+AA9 -> 17199184 | AC7: =SUM(D7:AA7) -> 1.4545753e+08 | AD7: =AC7/12 -> 12121461
B8: НДС | E8: 468663.42 | G8: 536537.34 | I8: 563526.7 | K8: 536106.76 | M8: 545088.45 | O8: 495577.4 | Q8: 565315.09 | S8: 464282.96 | U8: 620657.12 | W8: 541266.87 | Y8: 551061.01 | AA8: 788270.54 | AC8: =SUM(D8:AA8) -> 6676353.7 | AD8: =AC8/12 -> 556362.8
B9: Выручка всего, без НДС | D9: =D38+D55+D56+D57 -> 12422914 | E9: =E38+E55+E56+E57 -> 9633951.5 | F9: =F38+F55+F56+F57 -> 12630400 | G9: =G38+G55+G56+G57 -> 11492657 | H9: =H38+H55+H56+H57 -> 16723253 | I9: =I38+I55+I56+I57 -> 10796966 | J9: =J38+J55+J56+J57 -> 15989617 | K9: =K38+K55+K56+K57 -> 11542362 | ... AA9: =AA38+AA55+AA56+AA57 -> 16410914 | AB9: =D9+F9+H9+J9+L9+N9+P9+R9+T9+V9+X9+Z9 -> 1.9495234e+08 | AC9: =E9+G9+I9+K9+M9+O9+Q9+S9+U9+W9+Y9+AA9 -> 1.3878118e+08 | AD9: =AC9/12 -> 11565098
B10: БЛОК ПРОДАЖ | C10: =D10+F10+H10+J10+L10+N10+P10+R10+T10+V10+X10+Z10 -> 754.93421 | D10: =D11+D16+D21 -> 38.70614 | E10: =E11+E16+E21 -> 12 | F10: =F11+F16+F21 -> 38.70614 | G10: =G11+G16+G21 -> 40 | H10: =H11+H16+H21 -> 38.70614 | I10: =I11+I16+I21 -> 44 | J10: =J11+J16+J21 -> 54.495614 | K10: =K11+K16+K21 -> 47 | ... AA10: =AA11+AA16+AA21 -> 21 | AB10: =C10 -> 754.93421 | AC10: =E10+G10+I10++K10+M10+O10+Q10+S10+U10+W10+Y10+AA10 -> 391.25
B11: total БОЛЬШИЕ | C11: =D11+F11+H11+J11+L11+N11+P11+R11+T11+V11+X11+Z11 -> 200 | D11: =D12+D13 -> 16.666667 | E11: =E12+E13 -> 5 | F11: =F12+F13 -> 16.666667 | G11: =G12+G13 -> 10 | H11: =H12+H13 -> 16.666667 | I11: =I12+I13 -> 13 | J11: =J12+J13 -> 16.666667 | K11: =K12+K13 -> 13 | ... AA11: =AA12+AA13 -> 8 | AB11: =C11 -> 200 | AC11: =E11+G11+I11++K11+M11+O11+Q11+S11+U11+W11+Y11+AA11 -> 131
B12: лиды с др. каналов | C12: =SUM(D12:Z12)-E12-G12-I12-K12-M12-O12-Q12-S12-U12-W12-Y12 -> 100 | D12: =D14*100/$C$14 -> 8.3333333 | E12: 4 | F12: =F14*100/$C$14 -> 8.3333333 | G12: 4 | H12: =H14*100/$C$14 -> 8.3333333 | I12: 4 | J12: =J14*100/$C$14 -> 8.3333333 | K12: 4 | L12: =L14*100/$C$14 -> 8.3333333 | M12: 3 | N12: =N14*100/$C$14 -> 8.3333333 | O12: 2 | P12: =P14*100/$C$14 -> 8.3333333 | Q12: 1 | R12: =R14*100/$C$14 -> 8.3333333 | S12: 4 | T12: =T14*100/$C$14 -> 8.3333333 | U12: 3 | V12: =V14*100/$C$14 -> 8.3333333 | W12: 4 | X12: =X14*100/$C$14 -> 8.3333333 | Y12: 5 | Z12: =Z14*100/$C$14 -> 8.3333333 | AA12: 1 | AB12: =C12 -> 100 | AC12: =E12+G12+I12++K12+M12+O12+Q12+S12+U12+W12+Y12+AA12 -> 39
B13: лиды маркетинг | C13: =SUM(D13:Z13)-E13-G13-I13-K13-M13-O13-Q13-S13-U13-W13-Y13 -> 100 | D13: =D15*100/$C$14 -> 8.3333333 | E13: 1 | F13: =F15*100/$C$14 -> 8.3333333 | G13: 6 | H13: =H15*100/$C$14 -> 8.3333333 | I13: 9 | J13: =J15*100/$C$14 -> 8.3333333 | K13: 9 | L13: =L15*100/$C$14 -> 8.3333333 | M13: 5 | N13: =N15*100/$C$14 -> 8.3333333 | O13: 15 | P13: =P15*100/$C$14 -> 8.3333333 | Q13: 16 | R13: =R15*100/$C$14 -> 8.3333333 | S13: 6 | T13: =T15*100/$C$14 -> 8.3333333 | U13: 5 | V13: =V15*100/$C$14 -> 8.3333333 | W13: 6 | X13: =X15*100/$C$14 -> 8.3333333 | Y13: 7 | Z13: =Z15*100/$C$14 -> 8.3333333 | AA13: 7 | AB13: =C13 -> 100 | AC13: =E13+G13+I13++K13+M13+O13+Q13+S13+U13+W13+Y13+AA13 -> 92
B14: продажи с др. каналов | C14: =SUM(D14:Z14)-E14-G14-I14-Q14-S14-U14-W14-Y14 -> 6 | D14: 0.5 | E14: 0 | F14: =D14 -> 0.5 | G14: =E14 -> 0 | H14: =F14 -> 0.5 | I14: 2 | J14: =H14 -> 0.5 | K14: 0 | L14: =J14 -> 0.5 | M14: =K14 -> 0 | N14: =L14 -> 0.5 | O14: =M14 -> 0 | P14: =N14 -> 0.5 | Q14: 1 | R14: =P14 -> 0.5 | S14: 1 | T14: =R14 -> 0.5 | U14: 0 | V14: =T14 -> 0.5 | W14: 1 | X14: =V14 -> 0.5 | Y14: 2 | Z14: =X14 -> 0.5 | AA14: 0 | AB14: =D14+F14+H14+J14+L14+N14+P14+R14+T14+V14+X14+Z14 -> 6 | AC14: =E14+G14+I14+K14+M14+O14+Q14+S14+U14+W14+Y14+AA14 -> 7
B15: продажи с маркетинга | D15: 0.5 | E15: 1 | F15: =D15 -> 0.5 | G15: 0 | H15: =F15 -> 0.5 | I15: 0 | J15: =H15 -> 0.5 | K15: 2 | L15: =J15 -> 0.5 | M15: 0 | N15: =L15 -> 0.5 | O15: =M15 -> 0 | P15: =N15 -> 0.5 | Q15: 3 | R15: =P15 -> 0.5 | S15: 0 | T15: =R15 -> 0.5 | U15: 1 | V15: =T15 -> 0.5 | W15: =U15 -> 1 | X15: =V15 -> 0.5 | Y15: 1 | Z15: =X15 -> 0.5 | AA15: 0 | AB15: =D15+F15+H15+J15+L15+N15+P15+R15+T15+V15+X15+Z15 -> 6 | AC15: =E15+G15+I15+K15+M15+O15+Q15+S15+U15+W15+Y15+AA15 -> 9
B16: total ТЕНДЕРЫ | C16: =C17+C18 -> 81.25 | D16: =D17+D18 -> 6.25 | E16: =E17+E18 -> 7 | F16: =F17+F18 -> 6.25 | G16: =G17+G18 -> 7 | H16: =H17+H18 -> 6.25 | I16: =I17+I18 -> 8 | J16: =J17+J18 -> 6.25 | ... AA16: =AA17+AA18 -> 3 | AB16: =D16+F16+H16+J16+L16+N16+P16+R16+T16+V16+X16+Z16 -> 81.25 | AC16: =E16+G16+I16+K16+M16+O16+Q16+S16+U16+W16+Y16+AA16 -> 53.25
B17: лиды с др. каналов | C17: =SUM(D17:Z17)-E17-G17-I17-K17-M17-O17-S17-U17-W17 -> 43.75 | D17: =D19*100/$C$19 -> 3.125 | E17: 6 | F17: =F19*100/$C$19 -> 3.125 | G17: 6 | H17: =H19*100/$C$19 -> 3.125 | I17: 4 | J17: =J19*100/$C$19 -> 3.125 | K17: 1 | L17: =L19*100/$C$19 -> 3.125 | M17: 5 | N17: =N19*100/$C$19 -> 3.125 | O17: 1 | P17: =P19*100/$C$19 -> 9.375 | Q17: 0 | R17: =R19*100/$C$19 -> 3.125 | S17: =S19*100/$C$19 -> 6.25 | T17: =T19*100/$C$19 -> 3.125 | U17: 2 | V17: =V19*100/$C$19 -> 3.125 | W17: 2 | X17: =X19*100/$C$19 -> 3.125 | Y17: =Y19*100/$C$19 -> 0 | Z17: =Z19*100/$C$19 -> 3.125 | AA17: 1 | AB17: =D17+F17+H17+J17+L17+N17+P17+R17+T17+V17+X17+Z17 -> 43.75 | AC17: =E17+G17+I17+K17+M17+O17+Q17+S17+U17+W17+Y17+AA17 -> 34.25
B18: лиды с маркетинга | C18: =SUM(D18:Z18)-E18-G18-I18-K18-M18-O18-Q18-U18 -> 37.5 | D18: =D20*100/$C$19 -> 3.125 | E18: 1 | F18: =F20*100/$C$19 -> 3.125 | G18: 1 | H18: =H20*100/$C$19 -> 3.125 | I18: 4 | J18: =J20*100/$C$19 -> 3.125 | K18: 3 | L18: =L20*100/$C$19 -> 3.125 | M18: 2 | N18: =N20*100/$C$19 -> 3.125 | O18: 2 | P18: =P20*100/$C$19 -> 3.125 | Q18: 2 | R18: =R20*100/$C$19 -> 3.125 | S18: =S20*100/$C$19 -> 0 | T18: =T20*100/$C$19 -> 3.125 | U18: 2 | V18: =V20*100/$C$19 -> 3.125 | W18: =W20*100/$C$19 -> 0 | X18: =X20*100/$C$19 -> 3.125 | Y18: =Y20*100/$C$19 -> 0 | Z18: =Z20*100/$C$19 -> 3.125 | AA18: 2 | AB18: =D18+F18+H18+J18+L18+N18+P18+R18+T18+V18+X18+Z18 -> 37.5 | AC18: =E18+G18+I18+K18+M18+O18+Q18+S18+U18+W18+Y18+AA18 -> 19
B19: продажи с др. каналов | C19: 16 | D19: 0.5 | E19: 0 | F19: =D19 -> 0.5 | G19: 1 | H19: =F19 -> 0.5 | I19: 0 | J19: =H19 -> 0.5 | K19: =I19 -> 0 | L19: =J19 -> 0.5 | M19: 1 | N19: =L19 -> 0.5 | O19: 0 | P19: =N19+1 -> 1.5 | Q19: 0 | R19: =N19 -> 0.5 | S19: 1 | T19: =R19 -> 0.5 | U19: 0 | V19: =T19 -> 0.5 | W19: =U19 -> 0 | X19: =V19 -> 0.5 | Y19: =W19 -> 0 | Z19: =X19 -> 0.5 | AA19: 1 | AB19: =D19+F19+H19+J19+L19+N19+P19+R19+T19+V19+X19+Z19 -> 7 | AC19: =E19+G19+I19+K19+M19+O19+Q19+S19+U19+W19+Y19+AA19 -> 4
B20: продажи с маркетинга | D20: 0.5 | E20: 0 | F20: =D20 -> 0.5 | G20: 0 | H20: =F20 -> 0.5 | I20: 0 | J20: =H20 -> 0.5 | K20: 1 | L20: =J20 -> 0.5 | M20: 0 | N20: =L20 -> 0.5 | O20: 1 | P20: =N20 -> 0.5 | Q20: 0 | R20: =P20 -> 0.5 | S20: =Q20 -> 0 | T20: =R20 -> 0.5 | U20: =S20 -> 0 | V20: =T20 -> 0.5 | W20: =U20 -> 0 | X20: =V20 -> 0.5 | Y20: =W20 -> 0 | ... AA20: =Y20 -> 0 | AB20: =D20+F20+H20+J20+L20+N20+P20+R20+T20+V20+X20+Z20 -> 6 | AC20: =E20+G20+I20+K20+M20+O20+Q20+S20+U20+W20+Y20+AA20 -> 2
B21: total МАЛЕНЬКИЕ | C21: =C22+C23 -> 473.68421 | D21: =D22+D23 -> 15.789474 | E21: =E22+E23 -> 0 | F21: =F22+F23 -> 15.789474 | G21: =G22+G23 -> 23 | H21: =H22+H23 -> 15.789474 | I21: =I22+I23 -> 23 | J21: =J22+J23 -> 31.578947 | ... AA21: =AA22+AA23 -> 10 | AB21: =D21+F21+H21+J21+L21+N21+P21+R21+T21+V21+X21+Z21 -> 473.68421 | AC21: =E21+G21+I21+K21+M21+O21+Q21+S21+U21+W21+Y21+AA21 -> 207
B22: лиды с др. каналов | C22: =SUM(D22:Z22)-E22-G22-I22-K22-M22-O22-Q22-S22-U22-W22-Y22 -> 236.84211 | D22: =D24*100/$C$24 -> 10.526316 | E22: 0 | F22: =F24*100/$C$24 -> 10.526316 | G22: 7 | H22: =H24*100/$C$24 -> 10.526316 | I22: 4 | J22: =J24*100/$C$24 -> 15.789474 | K22: 2 | L22: =L24*100/$C$24 -> 15.789474 | M22: 2 | N22: =N24*100/$C$24 -> 15.789474 | O22: 1 | P22: =P24*100/$C$24 -> 21.052632 | Q22: 1 | R22: =R24*100/$C$24 -> 21.052632 | S22: 2 | T22: =T24*100/$C$24 -> 21.052632 | U22: 2 | V22: =V24*100/$C$24 -> 31.578947 | W22: 0 | X22: =X24*100/$C$24 -> 31.578947 | Y22: 4 | Z22: =Z24*100/$C$24 -> 31.578947 | AA22: 2 | AB22: =D22+F22+H22+J22+L22+N22+P22+R22+T22+V22+X22+Z22 -> 236.84211 | AC22: =E22+G22+I22+K22+M22+O22+Q22+S22+U22+W22+Y22+AA22 -> 27
B23: лиды с маркетинга | C23: =SUM(D23:Z23)-E23-G23-I23-K23-M23-O23-Q23-S23-U23-W23-Y23 -> 236.84211 | D23: =D25*100/$C$25 -> 5.2631579 | E23: 0 | F23: =F25*100/$C$25 -> 5.2631579 | G23: 16 | H23: =H25*100/$C$25 -> 5.2631579 | I23: 19 | J23: =J25*100/$C$25 -> 15.789474 | K23: 28 | L23: =L25*100/$C$25 -> 15.789474 | M23: 19 | N23: =N25*100/$C$25 -> 15.789474 | O23: 20 | P23: =P25*100/$C$25 -> 26.315789 | Q23: 19 | R23: =R25*100/$C$25 -> 26.315789 | S23: 14 | T23: =T25*100/$C$25 -> 26.315789 | U23: 15 | V23: =V25*100/$C$25 -> 31.578947 | W23: 16 | X23: =X25*100/$C$25 -> 31.578947 | Y23: 6 | Z23: =Z25*100/$C$25 -> 31.578947 | AA23: 8 | AB23: =D23+F23+H23+J23+L23+N23+P23+R23+T23+V23+X23+Z23 -> 236.84211 | AC23: =E23+G23+I23+K23+M23+O23+Q23+S23+U23+W23+Y23+AA23 -> 180
B24: продажи с др. каналов | C24: 19 | D24: 2 | E24: 1 | F24: =D24 -> 2 | G24: 1 | H24: =F24 -> 2 | I24: 0 | J24: 3 | K24: 0 | L24: =J24 -> 3 | M24: 1 | N24: =L24 -> 3 | O24: 3 | P24: 4 | Q24: 1 | R24: 4 | S24: 0 | T24: 4 | U24: 0 | V24: 6 | W24: 0 | X24: 6 | Y24: 1 | Z24: 6 | AA24: 1 | AB24: =D24+F24+H24+J24+L24+N24+P24+R24+T24+V24+X24+Z24 -> 45 | AC24: =E24+G24+I24+K24+M24+O24+Q24+S24+U24+W24+Y24+AA24 -> 9
B25: продажи с маркетинга | C25: 19 | D25: 1 | E25: 0 | F25: =D25 -> 1 | G25: 1 | H25: =F25 -> 1 | I25: 2 | J25: 3 | K25: 1 | L25: =J25 -> 3 | M25: =K25 -> 1 | N25: =L25 -> 3 | O25: 4 | P25: 5 | Q25: 4 | R25: 5 | S25: 0 | T25: 5 | U25: 2 | V25: 6 | W25: 0 | X25: 6 | Y25: 0 | Z25: 6 | AA25: 0 | AB25: =D25+F25+H25+J25+L25+N25+P25+R25+T25+V25+X25+Z25 -> 45 | AC25: =E25+G25+I25+K25+M25+O25+Q25+S25+U25+W25+Y25+AA25 -> 15
AB26: =D26+F26+H26+J26+L26+N26+P26+R26+T26+V26+X26+Z26 -> 0 | AC26: =E26+G26+I26+K26+M26+O26+Q26+S26+U26+W26+Y26+AA26 -> 0
B27: план total ПРОДАЖИ | C27: =SUM(D27:Z27)-E27-G27-I27-K27-M27-O27-Q27-S27-U27-W27-Y27 -> 115 | D27: =SUM(D28:D30) -> 5 | E27: =SUM(E28:E30) -> 2 | F27: =SUM(F28:F30) -> 5 | G27: =SUM(G28:G30) -> 3 | H27: =SUM(H28:H30) -> 5 | I27: =SUM(I28:I30) -> 4 | J27: =SUM(J28:J30) -> 8 | K27: =SUM(K28:K30) -> 4 | ... AA27: =SUM(AA28:AA30) -> 2 | AB27: =D27+F27+H27+J27+L27+N27+P27+R27+T27+V27+X27+Z27 -> 115 | AC27: =E27+G27+I27+K27+M27+O27+Q27+S27+U27+W27+Y27+AA27 -> 47
B28: итого продажи большой целевой проект/мес | C28: =SUM(D28:Z28)-E28-G28-I28-K28-M28-Q28-S28-U28-W28-Y28 -> 12 | D28: 1 | E28: 1 | F28: 1 | G28: 0 | H28: 1 | I28: =I14+I15 -> 2 | J28: 1 | K28: =K14+K15 -> 2 | L28: 1 | M28: =M14+M15 -> 0 | N28: 1 | O28: 0 | P28: 1 | Q28: 4 | R28: 1 | S28: 1 | T28: 1 | U28: 1 | V28: 1 | W28: 2 | X28: 1 | Y28: 4 | Z28: 1 | AA28: =AA14+AA15 -> 0 | AB28: =D28+F28+H28+J28+L28+N28+P28+R28+T28+V28+X28+Z28 -> 12 | AC28: =E28+G28+I28+K28+M28+O28+Q28+S28+U28+W28+Y28+AA28 -> 17
B29: итого продажи тендер | C29: =SUM(D29:Z29)-E29--I29-K29-M29-O29-Q29-S29-U29-W29-Y29 -> 14 | D29: 1 | E29: 0 | F29: 1 | G29: 1 | H29: 1 | I29: =I19+I20 -> 0 | J29: 1 | K29: =K19+K20 -> 1 | L29: 1 | M29: =M19+M20 -> 1 | N29: 1 | O29: 1 | P29: 2 | Q29: 0 | R29: 1 | S29: 1 | T29: 1 | U29: 0 | V29: 1 | W29: 0 | X29: 1 | Y29: 0 | Z29: 1 | AA29: =AA19+AA20 -> 1 | AB29: =D29+F29+H29+J29+L29+N29+P29+R29+T29+V29+X29+Z29 -> 13 | AC29: =E29+G29+I29+K29+M29+O29+Q29+S29+U29+W29+Y29+AA29 -> 6
B30: итого продажи маленький | C30: =SUM(D30:Z30)-E30-G30-I30-K30-M30-O30-Q30-S30-U30-W30-Y30 -> 90 | D30: 3 | E30: 1 | F30: 3 | G30: 2 | H30: 3 | I30: =I24+I25 -> 2 | J30: 6 | K30: =K24+K25 -> 1 | L30: 6 | M30: =M24+M25 -> 2 | N30: 6 | O30: 7 | P30: 9 | Q30: 5 | R30: 9 | S30: 0 | T30: 9 | U30: 2 | V30: 12 | W30: 0 | X30: 12 | Y30: 1 | Z30: 12 | AA30: =AA24+AA25 -> 1 | AB30: =D30+F30+H30+J30+L30+N30+P30+R30+T30+V30+X30+Z30 -> 90 | AC30: =E30+G30+I30+K30+M30+O30+Q30+S30+U30+W30+Y30+AA30 -> 24
B31: Средний чек тендер, руб. | C31: ср.ч./мес 180 000+1 большой | AB31: =D31+F31+H31+J31+L31+N31+P31+R31+T31+V31+X31+Z31 -> 0 | AC31: =E31+G31+I31+K31+M31+O31+Q31+S31+U31+W31+Y31+AA31 -> 0 | AD31: средний чек
B32: Сумма продаж тендеры, руб. | G32: 3332650 | H32: =1800000+360000 -> 2160000 | I32: 0 | J32: =H32 -> 2160000 | K32: 13200000 | L32: =J32 -> 2160000 | M32: 4254624 | N32: =L32 -> 2160000 | O32: 2580000 | P32: =N32+12000000 -> 14160000 | Q32: 0 | R32: =N32 -> 2160000 | S32: 7200000 | T32: =R32 -> 2160000 | U32: 0 | V32: =T32 -> 2160000 | W32: =U32 -> 0 | X32: =V32 -> 2160000 | Y32: =W32 -> 0 | Z32: =X32 -> 2160000 | AA32: =Y32 -> 0 | AB32: =D32+F32+H32+J32+L32+N32+P32+R32+T32+V32+X32+Z32 -> 33600000 | AC32: =E32+G32+I32+K32+M32+O32+Q32+S32+U32+W32+Y32+AA32 -> 30567274 | AD32: =AC32/AC29 -> 5094545.7
B33: Сумма продаж большие целевые, руб. | D33: 680000 | E33: 687535 | F33: =D33 -> 680000 | G33: 0 | H33: =F33 -> 680000 | I33: =1475614+1181515 -> 2657129 | J33: =H33 -> 680000 | K33: =1483910+426559 -> 1910469 | L33: =J33 -> 680000 | M33: 0 | N33: =L33 -> 680000 | O33: =M33 -> 0 | P33: 782000 | Q33: 6936586 | R33: 782000 | S33: 3139164 | T33: 782000 | U33: 2268726 | V33: 899300 | W33: 6665737 | X33: 899300 | Y33: 4530921 | Z33: 899300 | AA33: 3000000 | AB33: =D33+F33+H33+J33+L33+N33+P33+R33+T33+V33+X33+Z33 -> 9123900 | AC33: =E33+G33+I33+K33+M33+O33+Q33+S33+U33+W33+Y33+AA33 -> 31796267 | AD33: =AC33/AC28 -> 1870368.6
B34: Сумма продаж маленькие total, руб. | D34: ='план поступлений'!B61 -> 195000 | E34: 23000 | F34: ='план поступлений'!C61 -> 195000 | G34: 53442 | H34: ='план поступлений'!D61 -> 195000 | I34: 40575 | J34: ='план поступлений'!E61 -> 390000 | K34: 231680 | L34: ='план поступлений'!F61 -> 390000 | M34: 700989 | N34: ='план поступлений'!G61 -> 390000 | O34: 810600 | P34: ='план поступлений'!H61 -> 585000 | Q34: 942352 | R34: ='план поступлений'!I61 -> 585000 | S34: 0 | T34: ='план поступлений'!J61 -> 585000 | U34: 408739 | V34: ='план поступлений'!K61 -> 780000 | W34: 0 | X34: ='план поступлений'!L61 -> 780000 | Y34: 352702 | Z34: ='план поступлений'!M61 -> 780000 | AA34: 131200 | AB34: =D34+F34+H34+J34+L34+N34+P34+R34+T34+V34+X34+Z34 -> 5850000 | AC34: =E34+G34+I34+K34+M34+O34+Q34+S34+U34+W34+Y34+AA34 -> 3695279 | AD34: =AC34/AC30 -> 153969.96
B35: ИТОГО ПРОДАЖ-ПЛАН total, руб. | C35: =D35+F35+H35+J35+L35+N35+P35+R35+T35+V35+X35+Z35 -> 48573900 | D35: =SUM(D32:D34) -> 875000 | E35: =SUM(E32:E34) -> 710535 | F35: =SUM(F32:F34) -> 875000 | G35: =SUM(G32:G34) -> 3386092 | H35: =SUM(H32:H34) -> 3035000 | I35: =SUM(I32:I34) -> 2697704 | J35: =SUM(J32:J34) -> 3230000 | K35: =SUM(K32:K34) -> 15342149 | ... AA35: =SUM(AA32:AA34) -> 3131200 | AB35: =D35+F35+H35+J35+L35+N35+P35+R35+T35+V35+X35+Z35 -> 48573900 | AC35: =E35+G35+I35+K35+M35+O35+Q35+S35+U35+W35+Y35+AA35 -> 66058820 | AD35: =AC35/AC27 -> 1405506.8
B36: БЛОК ПРИЗНАНИЯ ВЫРУЧКИ
B38: Выручка- текущий портфель | D38: =D48+D51+D53 -> 12372914 | E38: =E48+E51+E53 -> 9152436 | F38: =F48+F51+F53 -> 12385400 | G38: =G48+G51+G53 -> 10970653 | H38: =H48+H51+H53 -> 16478253 | I38: =I48+I51+I53 -> 10185626 | J38: =J48+J51+J53 -> 15744617 | K38: =K48+K51+K53 -> 10397909 | ... AA38: =AA48+AA51+AA53 -> 11625129
B39: EMS | D39: ='Выручка-план'!P188 -> 10564101 | E39: 0 | F39: =D39 -> 10564101 | G39: =E39 -> 0 | H39: =F39 -> 10564101 | I39: =G39 -> 0 | J39: =H39 -> 10564101 | K39: =I39 -> 0 | L39: =J39 -> 10564101 | M39: =K39 -> 0 | N39: =L39 -> 10564101 | P39: =N39 -> 10564101 | R39: =P39 -> 10564101 | S39: =Q39 -> 0 | T39: =R39 -> 10564101 | V39: =T39 -> 10564101 | X39: =V39 -> 10564101 | Z39: =X39 -> 10564101 | AA39: =Y39 -> 0
B40: Коэффициент сезонности | D40: ='коэффициент сезонности'!B14 -> 0.97168371 | E40: ='коэффициент сезонности'!C14 -> 0.97283127 | F40: ='коэффициент сезонности'!C14 -> 0.97283127 | H40: ='коэффициент сезонности'!D14 -> 1.051397 | J40: ='коэффициент сезонности'!E14 -> 1.0796754 | L40: ='коэффициент сезонности'!F14 -> 1.0130132 | N40: ='коэффициент сезонности'!G14 -> 0.9327982 | P40: ='коэффициент сезонности'!H14 -> 0.96752634 | R40: ='коэффициент сезонности'!I14 -> 0.99074117 | T40: ='коэффициент сезонности'!J14 -> 1.1088903 | V40: ='коэффициент сезонности'!K14 -> 1.1443706 | X40: ='коэффициент сезонности'!L14 -> 1.1698922 | Z40: ='коэффициент сезонности'!M5 -> 1.1943613 | AA40: ='коэффициент сезонности'!N5 -> 0
B41: EMS с учетом коэффициента сезонности | D41: =D39*D40 -> 10264965 | E41: ='БЛОК-ВЫРУЧКА'!G78 -> 8477722.7 | F41: =F39*F40 -> 10277088 | G41: ='БЛОК-ВЫРУЧКА'!L78 -> 8583947.3 | H41: =H39*H40 -> 11107064 | I41: ='БЛОК-ВЫРУЧКА'!O78 -> 8987414.3 | J41: =J39*J40 -> 11405800 | K41: ='БЛОК-ВЫРУЧКА'!Q78 -> 9814327.9 | L41: =L39*L40 -> 10701574 | M41: ='БЛОК-ВЫРУЧКА'!S78 -> 9934360.9 | N41: =N39*N40 -> 9854174.4 | O41: ='БЛОК-ВЫРУЧКА'!U78 -> 8150692.4 | P41: =P39*P40 -> 10221046 | Q41: ='БЛОК-ВЫРУЧКА'!W78 -> 8346684.2 | R41: =R39*R40 -> 10466290 | S41: ='БЛОК-ВЫРУЧКА'!Z78 -> 7048368.3 | T41: =T39*T40 -> 11714429 | U41: ='БЛОК-ВЫРУЧКА'!AC78 -> 7264562 | V41: =V39*V40 -> 12089246 | W41: ='БЛОК-ВЫРУЧКА'!AE78 -> 7420532.8 | X41: =X39*X40 -> 12358860 | Y41: ='БЛОК-ВЫРУЧКА'!AG78 -> 7546009.7 | Z41: =Z39*Z40 -> 12617353 | AA41: ='БЛОК-ВЫРУЧКА'!AI78 -> 9479767.7
B42: рост за счет роста среднего чека
B43: Увеличение выручки текущего портфеля | C43: 0.03 | D43: =D41*$C$43 -> 307948.94 | E43: 0 | F43: =F41*$C$43 -> 308312.63 | H43: =H41*$C$43 -> 333211.92 | J43: =J41*$C$43 -> 342174.01 | L43: =L41*$C$43 -> 321047.21 | N43: =N41*$C$43 -> 295625.23 | P43: =P41*$C$43 -> 306631.38 | R43: =R41*$C$43 -> 313988.69 | T43: =T41*$C$43 -> 351432.86 | V43: =V41*$C$43 -> 362677.38 | X43: =X41*$C$43 -> 370765.79 | Z43: =Z41*$C$43 -> 378520.59
B44: Отток | C44: 1 клиент в месяц | D44: =-'Выручка-план'!O231 -> 0 | E44: =-'Выручка-план'!P231 -> 0 | F44: =-'Выручка-план'!P231 -> 0 | H44: =-'Выручка-план'!Q231 -> -102500 | J44: =-'Выручка-план'!R231 -> -205000 | L44: =-'Выручка-план'!S231 -> -307500 | N44: =-'Выручка-план'!T231 -> -410000 | P44: =-'Выручка-план'!U231 -> -512500 | R44: =-'Выручка-план'!V231 -> -615000 | T44: =-'Выручка-план'!W231 -> -717500 | V44: =-'Выручка-план'!X231 -> -820000 | X44: =-'Выручка-план'!Y231 -> -922500 | Z44: =-'Выручка-план'!Z231 -> -1025000
B45: Выручка техническая с новых клиентов (те, кто уже в работе) | H45: ='Выручка тех. с новых клиентов'!B8 -> 3040477 | J45: ='Выручка тех. с новых клиентов'!C8 -> 2101643 | L45: ='Выручка тех. с новых клиентов'!D8 -> 2330272 | N45: ='Выручка тех. с новых клиентов'!E8 -> 2330272 | P45: ='Выручка тех. с новых клиентов'!F8 -> 2214992 | R45: ='Выручка тех. с новых клиентов'!G8 -> 2128092 | T45: ='Выручка тех. с новых клиентов'!H8 -> 2128092 | V45: ='Выручка тех. с новых клиентов'!I8 -> 2128092 | X45: ='Выручка тех. с новых клиентов'!J8 -> 2128092 | Z45: ='Выручка тех. с новых клиентов'!K8 -> 2128092
B46: Клиенты на входе
B48: ИТОГО ВЫРУЧКА EMS | D48: =SUM(D41:D46) -> 10572914 | E48: =SUM(E41:E46) -> 8477722.7 | F48: =SUM(F41:F46) -> 10585400 | G48: =SUM(G41:G46) -> 8583947.3 | H48: =SUM(H41:H46) -> 14378253 | I48: =SUM(I41:I46) -> 8987414.3 | J48: =SUM(J41:J46) -> 13644617 | K48: =SUM(K41:K46) -> 9814327.9 | ... AA48: =SUM(AA41:AA46) -> 9479767.7 | AB48: =D48+F48+H48+J48+L48+N48+P48+R48+T48+V48+X48+Z48 -> 1.5409084e+08 | AC48: =E48+G48+I48+K48+M48+O48+Q48+S48+U48+W48+Y48+AA48 -> 1.0105439e+08 | AD48: =AC48/12 -> 8421199.2
B51: CS | C51: текущий портфель | D51: 1700000 | E51: ='БЛОК-ВЫРУЧКА'!G146 -> 674713.24 | F51: =D51 -> 1700000 | G51: ='БЛОК-ВЫРУЧКА'!L146 -> 2305705.4 | H51: =F51+300000 -> 2000000 | I51: ='БЛОК-ВЫРУЧКА'!O146 -> 1198212.1 | J51: =H51 -> 2000000 | K51: ='БЛОК-ВЫРУЧКА'!Q146 -> 583580.87 | L51: =J51 -> 2000000 | M51: ='БЛОК-ВЫРУЧКА'!S146 -> 1388277.3 | N51: =J51 -> 2000000 | O51: ='БЛОК-ВЫРУЧКА'!U146 -> 985338 | P51: =N51 -> 2000000 | Q51: ='БЛОК-ВЫРУЧКА'!W146 -> 912801.05 | R51: =N51 -> 2000000 | S51: ='БЛОК-ВЫРУЧКА'!Z146 -> 253475 | T51: =R51 -> 2000000 | U51: ='БЛОК-ВЫРУЧКА'!AC146 -> 1061608.7 | V51: =T51 -> 2000000 | W51: ='БЛОК-ВЫРУЧКА'!AE146 -> 920560 | X51: =V51 -> 2000000 | Y51: ='БЛОК-ВЫРУЧКА'!AG146 -> 1013960.5 | Z51: =X51 -> 2000000 | AA51: ='БЛОК-ВЫРУЧКА'!AI146 -> 2145361.8 | AB51: =D51+F51+H51+J51+L51+N51+P51+R51+T51+V51+X51+Z51 -> 23400000 | AC51: =E51+G51+I51+K51+M51+O51+Q51+S51+U51+W51+Y51+AA51 -> 13443594 | AD51: =AC51/12 -> 1120299.5
C52: спецпректы
B53: MONK | D53: 100000 | E53: ='БЛОК-ВЫРУЧКА'!G152 -> 0 | F53: 100000 | G53: ='БЛОК-ВЫРУЧКА'!L153 -> 81000 | H53: 100000 | I53: ='БЛОК-ВЫРУЧКА'!N153 -> 0 | J53: =H53 -> 100000 | K53: ='БЛОК-ВЫРУЧКА'!Q153 -> 0 | L53: 100000 | M53: ='БЛОК-ВЫРУЧКА'!S153 -> 0 | N53: 100000 | O53: ='БЛОК-ВЫРУЧКА'!U153 -> 552800 | P53: =N53 -> 100000 | Q53: ='БЛОК-ВЫРУЧКА'!W153 -> 25000 | R53: =P53 -> 100000 | S53: ='БЛОК-ВЫРУЧКА'!Z153 -> 0 | T53: =R53 -> 100000 | U53: ='БЛОК-ВЫРУЧКА'!AC153 -> 55000 | V53: =T53 -> 100000 | W53: ='БЛОК-ВЫРУЧКА'!AE153 -> 12000 | X53: =V53 -> 100000 | Y53: ='БЛОК-ВЫРУЧКА'!AG153 -> 22000 | Z53: =X53 -> 100000 | AB53: =D53+F53+H53+J53+L53+N53+P53+R53+T53+V53+X53+Z53 -> 1200000 | AC53: =E53+G53+I53+K53+M53+O53+Q53+S53+U53+W53+Y53+AA53 -> 747800
B54: Исполняемость новых контрактов+ отток новых контрактов | C54: 0.8
B55: Выручка техническая с новых клиентов ЕМС | I55: ='БЛОК-ВЫРУЧКА'!O87+'БЛОК-ВЫРУЧКА'!O91+'БЛОК-ВЫРУЧКА'!O88 -> 304590 | K55: ='БЛОК-ВЫРУЧКА'!Q83 -> 685695.48 | M55: ='БЛОК-ВЫРУЧКА'!S83 -> 364342 | N55: ='план поступлений'!B64 -> 265000 | O55: ='БЛОК-ВЫРУЧКА'!U87+'БЛОК-ВЫРУЧКА'!U93+'БЛОК-ВЫРУЧКА'!U125 -> 563275.51 | P55: ='план поступлений'!E64 -> 1060000 | Q55: ='БЛОК-ВЫРУЧКА'!W83-'БЛОК-ВЫРУЧКА'!W97 -> 1636430.2 | R55: ='план поступлений'!F64 -> 1325000 | S55: ='БЛОК-ВЫРУЧКА'!Z83-'БЛОК-ВЫРУЧКА'!Z96-'БЛОК-ВЫРУЧКА'!Z102-'БЛОК-ВЫРУЧКА'!Z104-'БЛОК-ВЫРУЧКА'!Z106 -> 2641830.5 | T55: ='план поступлений'!G64 -> 1590000 | U55: ='БЛОК-ВЫРУЧКА'!AC83-'БЛОК-ВЫРУЧКА'!AC89-'БЛОК-ВЫРУЧКА'!AC96-'БЛОК-ВЫРУЧКА'!AC102-'БЛОК-ВЫРУЧКА'!AC104-'БЛОК-ВЫРУЧКА'!AC105 -> 2630469.5 | V55: ='план поступлений'!H64 -> 1867750 | W55: ='БЛОК-ВЫРУЧКА'!AE83-'БЛОК-ВЫРУЧКА'!AE89-'БЛОК-ВЫРУЧКА'!AE106 -> 3347505.4 | X55: ='план поступлений'!I64 -> 2145500 | Y55: ='БЛОК-ВЫРУЧКА'!AG83-Y56 -> 2814287.5 | Z55: ='план поступлений'!J64 -> 2338250 | AA55: ='БЛОК-ВЫРУЧКА'!AI83-'БЛОК-ВЫРУЧКА'!AI100-'БЛОК-ВЫРУЧКА'!AI108 -> 4668634 | AB55: =D55+F55+H55+J55+L55+N55+P55+R55+T55+V55+X55+Z55 -> 10591500 | AC55: =E55+G55+I55+K55+M55+O55+Q55+S55+U55+W55+Y55+AA55 -> 19657060
B56: Выручка техническая с новых маленьких клиентов ЕМС | E56: ='БЛОК-ВЫРУЧКА'!G125 -> 23000 | F56: ='план поступлений'!B61 -> 195000 | G56: ='БЛОК-ВЫРУЧКА'!L83 -> 176800 | H56: ='план поступлений'!C61 -> 195000 | I56: ='БЛОК-ВЫРУЧКА'!O92+'БЛОК-ВЫРУЧКА'!O90+'БЛОК-ВЫРУЧКА'!O89 -> 75895 | J56: ='план поступлений'!D61 -> 195000 | L56: ='план поступлений'!E61 -> 390000 | N56: ='план поступлений'!F61 -> 390000 | O56: ='БЛОК-ВЫРУЧКА'!U96 -> 41300 | P56: ='план поступлений'!G61 -> 390000 | Q56: ='БЛОК-ВЫРУЧКА'!W97 -> 37906 | R56: ='план поступлений'!H61 -> 585000 | S56: ='БЛОК-ВЫРУЧКА'!Z96+'БЛОК-ВЫРУЧКА'!Z102+'БЛОК-ВЫРУЧКА'!Z104+'БЛОК-ВЫРУЧКА'!Z106 -> 141245 | T56: ='план поступлений'!I61 -> 585000 | U56: ='БЛОК-ВЫРУЧКА'!AC89+'БЛОК-ВЫРУЧКА'!AC96+'БЛОК-ВЫРУЧКА'!AC102+'БЛОК-ВЫРУЧКА'!AC104+'БЛОК-ВЫРУЧКА'!AC105 -> 310395.89 | V56: ='план поступлений'!J61 -> 585000 | W56: ='БЛОК-ВЫРУЧКА'!AE89+'БЛОК-ВЫРУЧКА'!AE106 -> 63065.238 | X56: ='план поступлений'!K61 -> 780000 | Y56: ='БЛОК-ВЫРУЧКА'!AG118+'БЛОК-ВЫРУЧКА'!AG89 -> 95612.524 | Z56: ='план поступлений'!L61 -> 780000 | AA56: ='БЛОК-ВЫРУЧКА'!AI108+'БЛОК-ВЫРУЧКА'!AI100 -> 71040 | AB56: =D56+F56+H56+J56+L56+N56+P56+R56+T56+V56+X56+Z56 -> 5070000 | AC56: =E56+G56+I56+K56+M56+O56+Q56+S56+U56+W56+Y56+AA56 -> 1036259.6
B57: Прочие поступления, в.т. Депозиты | C57: 50000 | D57: =$C$57 -> 50000 | E57: ='БЛОК-ВЫРУЧКА'!G154 -> 458515.57 | F57: =$C$57 -> 50000 | G57: ='БЛОК-ВЫРУЧКА'!L154 -> 345203.81 | H57: =$C$57 -> 50000 | I57: ='БЛОК-ВЫРУЧКА'!O154 -> 230854.75 | J57: =$C$57 -> 50000 | K57: ='БЛОК-ВЫРУЧКА'!Q154 -> 458757.9 | L57: =$C$57 -> 50000 | M57: ='БЛОК-ВЫРУЧКА'!S154 -> 271646.25 | N57: =$C$57 -> 50000 | O57: ='БЛОК-ВЫРУЧКА'!U154 -> 182105.93 | P57: =$C$57 -> 50000 | Q57: ='БЛОК-ВЫРУЧКА'!W154 -> 192013.4 | R57: =$C$57 -> 50000 | S57: ='БЛОК-ВЫРУЧКА'!Z154 -> 293918.65 | T57: =$C$57 -> 50000 | U57: ='БЛОК-ВЫРУЧКА'!AC154 -> 127753.75 | V57: =$C$57 -> 50000 | W57: ='БЛОК-ВЫРУЧКА'!AE154 -> 129349.92 | X57: =$C$57 -> 50000 | Y57: ='БЛОК-ВЫРУЧКА'!AG154 -> 105844.84 | Z57: =$C$57 -> 50000 | AA57: ='БЛОК-ВЫРУЧКА'!AI154 -> 46110.13 | AB57: =D57+F57+H57+J57+L57+N57+P57+R57+T57+V57+X57+Z57 -> 600000 | AC57: =E57+G57+I57+K57+M57+O57+Q57+S57+U57+W57+Y57+AA57 -> 2842074.9
B58: Прямые расходы | D58: =D59+D69 -> -6250610.2 | E58: =E59+E69 -> -6144387 | F58: =F59+H69 -> -6337829.8 | G58: =G59+J69 -> -6365034 | H58: =H59+J69 -> -6381703.2 | I58: =I59+N69 -> -6565853 | J58: =J59+L69 -> -6381703.1 | K58: =K59+K69 -> -6658663 | L58: =L59+N69 -> -6381703.1 | M58: =M59+P69 -> -6989486 | N58: =N59+P69 -> -6381703.1 | O58: =O59+R69 -> -6184930 | P58: =P59+R69 -> -6381703.1 | Q58: =Q59+T69 -> -6463372 | R58: =R59+T69 -> -6381703.1 | S58: =S59+V69 -> -7058942 | T58: =T59+V69 -> -7282151 | U58: =U59+X69 -> -6238397 | V58: =V59+X69 -> -7450376.2 | W58: =W59+Z69 -> -6653341 | X58: =X59+Z69 -> -7624290.1 | Y58: =Y59+Y69 -> -6754927.3 | Z58: =Z59+Z69 -> -7804096.9 | AA58: =AA59+AA69 -> -7080778.5 | AB58: =D58+F58+H58+J58+L58+N58+P58+R58+T58+V58+X58+Z58 -> -81039573 | AC58: =E58+G58+I58+K58+M58+O58+Q58+S58+U58+W58+Y58+AA58 -> -79158111
B59: Зарплата производственных сотрудников | D59: =SUM(D60:D67) -> -5900610.2 | E59: =SUM(E60:E67) -> -5868881 | F59: =SUM(F60:F67) -> -5987829.8 | G59: =SUM(G60:G67) -> -6015034 | H59: =SUM(H60:H67) -> -6031703.2 | I59: =-6215853 -> -6215853 | J59: =SUM(J60:J67) -> -6031703.1 | K59: =SUM(K60:K67) -> -6220314 | L59: =SUM(L60:L67) -> -6031703.1 | M59: =SUM(M60:M67) -> -6639486 | N59: =SUM(N60:N67) -> -6031703.1 | O59: =SUM(O60:O67) -> -5834930 | P59: =SUM(P60:P67) -> -6031703.1 | Q59: =SUM(Q60:Q67) -> -6113372 | ... AA59: =SUM(AA60:AA67) -> -6790203 | AB59: =D59+F59+H59+J59+L59+N59+P59+R59+T59+V59+X59+Z59 -> -76839573 | AC59: =E59+G59+I59+K59+M59+O59+Q59+S59+U59+W59+Y59+AA59 -> -74934403
B60: в т.ч. менедж. | D60: =-'База расходы зп'!G70 -> -1969613.8 | E60: =-2208056 -> -2208056 | F60: =H60 -> -2046858.4 | G60: =-2059055 -> -2059055 | H60: =-'База расходы зп'!I70 -> -2046858.4 | I60: =-2188862 -> -2188862 | J60: =H60 -> -2046858.4 | K60: =-2266458 -> -2266458 | L60: =J60 -> -2046858.4 | M60: =-2199611 -> -2199611 | N60: =L60 -> -2046858.4 | O60: =-2041902 -> -2041902 | P60: =N60 -> -2046858.4 | Q60: =-2242254 -> -2242254 | R60: =P60 -> -2046858.4 | S60: =-2246747 -> -2246747 | T60: =-'База расходы зп'!O70 -> -2578268.1 | U60: =-2053083 -> -2053083 | V60: =-'База расходы зп'!P70 -> -2679382.9 | W60: =-2331855 -> -2331855 | X60: =-'База расходы зп'!Q70 -> -2784463.3 | Y60: =-2534686 -> -2534686 | Z60: =-'База расходы зп'!R70 -> -2893664.7 | AA60: =-2726237 -> -2726237 | AB60: =D60+F60+H60+J60+L60+N60+P60+R60+T60+V60+X60+Z60 -> -27233401 | AC60: =E60+G60+I60+K60+M60+O60+Q60+S60+U60+W60+Y60+AA60 -> -27098806
B61: в т.ч. мартех | D61: =-'База расходы зп'!G71 -> -316393 | E61: =-352939 -> -352939 | F61: =H61 -> -326368.07 | G61: =-351399 -> -351399 | H61: =-'База расходы зп'!I71 -> -326368.07 | I61: =-353481 -> -353481 | J61: =H61 -> -326368.07 | K61: =-350864 -> -350864 | L61: =J61 -> -326368.07 | M61: =-520752 -> -520752 | N61: =L61 -> -326368.07 | O61: =-326873 -> -326873 | P61: =N61 -> -326368.07 | Q61: =-428111 -> -428111 | R61: =P61 -> -326368.07 | S61: =-520107 -> -520107 | T61: =-'База расходы зп'!O71 -> -393180.96 | U61: =-532723 -> -532723 | V61: =-'База расходы зп'!P71 -> -405576.97 | W61: =-491636 -> -491636 | X61: =-'База расходы зп'!Q71 -> -418363.79 | Y61: =-453009 -> -453009 | Z61: =-'База расходы зп'!R71 -> -431553.75 | AA61: =-503429 -> -503429 | AB61: =D61+F61+H61+J61+L61+N61+P61+R61+T61+V61+X61+Z61 -> -4249645 | AC61: =E61+G61+I61+K61+M61+O61+Q61+S61+U61+W61+Y61+AA61 -> -5185323
B62: в т.ч. дизайнеры | D62: =-'База расходы зп'!G72 -> -1254567.7 | E62: =-1093528 -> -1093528 | F62: =D62 -> -1254567.7 | G62: =-1303374 -> -1303374 | H62: =-'База расходы зп'!I72 -> -1287689.4 | I62: =-1344763 -> -1344763 | J62: =H62 -> -1287689.4 | K62: =-1320369 -> -1320369 | L62: =J62 -> -1287689.4 | M62: =-1329097 -> -1329097 | N62: =L62 -> -1287689.4 | O62: =-1182306 -> -1182306 | P62: =N62 -> -1287689.4 | Q62: =-1190113 -> -1190113 | R62: =P62 -> -1287689.4 | S62: =-1285395 -> -1285395 | T62: =-'База расходы зп'!O72 -> -1525079.9 | U62: =-1059343 -> -1059343 | V62: =-'База расходы зп'!P72 -> -1568698.6 | W62: =-1179147 -> -1179147 | X62: =-'База расходы зп'!Q72 -> -1613564.9 | Y62: =-1136487 -> -1136487 | Z62: =-'База расходы зп'!R72 -> -1659714.3 | AA62: =-1183351 -> -1183351 | AB62: =D62+F62+H62+J62+L62+N62+P62+R62+T62+V62+X62+Z62 -> -16602330 | AC62: =E62+G62+I62+K62+M62+O62+Q62+S62+U62+W62+Y62+AA62 -> -14607273
B63: в т.ч. верстальщики | D63: =-'База расходы зп'!G73 -> -335735.05 | E63: =-286175 -> -286175 | F63: =D63 -> -335735.05 | G63: =-317785 -> -317785 | H63: =-'База расходы зп'!I73 -> -338734.14 | I63: =-340496 -> -340496 | J63: =H63 -> -338734.14 | K63: =-349470 -> -349470 | L63: =J63 -> -338734.14 | M63: =-355072 -> -355072 | N63: =L63 -> -338734.14 | O63: =-361034 -> -361034 | P63: =N63 -> -338734.14 | Q63: =-417399 -> -417399 | R63: =P63 -> -338734.14 | S63: =-320276 -> -320276 | T63: =-'База расходы зп'!O73 -> -355842.16 | U63: =-421794 -> -421794 | V63: =-'База расходы зп'!P73 -> -358776.35 | W63: =-319952 -> -319952 | X63: =-'База расходы зп'!Q73 -> -361734.73 | Y63: =-431221 -> -431221 | Z63: =-'База расходы зп'!R73 -> -364717.51 | AA63: =-393249 -> -393249 | AB63: =D63+F63+H63+J63+L63+N63+P63+R63+T63+V63+X63+Z63 -> -4144945.7 | AC63: =E63+G63+I63+K63+M63+O63+Q63+S63+U63+W63+Y63+AA63 -> -4313923
B64: в т.ч. авторы | D64: =-'База расходы зп'!G74 -> -753206.03 | E64: =-685295 -> -685295 | F64: =D64 -> -753206.03 | G64: =-635132 -> -635132 | H64: =-'База расходы зп'!I74 -> -754361.72 | I64: =-670268 -> -670268 | J64: =H64 -> -754361.72 | K64: =-620073 -> -620073 | L64: =J64 -> -754361.72 | M64: =-897139 -> -897139 | N64: =L64 -> -754361.72 | O64: =-586374 -> -586374 | P64: =N64 -> -754361.72 | Q64: =-463968 -> -463968 | R64: =P64 -> -754361.72 | S64: =-626922 -> -626922 | T64: =-'База расходы зп'!O74 -> -761333.13 | U64: =-615066 -> -615066 | V64: =-'База расходы зп'!P74 -> -762501.28 | W64: =-839144 -> -839144 | X64: =-'База расходы зп'!Q74 -> -763671.23 | Y64: =-624617 -> -624617 | Z64: =-'База расходы зп'!R74 -> -764842.96 | AA64: =-631982 -> -631982 | AB64: =D64+F64+H64+J64+L64+N64+P64+R64+T64+V64+X64+Z64 -> -9084931 | AC64: =E64+G64+I64+K64+M64+O64+Q64+S64+U64+W64+Y64+AA64 -> -7895980
B65: в т.ч. аналитики | D65: =-'База расходы зп'!G75 -> -260337 | E65: =-334759 -> -334759 | F65: =D65 -> -260337 | G65: =-359560 -> -359560 | H65: =-'База расходы зп'!I75 -> -263186.41 | I65: =-370840 -> -370840 | J65: =H65 -> -263186.41 | K65: =-431263 -> -431263 | L65: =J65 -> -263186.41 | M65: =-415936 -> -415936 | N65: =L65 -> -263186.41 | O65: =-460127 -> -460127 | P65: =N65 -> -263186.41 | Q65: =-367557 -> -367557 | R65: =P65 -> -263186.41 | S65: =-476281 -> -476281 | T65: =-'База расходы зп'!O75 -> -280949.86 | U65: =-359822 -> -359822 | V65: =-'База расходы зп'!P75 -> -284024.88 | W65: =-361218 -> -361218 | X65: =-'База расходы зп'!Q75 -> -287133.56 | Y65: =-382611 -> -382611 | Z65: =-'База расходы зп'!R75 -> -290276.26 | AA65: =-424858 -> -424858 | AB65: =D65+F65+H65+J65+L65+N65+P65+R65+T65+V65+X65+Z65 -> -3242177 | AC65: =E65+G65+I65+K65+M65+O65+Q65+S65+U65+W65+Y65+AA65 -> -4744832
B66: в т.ч. управление CS | D66: =-'База расходы зп'!G77 -> -266481.6 | E66: =-266502 -> -266502 | F66: =D66 -> -266481.6 | G66: =-988729 -> -988729 | H66: =-'База расходы зп'!I77 -> -268863.11 | I66: =-947143 -> -947143 | K66: 0 | L66: =J66 -> 0 | M66: =K66 -> 0 | N66: =L66 -> 0 | O66: =M66 -> 0 | P66: =N66 -> 0 | Q66: =O66 -> 0 | R66: =P66 -> 0 | S66: =Q66 -> 0 | T66: =-'База расходы зп'!O77 -> -283605.85 | V66: =-'База расходы зп'!P77 -> -286140.4 | X66: =-'База расходы зп'!Q77 -> -288697.61 | Z66: =-'База расходы зп'!R77 -> -291277.66 | AB66: =D66+F66+H66+J66+L66+N66+P66+R66+T66+V66+X66+Z66 -> -1951547.8 | AC66: =E66+G66+I66+K66+M66+O66+Q66+S66+U66+W66+Y66+AA66 -> -2202374
B67: в т.ч. креативная команда | D67: =-'База расходы зп'!G78 -> -744275.98 | E67: =-641627 -> -641627 | F67: =D67 -> -744275.98 | H67: =-'База расходы зп'!I78 -> -745642.02 | J67: =-1014505 -> -1014505 | K67: =-881817 -> -881817 | L67: =J67 -> -1014505 | M67: -921879 | N67: =L67 -> -1014505 | O67: =-876314 -> -876314 | P67: =N67 -> -1014505 | Q67: =-1003970 -> -1003970 | R67: =P67 -> -1014505 | S67: =-1233214 -> -1233214 | T67: =-'База расходы зп'!O78 -> -753891.06 | U67: =-846566 -> -846566 | V67: =-'База расходы зп'!P78 -> -755274.75 | W67: =-780389 -> -780389 | X67: =-'База расходы зп'!Q78 -> -756660.98 | Y67: =-773019 -> -773019 | Z67: =-'База расходы зп'!R78 -> -758049.75 | AA67: =-927097 -> -927097 | AB67: =D67+F67+H67+J67+L67+N67+P67+R67+T67+V67+X67+Z67 -> -10330596 | AC67: =E67+G67+I67+K67+M67+O67+Q67+S67+U67+W67+Y67+AA67 -> -8885892
AB68: =D68+F68+H68+J68+L68+N68+P68+R68+T68+V68+X68+Z68 -> 0 | AC68: =E68+G68+I68+K68+M68+O68+Q68+S68+U68+W68+Y68+AA68 -> 0
B69: Сервисы для клиентов | C69: 350000 | D69: =-$C69 -> -350000 | E69: =-'База расходы'!M65 -> -275506 | F69: =D69 -> -350000 | G69: =-'База расходы'!O65 -> -456478.08 | H69: =-$C69 -> -350000 | I69: =-'База расходы'!Q65 -> -442465.03 | J69: =-$C69 -> -350000 | K69: =-'База расходы'!S65 -> -438348.99 | L69: =-$C69 -> -350000 | M69: =-'База расходы'!U65 -> -531254.8 | N69: =-$C69 -> -350000 | O69: =-'База расходы'!W65 -> -331854.9 | P69: =-$C69 -> -350000 | Q69: =-'База расходы'!Y65 -> -274269.75 | R69: =-$C69 -> -350000 | S69: =-'База расходы'!AA65 -> -291764.95 | T69: =-$C69 -> -350000 | U69: =-'База расходы'!AC65 -> -335755.31 | V69: =-$C69 -> -350000 | W69: =-'База расходы'!AE65 -> -372266.93 | X69: =-$C69 -> -350000 | Y69: =-'База расходы'!AG65 -> -419277.35 | Z69: =-$C69 -> -350000 | AA69: =-'База расходы'!AI65 -> -290575.54 | AB69: =D69+F69+H69+J69+L69+N69+P69+R69+T69+V69+X69+Z69 -> -4200000 | AC69: =E69+G69+I69+K69+M69+O69+Q69+S69+U69+W69+Y69+AA69 -> -4459817.6
B70: Валовая прибыль | D70: =D9+D58 -> 6172303.5 | E70: =E9+E58 -> 3489564.5 | F70: =F9+F58 -> 6292570.6 | G70: =G9+G58 -> 5127622.6 | H70: =H9+H58 -> 10341550 | I70: =I9+I58 -> 4231113.1 | J70: =J9+J58 -> 9607914.3 | K70: =K9+K58 -> 4883699.2 | ... AA70: =AA9+AA58 -> 9330135 | AB70: =D70+F70+H70+J70+L70+N70+P70+R70+T70+V70+X70+Z70 -> 1.1391277e+08 | AC70: =E70+G70+I70+K70+M70+O70+Q70+S70+U70+W70+Y70+AA70 -> 59623068
B71: Рентабельность по валовой прибыли,%% | D71: =D70/D9 -> 0.4968483 | E71: =E70/E9 -> 0.36221529 | F71: =F70/F9 -> 0.49820832 | G71: =G70/G9 -> 0.44616513 | H71: =H70/H9 -> 0.61839343 | I71: =I70/I9 -> 0.39187982 | J71: =J70/J9 -> 0.60088457 | K71: =K70/K9 -> 0.42311089 | ... AC71: =AC70/AC9 -> 0.42961926
B73: Косвенные расходы | D73: =D74+D95 -> -4434898.3 | E73: =E74+E95 -> -4167174.8 | F73: =F74+F95 -> -4693431.3 | G73: =G74+G95 -> -4573361.9 | H73: =H74+H95 -> -4763938.3 | I73: =I74+I95 -> -4343996.5 | J73: =J74+J95 -> -4744130.1 | K73: =K74+K95 -> -4618811.3 | ... AA73: =AA74+AA95 -> -4083743.9 | AB73: =D73+F73+H73+J73+L73+N73+P73+R73+T73+V73+X73+Z73 -> -57794708 | AC73: =E73+G73+I73+K73+M73+O73+Q73+S73+U73+W73+Y73+AA73 -> -51015329
B74: Административные расходы | D74: =SUM(D75:D94) -> -3101044.2 | E74: =SUM(E75:E94) -> -2996763.1 | F74: =SUM(F75:F94) -> -3261873.9 | G74: =SUM(G75:G94) -> -3030532 | H74: =SUM(H75:H94) -> -3238245.3 | I74: =SUM(I75:I94) -> -3226297.5 | J74: =SUM(J75:J94) -> -3235310.8 | K74: =SUM(K75:K94) -> -3458849 | ... AA74: =SUM(AA75:AA94) -> -3039334.5 | AB74: =D74+F74+H74+J74+L74+N74+P74+R74+T74+V74+X74+Z74 -> -39711037 | AC74: =E74+G74+I74+K74+M74+O74+Q74+S74+U74+W74+Y74+AA74 -> -36715098
B75: Административные расходы | C75: ='База расходы'!K51 -> 643649 | D75: =-'База расходы'!K51 -> -643649 | E75: =-'База расходы'!M51 -> -566158.86 | F75: =D75 -> -643649 | G75: =-'База расходы'!O51 -> -622366.06 | H75: =F75 -> -643649 | I75: =-'База расходы'!Q51 -> -638092.4 | J75: =H75 -> -643649 | K75: =-'База расходы'!S51 -> -621885.38 | L75: =J75 -> -643649 | M75: =-'База расходы'!U51 -> -513195.26 | N75: =L75 -> -643649 | O75: =-'База расходы'!W51 -> -547861.2 | P75: =N75 -> -643649 | Q75: =-'База расходы'!Y51 -> -567140.73 | R75: =P75 -> -643649 | S75: =-'База расходы'!AA51 -> -564510.12 | T75: =R75 -> -643649 | U75: =-'База расходы'!AC51 -> -537482.37 | V75: =T75 -> -643649 | W75: =-'База расходы'!AE51 -> -573186.34 | X75: =V75 -> -643649 | Y75: =-'База расходы'!AG51 -> -522320.27 | Z75: =X75 -> -643649 | AA75: =-'База расходы'!AI51 -> -608810.71 | AB75: =D75+F75+H75+J75+L75+N75+P75+R75+T75+V75+X75+Z75 -> -7723788 | AC75: =E75+G75+I75+K75+M75+O75+Q75+S75+U75+W75+Y75+AA75 -> -6883009.7
B76: ПО организационные офис | C76: ='База расходы'!K4+'База расходы'!K93+'База расходы'!K101 -> 296119.28 | D76: =-$C76 -> -296119.28 | E76: =-'База расходы'!M4-'База расходы'!M93-'База расходы'!M101 -> -227448.84 | F76: =-$C76 -> -296119.28 | G76: =-'База расходы'!O4-'База расходы'!O93-'База расходы'!O101 -> -311770.25 | H76: =-$C76 -> -296119.28 | I76: =-'База расходы'!Q4-'База расходы'!Q93-'База расходы'!Q101 -> -328572.35 | J76: =-$C76 -> -296119.28 | K76: =-'База расходы'!S4 -> -264785.72 | L76: =-$C76 -> -296119.28 | M76: =-'База расходы'!U4 -> -157722.3 | N76: =-$C76 -> -296119.28 | O76: =-'База расходы'!W4-'База расходы'!W93-'База расходы'!W101 -> -99110.08 | P76: =-$C76+'База расходы'!$G$5 -> -216119.28 | Q76: =-'База расходы'!Y4+'База расходы'!Y93+'База расходы'!Y101 -> -33354.27 | R76: =-$C76+'База расходы'!$G$5 -> -216119.28 | S76: =-'База расходы'!AA4 -> -142293.33 | T76: =-$C76+'База расходы'!$G$5 -> -216119.28 | U76: =-'База расходы'!AC4-'База расходы'!AC93-'База расходы'!AC101 -> -184388.24 | V76: =-$C76+'База расходы'!$G$5 -> -216119.28 | W76: =-'База расходы'!AE4-'База расходы'!AE93-'База расходы'!AE101 -> -145979.54 | X76: =-$C76+'База расходы'!$G$5 -> -216119.28 | Y76: =-'База расходы'!AG4-'База расходы'!AG93-'База расходы'!AG101 -> -408841.82 | Z76: =-$C76+'База расходы'!$G$5 -> -216119.28 | AA76: =-'База расходы'!AI4 -> -228482.64 | AB76: =D76+F76+H76+J76+L76+N76+P76+R76+T76+V76+X76+Z76 -> -3073431.4 | AC76: =E76+G76+I76+K76+M76+O76+Q76+S76+U76+W76+Y76+AA76 -> -2532749.4
B77: Сервисы финансы | C77: ='База расходы'!K82 -> 22190.067 | D77: =-$C77 -> -22190.067 | E77: =-'База расходы'!M82 -> -17331.898 | F77: =-$C77 -> -22190.067 | G77: =-'База расходы'!O82 -> -20816.627 | H77: =-$C77 -> -22190.067 | I77: =-'База расходы'!Q82 -> -20738.027 | J77: =-$C77 -> -22190.067 | K77: =-'База расходы'!S82 -> -20623.207 | L77: =-$C77 -> -22190.067 | M77: =-'База расходы'!U82 -> -97109.607 | N77: =-$C77 -> -22190.067 | O77: =-'База расходы'!W82 -> -105772.03 | P77: =-$C77 -> -22190.067 | Q77: =-'База расходы'!Y82 -> -88067.947 | R77: =-$C77 -> -22190.067 | S77: =-'База расходы'!AA82 -> -92067.947 | T77: =-$C77 -> -22190.067 | U77: =-'База расходы'!AC82 -> -90208.667 | V77: =-$C77 -> -22190.067 | W77: =-'База расходы'!AE82 -> -90765 | X77: =-$C77 -> -22190.067 | Y77: =-'База расходы'!AG82 -> -90765 | Z77: =-$C77 -> -22190.067 | AA77: =-'База расходы'!AI82 -> -90765 | AB77: =D77+F77+H77+J77+L77+N77+P77+R77+T77+V77+X77+Z77 -> -266280.8 | AC77: =E77+G77+I77+K77+M77+O77+Q77+S77+U77+W77+Y77+AA77 -> -825030.95
B78: Банковские расходы | C78: 0.004 | D78: =-D9*$C$78 -> -49691.655 | E78: =-25452.78-3016 -> -28468.78 | F78: =-F9*$C$78 -> -50521.602 | G78: =-26183.53 -> -26183.53 | H78: =-H9*$C$78 -> -66893.012 | I78: =-26310.79 -> -26310.79 | J78: =-J9*$C$78 -> -63958.47 | K78: =-28578.59 -> -28578.59 | L78: =-L9*$C$78 -> -62341.572 | M78: =-3848.17-25508 -> -29356.17 | N78: =-N9*$C$78 -> -59500.286 | O78: =-55223.07 -> -55223.07 | P78: =-P9*$C$78 -> -63320.677 | Q78: =-17505.22 -> -17505.22 | R78: =-R9*$C$78 -> -65413.482 | S78: =-26247.27 -> -26247.27 | T78: =-T9*$C$78 -> -71205.814 | U78: =-16989 -> -16989 | V78: =-V9*$C$78 -> -73451.062 | W78: =-30178.85 -> -30178.85 | X78: =-X9*$C$78 -> -76042.869 | Y78: =-12643.64 -> -12643.64 | Z78: =-Z9*$C$78 -> -77468.862 | AA78: =-17845.63 -> -17845.63 | AB78: =D78+F78+H78+J78+L78+N78+P78+R78+T78+V78+X78+Z78 -> -779809.36 | AC78: =E78+G78+I78+K78+M78+O78+Q78+S78+U78+W78+Y78+AA78 -> -315530.54
B79: Амортизация (ремонт, покупка нового оборудования) | C79: 120000 | D79: 0 | E79: =-4311 -> -4311 | F79: 0 | G79: =-1340 -> -1340 | H79: =-$C$79 -> -120000 | I79: =-28850 -> -28850 | J79: =-$C$79 -> -120000 | K79: =-34750 -> -34750 | L79: =-$C$79 -> -120000 | N79: =-$C$79 -> -120000 | O79: =-5118-9785 -> -14903 | P79: =-$C$79 -> -120000 | Q79: =-2423 -> -2423 | R79: =-$C$79 -> -120000 | S79: 0 | T79: =-$C$79 -> -120000 | U79: 0 | V79: =-$C$79 -> -120000 | W79: 0 | X79: =-$C$79 -> -120000 | Z79: =-$C$79 -> -120000 | AA79: 0 | AB79: =D79+F79+H79+J79+L79+N79+P79+R79+T79+V79+X79+Z79 -> -1200000 | AC79: =E79+G79+I79+K79+M79+O79+Q79+S79+U79+W79+Y79+AA79 -> -86577
B80: ЗП АУП
B81: ЗП топменеджмент (РнП) | C81: ='База расходы зп'!V4 -> 1078167 | D81: =-$C81 -> -1078167 | E81: =-1133974 -> -1133974 | F81: =-$C81 -> -1078167 | G81: =-1070617 -> -1070617 | H81: =-$C81 -> -1078167 | I81: =-SUM('База расходы зп'!G360:H362) -> -1144425 | J81: =-$C81 -> -1078167 | K81: =-1053157 -> -1053157 | L81: =-$C81 -> -1078167 | M81: =-1091475 -> -1091475 | N81: =-$C81 -> -1078167 | O81: =-1083780 -> -1083780 | P81: =-$C81 -> -1078167 | Q81: =-1226260 -> -1226260 | R81: =-$C81 -> -1078167 | S81: =-925677 -> -925677 | T81: =-$C81 -> -1078167 | U81: =-1180912 -> -1180912 | V81: =-$C81 -> -1078167 | W81: =-1489943 -> -1489943 | X81: =-$C81 -> -1078167 | Y81: =-1107837 -> -1107837 | Z81: =-$C81 -> -1078167 | AA81: =-1079392 -> -1079392 | AB81: =D81+F81+H81+J81+L81+N81+P81+R81+T81+V81+X81+Z81 -> -12938004 | AC81: =E81+G81+I81+K81+M81+O81+Q81+S81+U81+W81+Y81+AA81 -> -13587449
B82: Экстратраты топменеджмент (РнП) | C82: 0 | D82: =-$C$82/12 -> 0 | E82: =-$C$82/12 -> 0 | F82: =-$C$82/12 -> 0 | G82: =-$C$82/12 -> 0 | H82: =-$C$82/12 -> 0 | I82: =-$C$82/12 -> 0 | J82: =-$C$82/12 -> 0 | K82: =-$C$82/12 -> 0 | ... AA82: =-$C$82/12 -> 0 | AB82: =D82+F82+H82+J82+L82+N82+P82+R82+T82+V82+X82+Z82 -> 0 | AC82: =E82+G82+I82+K82+M82+O82+Q82+S82+U82+W82+Y82+AA82 -> 0
B83: ЗП административного персонала | C83: ='База расходы зп'!V17+'База расходы зп'!V7+'База расходы зп'!V12 -> 631035.18 | D83: =-$C83 -> -631035.18 | E83: =-728617 -> -728617 | F83: =-$C83 -> -631035.18 | G83: =-647527 -> -647527 | H83: =-$C83 -> -631035.18 | I83: =-SUM('База расходы зп'!G277:H284) -> -557670 | J83: =-$C83 -> -631035.18 | K83: =-980446 -> -980446 | L83: =-$C83 -> -631035.18 | M83: =-634579 -> -634579 | N83: =-$C83 -> -631035.18 | O83: =-494641 -> -494641 | P83: =-$C83 -> -631035.18 | Q83: =-415149 -> -415149 | R83: =-$C83 -> -631035.18 | S83: =-372802 -> -372802 | T83: =-$C83 -> -631035.18 | U83: =-477914 -> -477914 | V83: =-$C83 -> -631035.18 | W83: =-496095 -> -496095 | X83: =-$C83 -> -631035.18 | Y83: =-520250 -> -520250 | Z83: =-$C83 -> -631035.18 | AA83: =-529208 -> -529208 | AB83: =D83+F83+H83+J83+L83+N83+P83+R83+T83+V83+X83+Z83 -> -7572422.2 | AC83: =E83+G83+I83+K83+M83+O83+Q83+S83+U83+W83+Y83+AA83 -> -6854898
B84: Повышения зпл в текущем году | C84: 0 | D84: =D83*$C$84 -> 0 | E84: =E83*$C$84 -> 0 | F84: =F83*$C$84 -> 0 | G84: =G83*$C$84 -> 0 | H84: =H83*$C$84 -> 0 | I84: =I83*$C$84 -> 0 | J84: =J83*$C$84 -> 0 | K84: =K83*$C$84 -> 0 | ... AA84: =AA83*$C$84 -> 0 | AB84: =D84+F84+H84+J84+L84+N84+P84+R84+T84+V84+X84+Z84 -> 0 | AC84: =E84+G84+I84+K84+M84+O84+Q84+S84+U84+W84+Y84+AA84 -> 0
B85: ЗП выплаты | C85: 0 | D85: =-D9*$C$85 -> 0 | E85: =-E9*$C$85 -> 0 | F85: =-F9*$C$85 -> 0 | G85: =-G9*$C$85 -> 0 | H85: =-H9*$C$85 -> 0 | I85: =-I9*$C$85 -> 0 | J85: =-J9*$C$85 -> 0 | K85: =-K9*$C$85 -> 0 | ... AA85: =-AA9*$C$85 -> 0 | AB85: =D85+F85+H85+J85+L85+N85+P85+R85+T85+V85+X85+Z85 -> 0 | AC85: =E85+G85+I85+K85+M85+O85+Q85+S85+U85+W85+Y85+AA85 -> 0
B86: Затраты на персонал
B87: ЗП HR команды | C87: =SUM('База расходы зп'!I13:I14) -> 231877.8 | D87: =-231878 -> -231878 | E87: =-58340-150000 -> -208340 | F87: =-SUM('База расходы зп'!I13:I14) -> -231877.8 | G87: =-70740 -> -70740 | H87: =-$C$87 -> -231877.8 | I87: =-SUM('База расходы зп'!G275:H276) -> -231902.37 | J87: =-$C$87 -> -231877.8 | K87: =-231904 -> -231904 | L87: =-$C$87 -> -231877.8 | M87: =-276725 -> -276725 | N87: =-$C$87 -> -231877.8 | O87: =-323811 -> -323811 | P87: =-$C$87 -> -231877.8 | Q87: =-294514 -> -294514 | R87: =-$C$87 -> -231877.8 | S87: =-360500 -> -360500 | T87: =-$C$87 -> -231877.8 | U87: =-341670 -> -341670 | V87: =-$C$87 -> -231877.8 | W87: =-336420 -> -336420 | X87: =-$C$87 -> -231877.8 | Y87: =-261543 -> -261543 | Z87: =-$C$87 -> -231877.8 | AA87: =-262464 -> -262464 | AB87: =D87+F87+H87+J87+L87+N87+P87+R87+T87+V87+X87+Z87 -> -2782533.8 | AC87: =E87+G87+I87+K87+M87+O87+Q87+S87+U87+W87+Y87+AA87 -> -3200533.4
B88: Повышения зпл в текущем году | C88: 0 | D88: =D87*$C$84 -> 0 | E88: =E87*$C$84 -> 0 | F88: =F87*$C$84 -> 0 | G88: =G87*$C$84 -> 0 | H88: =H87*$C$84 -> 0 | I88: =I87*$C$84 -> 0 | J88: =J87*$C$84 -> 0 | K88: =K87*$C$84 -> 0 | ... AA88: =AA87*$C$84 -> 0 | AB88: =D88+F88+H88+J88+L88+N88+P88+R88+T88+V88+X88+Z88 -> 0 | AC88: =E88+G88+I88+K88+M88+O88+Q88+S88+U88+W88+Y88+AA88 -> 0
B89: ПО организационные HR | C89: ='База расходы'!K25 -> 73313.983 | D89: =-$C89 -> -73313.983 | E89: =-'База расходы'!M25 -> -53182.73 | F89: =-$C89 -> -73313.983 | G89: =-'База расходы'!O25 -> -53987.95 | H89: =-$C89 -> -73313.983 | I89: =-'База расходы'!Q25 -> -54369.34 | J89: =-$C89 -> -73313.983 | K89: =-'База расходы'!S25 -> -86956.67 | L89: =-$C89 -> -73313.983 | M89: =-'База расходы'!U25 -> -56236.67 | N89: =-$C89 -> -73313.983 | O89: =-'База расходы'!W25 -> -53499.67 | P89: =-$C89 -> -73313.983 | Q89: =-'База расходы'!Y25 -> -52852.67 | R89: =-$C89 -> -73313.983 | S89: =-'База расходы'!AA25 -> -275349.44 | T89: =-$C89 -> -73313.983 | U89: =-'База расходы'!AC25 -> -308433.44 | V89: =-$C89 -> -73313.983 | W89: =-'База расходы'!AE25 -> -51404.44 | X89: =-$C89 -> -73313.983 | Y89: =-'База расходы'!AG25 -> -55089.39 | Z89: =-$C89 -> -73313.983 | AA89: =-'База расходы'!AI25 -> -42366.57 | AB89: =D89+F89+H89+J89+L89+N89+P89+R89+T89+V89+X89+Z89 -> -879767.8 | AC89: =E89+G89+I89+K89+M89+O89+Q89+S89+U89+W89+Y89+AA89 -> -1143729
B90: Непредвиденные расходы | C90: 20000 | D90: =-$C90 -> -20000 | E90: 0 | F90: =-$C90 -> -20000 | G90: 0 | H90: =-$C90 -> -20000 | I90: 0 | J90: =-$C90 -> -20000 | L90: =-$C90 -> -20000 | M90: =-60000 -> -60000 | N90: =-$C90 -> -20000 | O90: =-29836.9 -> -29836.9 | P90: =-$C90 -> -20000 | R90: =-$C90 -> -20000 | T90: =-$C90 -> -20000 | V90: =-$C90 -> -20000 | X90: =-$C90 -> -20000 | Z90: =-$C90 -> -20000 | AB90: =D90+F90+H90+J90+L90+N90+P90+R90+T90+V90+X90+Z90 -> -240000 | AC90: =E90+G90+I90+K90+M90+O90+Q90+S90+U90+W90+Y90+AA90 -> -89836.9
B91: Компенсация за использование личного оборудования | G91: =-29000 -> -29000 | I91: 0 | AB91: =D91+F91+H91+J91+L91+N91+P91+R91+T91+V91+X91+Z91 -> 0 | AC91: =E91+G91+I91+K91+M91+O91+Q91+S91+U91+W91+Y91+AA91 -> -29000
B92: Прочие затраты на персонал (корп. расходы) | C92: =-SUM(D92:Z92) -> 2538970.8 | D92: =-55000 -> -55000 | E92: =-2980-25950 -> -28930 | F92: =-95000 -> -95000 | G92: =-59845.1-88593.5-5245-22500 -> -176183.6 | H92: =-55000 -> -55000 | I92: =I93 -> -42683.61 | J92: =-55000 -> -55000 | K92: =-25762.4 -> -25762.4 | L92: =-350000 -> -350000 | M92: =-7892.65 -> -7892.65 | N92: =-55000 -> -55000 | O92: =-55000 -> -55000 | P92: =-55000 -> -55000 | R92: =-55000 -> -55000 | S92: =-17790-3947 -> -21737 | T92: =-55000 -> -55000 | U92: =-4500-22459 -> -26959 | V92: =-55000 -> -55000 | W92: =-18822.5 -> -18822.5 | X92: =-600000 -> -600000 | Z92: =-650000 -> -650000 | AA92: =-150000-30000 -> -180000 | AB92: =D92+F92+H92+J92+L92+N92+P92+R92+T92+V92+X92+Z92 -> -2135000 | AC92: =E92+G92+I92+K92+M92+O92+Q92+S92+U92+W92+Y92+AA92 -> -583970.76
B93: в т.ч. Командировочные расходы | I93: =-10457.71-32225.9 -> -42683.61 | AB93: =D93+F93+H93+J93+L93+N93+P93+R93+T93+V93+X93+Z93 -> 0 | AC93: =E93+G93+I93+K93+M93+O93+Q93+S93+U93+W93+Y93+AA93 -> -42683.61
B94: Обучение | C94: 420000 | D94: 0 | E94: 0 | F94: =-120000 -> -120000 | H94: 0 | I94: -110000 | J94: 0 | K94: =-110000 -> -110000 | L94: =J94 -> 0 | M94: =K94 -> -110000 | N94: =L94 -> 0 | O94: =100000+89900 -> 189900 | P94: =N94 -> 0 | Q94: -100000 | R94: =P94 -> 0 | S94: =Q94 -> -100000 | T94: =R94 -> 0 | U94: =S94 -> -100000 | V94: =T94 -> 0 | W94: =U94 -> -100000 | X94: =V94 -> 0 | Y94: 0 | Z94: =X94 -> 0 | AA94: =Y94 -> 0 | AB94: =D94+F94+H94+J94+L94+N94+P94+R94+T94+V94+X94+Z94 -> -120000 | AC94: =E94+G94+I94+K94+M94+O94+Q94+S94+U94+W94+Y94+AA94 -> -540100
B95: Коммерческие расходы | D95: =SUM(D97:D104) -> -1333854.1 | E95: =SUM(E97:E104) -> -1170411.7 | F95: =SUM(F97:F104) -> -1431557.4 | G95: =SUM(G97:G104) -> -1542829.8 | H95: =SUM(H97:H104) -> -1525693 | I95: =SUM(I97:I104) -> -1117699 | J95: =SUM(J97:J104) -> -1508819.4 | K95: =SUM(K97:K104) -> -1159962.3 | ... AA95: =SUM(AA97:AA104) -> -1044409.3 | AB95: =D95+F95+H95+J95+L95+N95+P95+R95+T95+V95+X95+Z95 -> -18083671 | AC95: =E95+G95+I95+K95+M95+O95+Q95+S95+U95+W95+Y95+AA95 -> -14300231
B96: Продажи | AB96: =D96+F96+H96+J96+L96+N96+P96+R96+T96+V96+X96+Z96 -> 0
B97: ЗП отдела продаж | C97: ='База расходы зп'!V27 -> 501957.69 | D97: =-C97+'База расходы зп'!I28 -> -409026.66 | E97: =-303477 -> -303477 | F97: =D97-'База расходы зп'!I28 -> -501957.69 | G97: =-371992 -> -371992 | H97: =F97 -> -501957.69 | I97: =-550924 -> -550924 | J97: =H97 -> -501957.69 | K97: =-589002 -> -589002 | L97: =J97 -> -501957.69 | M97: =-746878-M99 -> -540015.98 | N97: =L97 -> -501957.69 | O97: =-895282+188633.55 -> -706648.45 | P97: =N97 -> -501957.69 | Q97: =-799391 -> -799391 | R97: =P97 -> -501957.69 | S97: =-551837 -> -551837 | T97: =R97 -> -501957.69 | U97: =-719102 -> -719102 | V97: =T97 -> -501957.69 | W97: =-774429 -> -774429 | X97: =V97 -> -501957.69 | Y97: =-699530 -> -699530 | Z97: =X97 -> -501957.69 | AA97: =-724529 -> -724529 | AB97: =D97+F97+H97+J97+L97+N97+P97+R97+T97+V97+X97+Z97 -> -5930561.2 | AC97: =E97+G97+I97+K97+M97+O97+Q97+S97+U97+W97+Y97+AA97 -> -7330877.4
B98: Повышения зпл в текущем году | C98: 0 | D98: =D97*$C$84 -> 0 | E98: =E97*$C$84 -> 0 | F98: =F97*$C$84 -> 0 | G98: =G97*$C$84 -> 0 | H98: =H97*$C$84 -> 0 | I98: =I97*$C$84 -> 0 | J98: =J97*$C$84 -> 0 | K98: =K97*$C$84 -> 0 | ... AA98: =AA97*$C$84 -> 0 | AB98: =D98+F98+H98+J98+L98+N98+P98+R98+T98+V98+X98+Z98 -> 0 | AC98: =E98+G98+I98+K98+M98+O98+Q98+S98+U98+W98+Y98+AA98 -> 0
B99: Бонусы отдела продаж | C99: 0.011 | D99: =-$C$99*D9 -> -136652.05 | E99: =-154756.6 -> -154756.6 | F99: =-$C$99*F9 -> -138934.4 | G99: =-284196.51 -> -284196.51 | H99: =-$C$99*H9 -> -183955.78 | I99: 0 | J99: =-$C$99*J9 -> -175885.79 | K99: =-233712.74+50000 -> -183712.74 | L99: =-$C$99*L9 -> -171439.32 | M99: =-166948-39914.02 -> -206862.02 | N99: =-$C$99*N9 -> -163625.79 | O99: =-188633.55 -> -188633.55 | P99: =-$C$99*P9 -> -174131.86 | R99: =-$C$99*R9 -> -179887.07 | T99: =-$C$99*T9 -> -195815.99 | V99: =-$C$99*V9 -> -201990.42 | X99: =-$C$99*X9 -> -209117.89 | Z99: =-$C$99*Z9 -> -213039.37 | AB99: =D99+F99+H99+J99+L99+N99+P99+R99+T99+V99+X99+Z99 -> -2144475.7 | AC99: =E99+G99+I99+K99+M99+O99+Q99+S99+U99+W99+Y99+AA99 -> -1018161.4
B100: Сервисы отдела продаж | C100: ='База расходы'!K33 -> 39437.683 | D100: =-C100 -> -39437.683 | E100: =-'База расходы'!M33 -> -12061.66 | F100: =D100 -> -39437.683 | G100: =-'База расходы'!O33 -> -11288.94 | H100: =F100 -> -39437.683 | I100: =-'База расходы'!Q33 -> -13414.97 | J100: =H100 -> -39437.683 | K100: =-'База расходы'!S33 -> -13389.71 | L100: =J100 -> -39437.683 | M100: =-'База расходы'!U33 -> -20127.48 | N100: =L100 -> -39437.683 | O100: =-'База расходы'!W33 -> -48356.26 | P100: =N100 -> -39437.683 | Q100: =-'База расходы'!Y33 -> -10401.33 | R100: =P100 -> -39437.683 | S100: =-'База расходы'!AA33 -> -23299.64 | T100: =R100 -> -39437.683 | U100: =-'База расходы'!AC33 -> -10468.21 | V100: =T100 -> -39437.683 | W100: =-'База расходы'!AE33 -> -11370.08 | X100: =V100 -> -39437.683 | Y100: =-'База расходы'!AG33 -> -7579.0614 | Z100: =X100 -> -39437.683 | AA100: =-'База расходы'!AI33 -> -7249.0114 | AB100: =D100+F100+H100+J100+L100+N100+P100+R100+T100+V100+X100+Z100 -> -473252.2 | AC100: =E100+G100+I100+K100+M100+O100+Q100+S100+U100+W100+Y100+AA100 -> -189006.35
B101: Маркетинг
B102: ЗП маркетинга | C102: ='База расходы зп'!V20 -> 753186.29 | D102: =-C102+'База расходы зп'!I20 -> -579628.29 | E102: =-602134 -> -602134 | F102: =D102 -> -579628.29 | G102: =-777845 -> -777845 | H102: =F102 -> -579628.29 | I102: =-SUM('База расходы зп'!G351:H353) -> -369210.73 | J102: =H102 -> -579628.29 | K102: =-198352-50000 -> -248352 | L102: =J102 -> -579628.29 | M102: =-327718 -> -327718 | N102: =L102 -> -579628.29 | O102: =-267276 -> -267276 | P102: =N102 -> -579628.29 | Q102: =-512849 -> -512849 | R102: =P102 -> -579628.29 | S102: =-295871 -> -295871 | T102: =R102 -> -579628.29 | U102: =-183568 -> -183568 | V102: =T102 -> -579628.29 | W102: =-193735 -> -193735 | X102: =V102 -> -579628.29 | Y102: =-228939 -> -228939 | Z102: =X102 -> -579628.29 | AA102: =-229612 -> -229612 | AB102: =D102+F102+H102+J102+L102+N102+P102+R102+T102+V102+X102+Z102 -> -6955539.4 | AC102: =E102+G102+I102+K102+M102+O102+Q102+S102+U102+W102+Y102+AA102 -> -4237109.7
B103: Реклама, продвижение | C103: 0.012 | D103: =-C103*D9 -> -149074.96 | E103: =-'База расходы'!M42+'База расходы'!L42 -> -92286.41 | F103: =-$C$103*F9 -> -151564.81 | G103: =-'База расходы'!O42 -> -97507.4 | H103: =-$C$103*H9 -> -200679.03 | I103: =-'База расходы'!Q42 -> -184149.33 | J103: =-$C$103*J9 -> -191875.41 | K103: =-'База расходы'!S42 -> -125505.85 | L103: =-$C$103*L9 -> -187024.72 | M103: =-'База расходы'!U42 -> -106595.61 | N103: =-$C$103*N9 -> -178500.86 | O103: =-'База расходы'!W42 -> -112481.96 | P103: =-$C$103*P9 -> -189962.03 | Q103: =-'База расходы'!Y42 -> -167727.54 | R103: =-$C$103*R9 -> -196240.44 | S103: =-'База расходы'!AA42 -> -227290.68 | T103: =-$C$103*T9 -> -213617.44 | U103: =-'База расходы'!AC42 -> -103265.17 | V103: =-$C$103*V9 -> -220353.19 | W103: =-'База расходы'!AE42 -> -103132.99 | X103: =-$C$103*X9 -> -228128.61 | Y103: =-'База расходы'!AG42 -> -116417.95 | Z103: =-$C$103*Z9 -> -232406.59 | AA103: =-'База расходы'!AI42 -> -83019.31 | AB103: =D103+F103+H103+J103+L103+N103+P103+R103+T103+V103+X103+Z103 -> -2339428.1 | AC103: =E103+G103+I103+K103+M103+O103+Q103+S103+U103+W103+Y103+AA103 -> -1519380.2
B104: Сервисы маркетинг, в т.ч. ГПХ | C104: =SUM('База расходы'!G42:G43) -> 20034.5 | D104: =-C104 -> -20034.5 | E104: =-'База расходы'!L42 -> -5696.01 | F104: =D104 -> -20034.5 | G104: 0 | H104: =F104 -> -20034.5 | I104: 0 | J104: =H104 -> -20034.5 | K104: =I104 -> 0 | L104: =J104 -> -20034.5 | M104: =K104 -> 0 | N104: =L104 -> -20034.5 | O104: =M104 -> 0 | P104: =N104 -> -20034.5 | Q104: =O104 -> 0 | ... AA104: =Y104 -> 0 | AB104: =D104+F104+H104+J104+L104+N104+P104+R104+T104+V104+X104+Z104 -> -240414 | AC104: =E104+G104+I104+K104+M104+O104+Q104+S104+U104+W104+Y104+AA104 -> -5696.01
B105: Операционная прибыль(EBITDA) | D105: =D70+D73 -> 1737405.2 | E105: =E70+E73 -> -677610.25 | F105: =F70+F73 -> 1599139.3 | G105: =G70+G73 -> 554260.72 | H105: =H70+H73 -> 5577611.4 | I105: =I70+I73 -> -112883.39 | J105: =J70+J73 -> 4863784.2 | K105: =K70+K73 -> 264887.91 | ... AC105: =AC70+AC73 -> 8607738.7
B106: Рентабельность по Операционной прибыли,%% | D106: =D105/D9 -> 0.13985489 | E106: =E105/E9 -> -0.07033565 | F106: =F105/F9 -> 0.12661034 | G106: =G105/G9 -> 0.04822738 | H106: =H105/H9 -> 0.33352431 | I106: =I105/I9 -> -0.010455103 | J106: =J105/J9 -> 0.3041839 | K106: =K105/K9 -> 0.022949194 | ... AC106: =AC105/AC9 -> 0.062023819
...

Sheet Юнит ЕМС 
B1: Юр.лицо | C1: Клиент | D1: ЯНВАРЬ | G1: ФЕВРАЛЬ
B2: ТЕКУЩИЙ ПОРТФЕЛЬ ЕМС | C2: Проекты-текущий портфель EMS | D2: ФАКТ | E2: ПУЛ | F2: менеджер | G2: ФАКТ | H2: ПУЛ | I2: менеджер
A3: 1 | B3: 1-Й КРАСНОГВАРДЕЙСКИЙ ООО СЗ | C3: Сумма Элементов | D3: 20600 | G3: 27300 | H3: 5 | I3: Юмакулова Аида
A4: =A3+1 -> 2 | B4: ЮНИСЕНДЕР СМАРТ ООО | C4: RD Electronics | D4: 1452689 | G4: 332394.78 | H4: 5 | I4: Юмакулова Аида
A5: =A4+1 -> 3 | B5: А101 | D5: 51600 | G5: 51600 | H5: 5 | I5: Аблов Андрей
A6: =A5+1 -> 4 | B6: АО ЦВ ПРОТЕК | C6: Здравсити | D6: 10310 | G6: 98186 | H6: 1 | I6: Паршакина Ольга
A7: =A6+1 -> 5 | B7: АРТИС 21 ООО | C7: Artis21 | D7: 77047.619 | G7: 80900 | H7: 5 | I7: Боровова Дарья
A8: =A7+1 -> 6 | B8: БОРИСХОФ 1 ООО | C8: БорисХоф
A9: =A8+1 -> 7 | B9: БОРИСХОФ Т ООО
A10: =A9+1 -> 8 | B10: БОРИСХОФ ХОЛДИНГ ООО | C10: БорисХоф | D10: 63200 | G10: 46200 | H10: 1 | I10: Швецов Никита
A11: =A10+1 -> 9 | B11: БРОНИРОВАНИЕ ГОСТИНИЦ ООО | C11: Ostrovok | D11: 121050 | G11: 313450 | H11: 1 | I11: Радецкая Лика
A12: =A11+1 -> 10 | B12: БУРГЕР РУС ООО | C12: Бургеркинг | D12: 173500 | G12: 182600 | H12: 1 | I12: Радецкая Лика
A13: =A12+1 -> 11 | B13: ГК СБСВ-КЛЮЧАВТО ООО | C13: Keyauto | D13: 117642 | G13: 152208 | H13: 1 | I13: Паршакина Ольга
A14: =A13+1 -> 12 | B14: ДЖ.Т.И. РОССИЯ ООО | C14: JTI RMC | D14: 364902 | G14: 372524 | H14: 1 | I14: Еремин Михаил
A15: =A14+1 -> 13 | B15: ДИОНА ООО | C15: Внуково | D15: 166800 | G15: 147400 | H15: 1 | I15: Давтян Инга
A16: =A15+1 -> 14 | B16: ЕАПТЕКА ООО | C16: ЕАптека | H16: 1
A17: =A16+1 -> 15 | B17: ЕВРОПА ООО/ЭТНЕ ООО | C17: Vnukovo Outlet Village | D17: 244400 | G17: 244400 | H17: 1 | I17: Давтян Инга
A18: =A17+1 -> 16 | B18: ИМПУЛЬС ООО | C18: Amazing Red | D18: 327680 | G18: 314870.48 | H18: 5 | I18: Потковский Иван
A19: =A18+1 -> 17 | B19: ИНСТАМАРТ СЕРВИС ООО | C19: Сбермаркет ВнутриКом | D19: 211175 | G19: 236560 | H19: 5 | I19: Боровова Дарья
A20: =A18+1 -> 17 | B20: ИП Абдулин | C20: VK | D20: 11429 | H20: 5
A21: =A19+1 -> 18 | B21: ИП Суходоев | C21: Profmax | D21: 134400 | G21: 91200 | H21: 1 | I21: Радецкая Лика
A22: =A21+1 -> 19 | B22: КАЗАНЬ РЕАЛ ЭСТЕЙТ ООО | C22: Benetton | D22: 1033029.2 | G22: 891469.01 | H22: 1 | I22: Логвинова Уэзер
A23: =A22+1 -> 20 | B23: КАПИТАЛ ГРУП ООО | C23: Capital group | D23: 98150 | G23: 103057.5 | H23: 5 | I23: Потковский Иван
A24: =A23+1 -> 21 | B24: КАРШЕРИНГ РУССИЯ ПАО | C24: Делимобиль | D24: 72325 | G24: 126525 | H24: 5 | I24: Юмакулова Аида
A25: =A24+1 -> 22 | B25: КИНОПОИСК ООО | C25: Яндекс | D25: 203000 | G25: 248700 | H25: 5 | I25: Новикова Екатерина
A26: =A25+1 -> 23 | B26: КНАУФ ГИПС ООО | C26: Knauf | G26: 27360 | H26: 1 | I26: Гутина Юля
A27: =A26+1 -> 24 | B27: КОЛЕСА ДАРОМ.РУ ООО | C27: Колёса Даром | D27: 285714.29 | G27: 285714.29 | H27: 5 | I27: Новикова Екатерина
A28: =A27+1 -> 25 | B28: КОНДИТЕРСКАЯ ФАБРИКА ПОБЕДА ООО | C28: Победа Вкуса | D28: 114875 | G28: 114875 | H28: 1 | I28: Гутина Юля
A29: =A28+1 -> 26 | B29: КРАСНАЯ ПОЛЯНА НАО | C29: Красная поляна | D29: 82998.038 | G29: 234952.44 | H29: 1 | I29: Гутина Юля
A30: =A29+1 -> 27 | B30: Л'ОРЕАЛЬ АО | C30: CDMO | D30: 42565.333 | G30: 42565.333 | H30: 1 | I30: Андреева Валентина
A31: =A30+1 -> 28 | B31: Майндбокс ООО | C31: Mindbox | D31: 111254.67 | G31: 166070 | H31: 1 | I31: Гутина Юля
A32: =A31+1 -> 29 | B32: МАРС ООО | C32: Марс - комплексный проект, подписание доков, команда (Давтян, Ерёмин) | D32: 1006325
A33: =A32+1 -> 30 | C33: Экосистема | H33: 5 | I33: Соболевский Сергей
A34: =A33+1 -> 31 | B34: РУСКАН АО | C34: Royal Canin | G34: 571650 | H34: 1 | I34: Давтян Инга
A35: =A34+1 -> 32 | C35: Kinpet | G35: 563246.25 | H35: 1 | I35: Андреева Валентина
A36: =A35+1 -> 33 | C36: Любимчик | H36: 5 | I36: Потковский Иван
A37: =A36+1 -> 34 | B37: МЕТРО КЭШ ЭНД КЕРРИ ООО | C37: Metro | D37: 49982 | F37: Страхов Никита | H37: 5 | I37: Страхов Никита
A38: =A37+1 -> 35 | B38: МОСКВИЧ АО МАЗ | D38: 400000 | G38: 533000 | H38: 1 | I38: Швецов Никита
A39: =A38+1 -> 36 | B39: Мосурбанфорум
A40: =A39+1 -> 37 | B40: МУСА МОТОРС ДЖЕЙ ЭЛ ЭР ООО | C40: БорисХоф
A41: =A40+1 -> 38 | B41: ОККАМ ИКС ООО | C41: Алроса | D41: 68750 | G41: 72250 | H41: 1 | I41: Гутина Юля
A42: =A41+1 -> 39 | B42: ООО «ДЖИЭФЭН КЛАУД ИНТЕРНЕТ СЕРВИСИС» | C42: GFN | D42: 21440 | G42: 65840 | H42: 5 | I42: Волков Александр
A43: =A42+1 -> 40 | B43: ООО "Корзинка-6" | C43: Правильная Корзинка | H43: 1 | I43: Потковский Иван
A44: =A43+1 -> 41 | B44: ООО «СПАДРИМ» | C44: SpaDream | D44: 71300 | G44: 119000 | H44: 5 | I44: Боровова Дарья
A45: =A44+1 -> 42 | B45: ПЕТРОВАКС ФАРМ ООО | C45: Петровакс Фарм | D45: 513000 | G45: 516900 | H45: 5 | I45: Тараскин Алексей
A46: =A45+1 -> 43 | B46: ПРЕМИУМ ЭСТЕЙТ ООО | C46: Level | D46: 140747.62 | G46: 319648.1 | H46: 1 | I46: Паршакина Ольга
A47: =A46+1 -> 44 | B47: ПРОФИТАТОР ООО | C47: Кокос | H47: 1
A48: =A47+1 -> 45 | B48: Публичное акционерное общество "ПИК - специализированный застройщик" | C48: Пик | G48: 17825 | H48: 1 | I48: Радецкая Лика
A49: =A48+1 -> 46 | B49: ПУЛЬС ООО СК | C49: СК Пульс | H49: 5
A50: =A49+1 -> 47 | B50: ПРОГРЕСС ГРУПП ООО | C50: NBB | D50: 27000 | F50: Соболевский Сергей | H50: 5 | I50: Соболевский Сергей
A51: =A50+1 -> 48 | B51: РОКВУЛ ООО | D51: 82302 | G51: 95348 | H51: 1 | I51: Паршакина Ольга
A52: =A51+1 -> 49 | B52: РУТА АО | C52: labquest.ru | D52: 248600 | G52: 286800 | H52: 1 | I52: Еремин Михаил
A53: =A52+1 -> 50 | B53: Пионе | C53: Пионер | D53: 167365 | G53: 197684 | H53: 1 | I53: Паршакина Ольга
A54: =A53+1 -> 51 | B54: ТЕХНОНИКОЛЬ-СТРОИТЕЛЬНЫЕ СИСТЕМЫ ООО | C54: Технониколь | G54: 114300 | H54: 5 | I54: Миронова Алина
A55: =A54+1 -> 52 | B55: ФГБУК "Государственный академический Большой театр России" | C55: Большой театр | D55: 18975 | G55: 21086.667 | H55: 5 | I55: Аблов Андрей
A56: =A55+1 -> 53 | B56: ФЕРСТ ДАТА ООО | C56: Beko, Indesit, Grundig, Hotpoint | H56: 5
A57: =A56+1 -> 54 | B57: ХЕНДЭ МОТОР СНГ ООО | C57: Hyundai | D57: 15100 | G57: 62440 | H57: 1 | I57: Швецов Никита
A58: =A57+1 -> 55 | B58: Циммер Евгения Владимировна | C58: аврора 24 | H58: 5
A59: =A58+1 -> 56 | B59: ЯНДЕКС МУЗЫКА ООО | C59: Яндекс | D59: 54500 | G59: 92400 | H59: 5 | I59: Новикова Екатерина
B60: НОВЫЕ ПРОЕКТЫ
A61: 1 | B61: Лаборатория касперского | C61: Лаборатория касперского
A62: 2 | B62: ЛИДЕРЫ МНЕНИЙ ООО | G62: 76800 | I62: Семикин Сережа
A63: =A62+1 -> 3 | B63: ООО "Лидер" | C63: Эпл Даймонд | D63: 23000 | G63: 100000 | H63: 5 | I63: Новикова Екатерина
B67: ФЕВРАЛЬ
B68: Итого платящих проектов | G68: =COUNT(G3:G63) -> 43
B69: Итого сумма выручки по актам | G69: =SUM(G3:G63)-G62 -> 8682499.8
B70: Итого проектов в уе | G70: =G69/200000 -> 43.412499
B71: Итого выручка 1 пул | G71: 5845351
B72: Итого проектов в уе 1 пул | G72: =G71/200000 -> 29.226755
B73: Итого выручка 5 пул | G73: 2837149
B74: Итого проектов в уе 5 пул | G74: =G73/200000 -> 14.185745
B77: ПУЛ 5-Соболевский Сергей | D77: Выручка | E77: пул | F77: ФИ | I77: ФИО | J77: грейд | K77: выручка план | L77: выручка факт | M77: кол-во проектов план | N77: кол-во проектов факт
B78: 1-Й КРАСНОГВАРДЕЙСКИЙ ООО СЗ | C78: Сумма Элементов | D78: 27300 | E78: 5 | F78: Юмакулова Аида | I78: =F80 -> Аблов Андрей | L78: =D92+D80 -> 72686.667 | N78: =L78/200000 -> 0.36343333
B79: ЮНИСЕНДЕР СМАРТ ООО | C79: RD Electronics | D79: 332394.78 | E79: 5 | F79: Юмакулова Аида | I79: =F82 -> Потковский Иван | J79: миддл | K79: 800000 | L79: =D82+D84 -> 417927.98 | M79: =K79/200000 -> 4 | N79: =L79/200000 -> 2.0896399
B80: А101 | D80: 51600 | E80: 5 | F80: Аблов Андрей | I80: =F90 -> Тараскин Алексей | J80: миддл | K80: 800000 | L80: =D90 -> 516900 | M80: =K80/200000 -> 4 | N80: =L80/200000 -> 2.5845
B81: АРТИС 21 ООО | C81: Artis21 | D81: 80900 | E81: 5 | F81: Боровова Дарья | I81: =F88 -> Волков Александр | L81: =D88 -> 65840 | N81: =L81/200000 -> 0.3292
B82: ИМПУЛЬС ООО | C82: Amazing Red | D82: 314870.48 | E82: 5 | F82: Потковский Иван | I82: =F86 -> Новикова Екатерина | J82: джун | K82: 600000 | L82: =D93+D94+D86+D87 -> 726814.29 | M82: =K82/200000 -> 3 | N82: =L82/200000 -> 3.6340714
B83: ИНСТАМАРТ СЕРВИС ООО | C83: Сбермаркет ВнутриКом | D83: 236560 | E83: 5 | F83: Боровова Дарья | I83: =F85 -> Юмакулова Аида | J83: джун | K83: 600000 | L83: =D78+D79+D85 -> 486219.78 | M83: =K83/200000 -> 3 | N83: =L83/200000 -> 2.4310989
B84: КАПИТАЛ ГРУП ООО | C84: Capital group | D84: 103057.5 | E84: 5 | F84: Потковский Иван | I84: =F81 -> Боровова Дарья | J84: джун | K84: 600000 | L84: =D81+D89+D83 -> 436460 | M84: =K84/200000 -> 3 | N84: =L84/200000 -> 2.1823
B85: КАРШЕРИНГ РУССИЯ ПАО | C85: Делимобиль | D85: 126525 | E85: 5 | F85: Юмакулова Аида | I85: =F91 -> Миронова Алина | J85: джун | K85: 600000 | L85: =D91 -> 114300 | M85: =K85/200000 -> 3 | N85: =L85/200000 -> 0.5715
B86: КИНОПОИСК ООО | C86: Яндекс | D86: 248700 | E86: 5 | F86: Новикова Екатерина
B87: КОЛЕСА ДАРОМ.РУ ООО | C87: Колёса Даром | D87: 285714.29 | E87: 5 | F87: Новикова Екатерина
B88: ООО «ДЖИЭФЭН КЛАУД ИНТЕРНЕТ СЕРВИСИС» | C88: GFN | D88: 65840 | E88: 5 | F88: Волков Александр
B89: ООО «СПАДРИМ» | C89: SpaDream | D89: 119000 | E89: 5 | F89: Боровова Дарья
B90: ПЕТРОВАКС ФАРМ ООО | C90: Петровакс Фарм | D90: 516900 | E90: 5 | F90: Тараскин Алексей
B91: ТЕХНОНИКОЛЬ-СТРОИТЕЛЬНЫЕ СИСТЕМЫ ООО | C91: Технониколь | D91: 114300 | E91: 5 | F91: Миронова Алина
B92: ФГБУК "Государственный академический Большой театр России" | C92: Большой театр | D92: 21086.667 | E92: 5 | F92: Аблов Андрей
B93: ЯНДЕКС МУЗЫКА ООО | C93: Яндекс | D93: 92400 | E93: 5 | F93: Новикова Екатерина
B94: ООО "Лидер" | C94: Эпл Даймонд | D94: 100000 | E94: 5 | F94: Новикова Екатерина
B95: ИТОГО ВЫРУЧКА/ кол-во менеджеров | D95: =SUBTOTAL(9,D78:D94) -> 2837148.7 | F95: 6 | I95: 6 | K95: =SUBTOTAL(9,K78:K94) -> 4000000 | L95: =SUBTOTAL(9,L78:L94) -> 2837148.7 | M95: =SUBTOTAL(9,M78:M94) -> 20 | N95: =SUBTOTAL(9,N78:N94) -> 14.185744
B96: Итого проектов/ проектов на 1 менеджера | D96: =D95/200000 -> 14.185744 | F96: =D96/F95 -> 2.3642906 | N96: =N95/I95 -> 2.3642906
B98: ПУЛ1- Страхов Никита | D98: Выручка | E98: пул | F98: ФИ | I98: ФИО | J98: грейд | K98: выручка план | L98: выручка факт | M98: кол-во проектов план | N98: кол-во проектов факт
B99: АО ЦВ ПРОТЕК | C99: Здравсити | D99: 98186 | E99: 1 | F99: Паршакина Ольга | I99: =F116 -> Швецов Никита | J99: сеньор | K99: 800000 | L99: =D123+D116+D100 -> 641640 | M99: =K99/200000 -> 4 | N99: =L99/200000 -> 3.2082
B100: БОРИСХОФ ХОЛДИНГ ООО | C100: БорисХоф | D100: 46200 | E100: 1 | F100: Швецов Никита | I100: =F112 -> Андреева Валентина | J100: миддл | K100: 800000 | L100: =D112+D115 -> 605811.58 | M100: =K100/200000 -> 4 | N100: =L100/200000 -> 3.0290579
B101: БРОНИРОВАНИЕ ГОСТИНИЦ ООО | C101: Ostrovok | D101: 313450 | E101: 1 | F101: Радецкая Лика | I101: =F105 -> Давтян Инга | J101: миддл | K101: 800000 | L101: =D105+D106+D114 -> 963450 | M101: =K101/200000 -> 4 | N101: =L101/200000 -> 4.81725
B102: БУРГЕР РУС ООО | C102: Бургеркинг | D102: 182600 | E102: 1 | F102: Радецкая Лика | I102: =F104 -> Еремин Михаил | J102: миддл | K102: 800000 | L102: =D104+D121 -> 659324 | M102: =K102/200000 -> 4 | N102: =L102/200000 -> 3.29662
B103: ГК СБСВ-КЛЮЧАВТО ООО | C103: Keyauto | D103: 152208 | E103: 1 | F103: Паршакина Ольга | I103: =F103 -> Паршакина Ольга | J103: миддл | K103: 800000 | L103: =D99+D103+D118+D120+D122 -> 863074.1 | M103: =K103/200000 -> 4 | N103: =L103/200000 -> 4.3153705
B104: ДЖ.Т.И. РОССИЯ ООО | C104: JTI RMC | D104: 372524 | E104: 1 | F104: Еремин Михаил | I104: =F108 -> Логвинова Уэзер | J104: джун | K104: 600000 | L104: =D108 -> 891469.01 | M104: =K104/200000 -> 3 | N104: =L104/200000 -> 4.457345
B105: ДИОНА ООО | C105: Внуково | D105: 147400 | E105: 1 | F105: Давтян Инга | I105: =F109 -> Гутина Юля | J105: джун | K105: 600000 | L105: =D109+D110+D111+D113+D117 -> 615507.44 | M105: =K105/200000 -> 3 | N105: =L105/200000 -> 3.0775372
B106: ЕВРОПА ООО/ЭТНЕ ООО | C106: Vnukovo Outlet Village | D106: 244400 | E106: 1 | F106: Давтян Инга | I106: =F119 -> Радецкая Лика | J106: джун | K106: 600000 | L106: =D101+D102+D107+D119 -> 605075 | M106: =K106/200000 -> 3 | N106: =L106/200000 -> 3.025375
...

Sheet БЛОК-ВЫРУЧКА
B1: Юр.лицо | C1: Клиент | E1: 6 мес | F1: 0.97 | I1: 0.97 | N1: 1.05 | P1: 1.08 | R1: 1.01 | T1: 0.93 | V1: 0.97 | Y1: 0.99 | AB1: 1.11 | AD1: 1.14 | AF1: 1.17 | AH1: 1.19
B2: ТЕКУЩИЙ ПОРТФЕЛЬ ЕМС | C2: Проекты-текущий портфель EMS | D2: ПУЛ | E2: план-среднемесячн. значение | F2: ПЛАН | G2: ФАКТ | I2: ПЛАН | J2: план в менеджерской таблице | L2: ФАКТ | M2: ПУЛ | N2: ПЛАН | O2: ФАКТ | P2: ПЛАН | Q2: ФАКТ | R2: ПЛАН | S2: ФАКТ | T2: ПЛАН | U2: ФАКТ | V2: ПЛАН | W2: ФАКТ | X2: ндс с выручки | Y2: ПЛАН | Z2: ФАКТ | AA2: ндс с выручки | AB2: ПЛАН | AC2: ФАКТ | AD2: ПЛАН | AE2: ФАКТ | AF2: ПЛАН | AG2: ФАКТ | AH2: ПЛАН | AI2: ФАКТ
F3: ЯНВАРЬ | I3: ФЕВРАЛЬ | N3: МАРТ | P3: АПРЕЛЬ | R3: МАЙ | T3: ИЮНЬ | V3: ИЮЛЬ | Y3: АВГУСТ | AB3: СЕНТЯБРЬ | AD3: ОКТЯБРЬ | AF3: НОЯБРЬ | AH3: ДЕКАБРЬ
A4: 1 | B4: 1-Й КРАСНОГВАРДЕЙСКИЙ ООО СЗ | C4: Сумма Элементов | E4: 42806.5 | F4: =E4*$F$1 -> 41522.305 | G4: =VLOOKUP(B4,[1]Лист_1!$A$1:$G$65536,7,0) -> 20600 | H4: =G4-F4 -> -20922.305 | I4: =E4*$I$1 -> 41522.305 | J4: 20600 | K4: =J4-I4 -> -20922.305 | L4: 27300 | N4: =E4*P1 -> 46231.02 | O4: 20600 | P4: =E4*$P$1 -> 46231.02 | Q4: 20600 | R4: =G4*$P$1 -> 22248 | S4: =VLOOKUP(B4,[2]Лист_1!$A$1:$C$65536,3,0) -> 20600 | T4: =I4*$T$1 -> 38615.744 | U4: 41200 | V4: =E4*$V$1 -> 41522.305 | W4: =VLOOKUP(B4,[3]Лист_1!$A$5:$F$55,4,0) -> 20600 | X4: =VLOOKUP(B4,[3]Лист_1!$A$5:$D$54,3,0) -> 1030 | Y4: =E4*$Y$1 -> 42378.435 | AB4: =E4*$AB$1 -> 47515.215 | AC4: 41200 | AD4: =E4*$AD$1 -> 48799.41 | AE4: =VLOOKUP(B4,[4]Лист_1!$A$5:$D$59,3,0) -> 20600 | AF4: =E4*$AF$1 -> 50083.605 | AG4: =VLOOKUP(B4,[5]Лист_1!$A$3:$C$50,3,0) -> 20600 | AH4: =G4*$AF$1 -> 24102 | AI4: =VLOOKUP(B4,[29]Лист_1!$A$5:$C$67,3,0) -> 20600
A5: =A4+1 -> 2 | B5: ЮНИСЕНДЕР СМАРТ ООО | C5: RD Electronics | D5: 5 | E5: 616827.86 | F5: =E5*$F$1 -> 598323.02 | G5: 1452689 | H5: =G5-F5 -> 854365.98 | I5: =E5*$I$1 -> 598323.02 | J5: 580000 | K5: =J5-I5 -> -18323.024 | L5: 332394.78 | N5: =E5*$N$1 -> 647669.25 | O5: 637722.33 | P5: =E5*$P$1 -> 666174.09 | Q5: 580627.81 | R5: =G5*$P$1 -> 1568904.1 | S5: =VLOOKUP(B5,[2]Лист_1!$A$1:$C$65536,3,0)+100000 -> 519672.94 | T5: =I5*$T$1 -> 556440.41 | U5: 365797.22 | V5: =E5*$V$1 -> 598323.02 | W5: =VLOOKUP(B5,[3]Лист_1!$A$5:$F$55,4,0) -> 515089.51 | X5: 25754.47 | Y5: =E5*$Y$1 -> 610659.58 | Z5: =VLOOKUP(B5,[6]Лист_1!$C$5:$E$64,3,0) -> 473226.97 | AB5: =E5*$AB$1 -> 684678.92 | AC5: 377158.32 | AD5: =E5*$AD$1 -> 703183.76 | AE5: =VLOOKUP(B5,[4]Лист_1!$A$5:$D$59,3,0) -> 715300.96 | AF5: =E5*$AF$1 -> 721688.6 | AG5: =VLOOKUP(B5,[5]Лист_1!$A$3:$C$50,3,0) -> 521234.77 | AH5: =G5*$AF$1 -> 1699646.1 | AI5: =VLOOKUP(B5,[29]Лист_1!$A$5:$C$67,3,0) -> 525939.36
A6: =A5+1 -> 3 | B6: А101 | D6: 5 | E6: 32390 | F6: =E6*$F$1 -> 31418.3 | G6: 51600 | H6: =G6-F6 -> 20181.7 | I6: =E6*$I$1 -> 31418.3 | J6: 130000 | K6: =J6-I6 -> 98581.7 | L6: 51600 | N6: =E6*$N$1 -> 34009.5 | P6: =E6*$P$1 -> 34981.2 | T6: =I6*$T$1 -> 29219.019 | V6: =E6*$V$1 -> 31418.3 | Y6: =E6*$Y$1 -> 32066.1 | Z6: 185800 | AB6: =E6*$AB$1 -> 35952.9 | AD6: =E6*$AD$1 -> 36924.6 | AE6: 51600 | AF6: =E6*$AF$1 -> 37896.3 | AG6: 38700 | AH6: =G6*$AF$1 -> 60372 | AI6: 51600
A7: =A6+1 -> 4 | B7: АО ЦВ ПРОТЕК | C7: Здравсити | D7: 1 | E7: 80764.833 | F7: =E7*$F$1 -> 78341.888 | G7: =VLOOKUP(B7,[1]Лист_1!$A$1:$G$65536,7,0) -> 10310 | H7: =G7-F7 -> -68031.888 | I7: =E7*$I$1 -> 78341.888 | J7: 30000 | K7: =J7-I7 -> -48341.888 | L7: 98186 | N7: =E7*$N$1 -> 84803.075 | O7: 192204 | P7: =E7*$P$1 -> 87226.02 | Q7: 218911 | R7: =G7*$P$1 -> 11134.8 | S7: =VLOOKUP(B7,[2]Лист_1!$A$1:$C$65536,3,0) -> 219047 | T7: =I7*$T$1 -> 72857.956 | U7: 142012 | V7: =E7*$V$1 -> 78341.888 | W7: =VLOOKUP(B7,[3]Лист_1!$A$5:$F$55,4,0) -> 220154 | X7: =VLOOKUP(B7,[3]Лист_1!$A$5:$D$54,3,0) -> 11007.7 | Y7: =E7*$Y$1 -> 79957.185 | Z7: =VLOOKUP(B7,[6]Лист_1!$C$5:$E$64,3,0) -> 18550 | AB7: =E7*$AB$1 -> 89648.965 | AD7: =E7*$AD$1 -> 92071.91
A8: =A7+1 -> 5 | B8: АРТИС 21 ООО | C8: Artis21 | D8: 5 | E8: 84041.667 | F8: =E8*$F$1 -> 81520.417 | G8: =VLOOKUP(B8,[1]Лист_1!$A$1:$G$65536,7,0) -> 77047.619 | H8: =G8-F8 -> -4472.7976 | I8: =E8*$I$1 -> 81520.417 | J8: 69400 | K8: =J8-I8 -> -12120.417 | L8: 80900 | N8: =E8*$N$1 -> 88243.75 | O8: 67950 | P8: =E8*$P$1 -> 90765 | Q8: 110350 | R8: =G8*$P$1 -> 83211.429 | S8: =VLOOKUP(B8,[2]Лист_1!$A$1:$C$65536,3,0) -> 110350 | T8: =I8*$T$1 -> 75813.988 | Z8: =VLOOKUP(B8,[6]Лист_1!$C$5:$E$64,3,0)+69400 -> 138800 | AB8: =E8*$AB$1 -> 93286.25 | AC8: =VLOOKUP(B8,[7]Лист_1!$A$3:$E$57,4,0) -> 69400 | AD8: =E8*$AD$1 -> 95807.5 | AE8: =VLOOKUP(B8,[4]Лист_1!$A$5:$D$59,3,0) -> 95300 | AF8: =E8*$AF$1 -> 98328.75 | AG8: =VLOOKUP(B8,[5]Лист_1!$A$3:$C$50,3,0) -> 39950 | AH8: =G8*$AF$1 -> 90145.714 | AI8: =VLOOKUP(B8,[29]Лист_1!$A$5:$C$67,3,0) -> 109350
A9: =A8+1 -> 6 | B9: БОРИСХОФ 1 ООО | C9: БорисХоф | E9: 15883.333 | F9: =E9*$F$1 -> 15406.833 | H9: =G9-F9 -> -15406.833 | I9: =E9*$I$1 -> 15406.833 | K9: =J9-I9 -> -15406.833 | N9: =E9*$N$1 -> 16677.5
A10: =A9+1 -> 7 | B10: БОРИСХОФ Т ООО | E10: 1500 | F10: =E10*$F$1 -> 1455 | H10: =G10-F10 -> -1455 | I10: =E10*$I$1 -> 1455 | K10: =J10-I10 -> -1455 | N10: =E10*$N$1 -> 1575
A11: =A10+1 -> 8 | B11: БОРИСХОФ ХОЛДИНГ ООО | C11: БорисХоф | D11: 1 | E11: 111396.67 | F11: =E11*$F$1 -> 108054.77 | G11: =VLOOKUP(B11,[1]Лист_1!$A$1:$G$65536,7,0) -> 63200 | H11: =G11-F11 -> -44854.767 | I11: =E11*$I$1 -> 108054.77 | J11: 50000 | K11: =J11-I11 -> -58054.767 | L11: 46200 | N11: =E11*$N$1 -> 116966.5 | O11: 53900 | P11: =E11*$P$1 -> 120308.4 | Q11: 41000 | R11: =G11*$P$1 -> 68256 | S11: =VLOOKUP(B11,[2]Лист_1!$A$1:$C$65536,3,0) -> 38000 | T11: =I11*$T$1 -> 100490.93 | U11: 88620 | V11: =E11*$V$1 -> 108054.77 | W11: =VLOOKUP(B11,[3]Лист_1!$A$5:$F$55,4,0) -> 114180 | X11: =VLOOKUP(B11,[3]Лист_1!$A$5:$D$54,3,0) -> 5709 | Y11: =E11*$Y$1 -> 110282.7 | Z11: 145728.57 | AB11: =E11*$AB$1 -> 123650.3 | AC11: =VLOOKUP(B11,[7]Лист_1!$A$3:$E$57,4,0) -> 119880 | AD11: =E11*$AD$1 -> 126992.2 | AE11: =VLOOKUP(B11,[4]Лист_1!$A$5:$D$59,3,0) -> 133400 | AF11: =E11*$AF$1 -> 130334.1 | AG11: =VLOOKUP(B11,[5]Лист_1!$A$3:$C$50,3,0) -> 104160 | AH11: =G11*$AF$1 -> 73944 | AI11: =VLOOKUP(B11,[29]Лист_1!$A$5:$C$67,3,0) -> 109696
A12: =A11+1 -> 9 | B12: БРОНИРОВАНИЕ ГОСТИНИЦ ООО | C12: Ostrovok | D12: 3 | E12: 352588.33 | F12: =E12*$F$1 -> 342010.68 | G12: =VLOOKUP(B12,[1]Лист_1!$A$1:$G$65536,7,0) -> 121050 | H12: =G12-F12 -> -220960.68 | I12: =E12*$I$1 -> 342010.68 | J12: 300000 | K12: =J12-I12 -> -42010.683 | L12: 313450 | N12: =E12*$N$1 -> 370217.75 | O12: 247650 | P12: =E12*$P$1 -> 380795.4 | Q12: 322870 | R12: =G12*$P$1 -> 130734 | S12: =VLOOKUP(B12,[2]Лист_1!$A$1:$C$65536,3,0) -> 254960 | T12: =I12*$T$1 -> 318069.94 | U12: 195900 | V12: =E12*$V$1 -> 342010.68 | W12: =VLOOKUP(B12,[3]Лист_1!$A$5:$F$55,4,0) -> 274070 | X12: =VLOOKUP(B12,[3]Лист_1!$A$5:$D$54,3,0) -> 13703.5 | Y12: =E12*$Y$1 -> 349062.45 | Z12: =VLOOKUP(B12,[6]Лист_1!$C$5:$E$64,3,0) -> 107560 | AB12: =E12*$AB$1 -> 391373.05 | AC12: =VLOOKUP(B12,[7]Лист_1!$A$3:$E$57,4,0) -> 77350 | AE12: =VLOOKUP(B12,[4]Лист_1!$A$5:$D$59,3,0) -> 25050 | AG12: =VLOOKUP(B12,[5]Лист_1!$A$3:$C$50,3,0) -> 21150 | AI12: =VLOOKUP(B12,[29]Лист_1!$A$5:$C$67,3,0) -> 17180
A13: =A12+1 -> 10 | B13: БУРГЕР РУС ООО | C13: Бургеркинг | D13: 3 | E13: 94200 | F13: =E13*$F$1 -> 91374 | G13: =VLOOKUP(B13,[1]Лист_1!$A$1:$G$65536,7,0) -> 173500 | H13: =G13-F13 -> 82126 | I13: =E13*$I$1 -> 91374 | J13: 200000 | K13: =J13-I13 -> 108626 | L13: 182600 | N13: =E13*$N$1 -> 98910 | O13: 181400 | P13: =E13*$P$1 -> 101736 | Q13: 176200 | R13: =G13*$P$1 -> 187380 | S13: =VLOOKUP(B13,[2]Лист_1!$A$1:$C$65536,3,0) -> 180500 | T13: =I13*$T$1 -> 84977.82 | U13: 234000 | V13: =E13*$V$1 -> 91374 | W13: =VLOOKUP(B13,[3]Лист_1!$A$5:$F$55,4,0) -> 235000 | X13: =VLOOKUP(B13,[3]Лист_1!$A$5:$D$54,3,0) -> 11750 | Y13: =E13*$Y$1 -> 93258 | Z13: =VLOOKUP(B13,[6]Лист_1!$C$5:$E$64,3,0) -> 237000 | AB13: =E13*$AB$1 -> 104562 | AC13: =VLOOKUP(B13,[7]Лист_1!$A$3:$E$57,4,0) -> 236500 | AD13: =E13*$AD$1 -> 107388 | AE13: =VLOOKUP(B13,[4]Лист_1!$A$5:$D$59,3,0) -> 237600 | AF13: =E13*$AF$1 -> 110214 | AG13: =VLOOKUP(B13,[5]Лист_1!$A$3:$C$50,3,0) -> 233600 | AH13: =G13*$AF$1 -> 202995 | AI13: =VLOOKUP(B13,[29]Лист_1!$A$5:$C$67,3,0) -> 236000
A14: =A13+1 -> 11 | B14: ГК СБСВ-КЛЮЧАВТО ООО | C14: Keyauto | D14: 1 | E14: 153622 | F14: =E14*$F$1 -> 149013.34 | G14: =VLOOKUP(B14,[1]Лист_1!$A$1:$G$65536,7,0) -> 117642 | H14: =G14-F14 -> -31371.34 | I14: =E14*$I$1 -> 149013.34 | J14: 140000 | K14: =J14-I14 -> -9013.34 | L14: 152208 | N14: =E14*$N$1 -> 161303.1 | O14: 160902 | P14: =E14*$P$1 -> 165911.76 | Q14: 177658.9 | R14: =G14*$P$1 -> 127053.36 | T14: =I14*$T$1 -> 138582.41
A15: =A14+1 -> 12 | B15: ДЖ.Т.И. РОССИЯ ООО | C15: JTI RMC | D15: 1 | E15: 515262.41 | F15: =E15*$F$1 -> 499804.54 | G15: =VLOOKUP(B15,[1]Лист_1!$A$1:$G$65536,7,0) -> 364902 | H15: =G15-F15 -> -134902.54 | I15: =E15*$I$1 -> 499804.54 | J15: 350000 | K15: =J15-I15 -> -149804.54 | L15: 372524 | N15: =E15*$N$1 -> 541025.53 | O15: 380710 | P15: =E15*$P$1 -> 556483.4 | Q15: 368220 | R15: =G15*$P$1 -> 394094.16 | S15: =VLOOKUP(B15,[2]Лист_1!$A$1:$C$65536,3,0) -> 465308 | T15: =I15*$T$1 -> 464818.22 | U15: 340228 | V15: =E15*$V$1 -> 499804.54 | W15: =VLOOKUP(B15,[3]Лист_1!$A$5:$F$55,4,0) -> 305628 | X15: =VLOOKUP(B15,[3]Лист_1!$A$5:$D$54,3,0) -> 15281.4 | Y15: =E15*$Y$1 -> 510109.79 | Z15: =VLOOKUP(B15,[6]Лист_1!$C$5:$E$64,3,0) -> 500742 | AB15: =E15*$AB$1 -> 571941.28 | AC15: =VLOOKUP(B15,[7]Лист_1!$A$3:$E$57,4,0) -> 509163.9 | AD15: =E15*$AD$1 -> 587399.15 | AE15: =VLOOKUP(B15,[4]Лист_1!$A$5:$D$59,3,0) -> 442967.7 | AF15: =E15*$AF$1 -> 602857.02 | AG15: =VLOOKUP(B15,[5]Лист_1!$A$3:$C$50,3,0) -> 431505.1 | AH15: =G15*$AF$1 -> 426935.34 | AI15: =VLOOKUP(B15,[29]Лист_1!$A$5:$C$67,3,0) -> 412654.4
A16: =A15+1 -> 13 | B16: ДИОНА ООО | C16: Внуково | D16: 3 | E16: 114358.33 | F16: =E16*$F$1 -> 110927.58 | G16: =VLOOKUP(B16,[1]Лист_1!$A$1:$G$65536,7,0) -> 166800 | H16: =G16-F16 -> 55872.417 | I16: =E16*$I$1 -> 110927.58 | J16: 100000 | K16: =J16-I16 -> -10927.583 | L16: 391800 | N16: =E16*$N$1 -> 120076.25 | O16: 301200 | Y16: =E16*$Y$1 -> 113214.75
A17: =A16+1 -> 14 | B17: ЕАПТЕКА ООО | C17: ЕАптека | E17: 27700.667 | F17: =E17*$F$1 -> 26869.647 | H17: =G17-F17 -> -26869.647 | I17: =E17*$I$1 -> 26869.647 | J17: 0 | K17: =J17-I17 -> -26869.647 | N17: =E17*$N$1 -> 29085.7 | Y17: =E17*$Y$1 -> 27423.66
A18: =A17+1 -> 15 | B18: ЕВРОПА ООО | C18: Vnukovo Outlet Village | E18: 179283.33 | F18: =E18*$F$1 -> 173904.83 | G18: =VLOOKUP(B18,[1]Лист_1!$A$1:$G$65536,7,0) -> 186200 | H18: =G18-F18 -> 12295.167 | I18: =E18*$I$1 -> 173904.83 | J18: 0 | K18: =J18-I18 -> -173904.83 | N18: =E18*$N$1 -> 188247.5 | Y18: =E18*$Y$1 -> 177490.5
A19: =A18+1 -> 16 | B19: ЭТНЕ ООО | C19: Vnukovo Outlet Village | D19: 3 | G19: =VLOOKUP(B19,[1]Лист_1!$A$1:$G$65536,7,0) -> 58200 | H19: =G19-F19 -> 58200 | I19: 173905 | J19: 200000 | K19: =J19-I19 -> 26095 | Y19: =E19*$Y$1 -> 0
A20: =A19+1 -> 17 | B20: ИМПУЛЬС ООО | C20: Amazing Red | D20: 3 | E20: 313758.33 | F20: =E20*$F$1 -> 304345.58 | G20: =VLOOKUP(B20,[1]Лист_1!$A$1:$G$65536,7,0) -> 327680 | H20: =G20-F20 -> 23334.417 | I20: =E20*$I$1 -> 304345.58 | J20: 220000 | K20: =J20-I20 -> -84345.583 | L20: 314870.48 | N20: =E20*$N$1 -> 329446.25 | O20: 299000 | P20: =E20*$P$1 -> 338859 | Q20: 504590 | R20: =G20*$P$1 -> 353894.4 | S20: =VLOOKUP(B20,[2]Лист_1!$A$1:$C$65536,3,0) -> 296860 | T20: =I20*$T$1 -> 283041.39 | U20: 262220 | V20: =E20*$V$1 -> 304345.58 | W20: =VLOOKUP(B20,[3]Лист_1!$A$5:$F$55,4,0) -> 231980 | X20: =VLOOKUP(B20,[3]Лист_1!$A$5:$D$54,3,0) -> 11599 | Y20: =E20*$Y$1 -> 310620.75 | Z20: =VLOOKUP(B20,[6]Лист_1!$C$5:$E$64,3,0) -> 51200 | AE20: =VLOOKUP(B20,[4]Лист_1!$A$5:$D$59,3,0) -> 57200
A21: =A20+1 -> 18 | B21: ИНСТАМАРТ СЕРВИС ООО | C21: Сбермаркет ВнутриКом | D21: 3 | E21: 542963.33 | F21: =E21*$F$1 -> 526674.43 | G21: =VLOOKUP(B21,[1]Лист_1!$A$1:$G$65536,7,0) -> 211175 | H21: =G21-F21 -> -315499.43 | I21: =E21*$I$1 -> 526674.43 | J21: 200000 | K21: =J21-I21 -> -326674.43 | L21: 236560 | N21: =E21*$N$1 -> 570111.5 | O21: 139340 | P21: =E21*$P$1 -> 586400.4 | Q21: 118020 | R21: =G21*$P$1 -> 228069 | S21: =VLOOKUP(B21,[2]Лист_1!$A$1:$C$65536,3,0) -> 20800 | T21: =I21*$T$1 -> 489807.22 | U21: 86510 | V21: =E21*$V$1 -> 526674.43 | Z21: 75400
A22: =A21+1 -> 19 | B22: ИП Абдулин | C22: VK | G22: 11429 | H22: =G22-F22 -> 11429 | I22: =E22*$I$1 -> 0 | K22: =J22-I22 -> 0 | T22: =I22*$T$1 -> 0 | Y22: =E22*$Y$1 -> 0
A23: =A22+1 -> 20 | B23: ДЗЕН.ПЛАТФОРМА ООО | C23: VK | O23: 12274 | Q23: 12274 | S23: =VLOOKUP(B23,[2]Лист_1!$A$1:$C$65536,3,0) -> 6137 | T23: =I23*$T$1 -> 0 | U23: 33683 | W23: =VLOOKUP(B23,[3]Лист_1!$A$5:$F$55,4,0) -> 12274 | X23: =VLOOKUP(B23,[3]Лист_1!$A$5:$D$54,3,0) -> 613.7 | Y23: =E23*$Y$1 -> 0 | Z23: =VLOOKUP(B23,[6]Лист_1!$C$5:$E$64,3,0) -> 5900 | AC23: =VLOOKUP(B23,[7]Лист_1!$A$3:$E$57,4,0) -> 24264 | AD23: =E23*$AD$1 -> 0 | AE23: =VLOOKUP(B23,[4]Лист_1!$A$5:$D$59,3,0) -> 15082
A24: =A23+1 -> 21 | B24: ВК ООО | C24: VK | AI24: =VLOOKUP(B24,[29]Лист_1!$A$5:$C$67,3,0) -> 12274
A25: =A23+1 -> 21 | B25: ДОНОР-СЁРЧ (ПОИСК ДОНОРОВ) АНО | C25: DonorSearch | O25: 76190.476 | Q25: 38095.238 | S25: =VLOOKUP(B25,[2]Лист_1!$A$1:$C$65536,3,0) -> 38095.238 | T25: =I25*$T$1 -> 0 | U25: 38095.238 | W25: =VLOOKUP(B25,[3]Лист_1!$A$5:$F$55,4,0) -> 38095.238 | X25: =VLOOKUP(B25,[3]Лист_1!$A$5:$D$54,3,0) -> 1904.7619 | Y25: =E25*$Y$1 -> 0 | Z25: =VLOOKUP(B25,[6]Лист_1!$C$5:$E$64,3,0) -> 38095.238 | AC25: =VLOOKUP(B25,[7]Лист_1!$A$3:$E$57,4,0) -> 38095.238 | AD25: =E25*$AD$1 -> 0 | AE25: =VLOOKUP(B25,[4]Лист_1!$A$5:$D$59,3,0) -> 38095.238 | AG25: =VLOOKUP(B25,[5]Лист_1!$A$3:$C$50,3,0) -> 38095.238 | AI25: =VLOOKUP(B25,[29]Лист_1!$A$5:$C$67,3,0) -> 38095.238
A26: =A23+1 -> 21 | B26: ИП Суходоев | C26: Profmax | D26: 3 | E26: 186900 | F26: =E26*$F$1 -> 181293 | G26: 134400 | H26: =G26-F26 -> -46893 | I26: =E26*$I$1 -> 181293 | J26: 110000 | K26: =J26-I26 -> -71293 | L26: 91200 | N26: =E26*$N$1 -> 196245 | O26: 82400 | P26: =E26*$P$1 -> 201852 | Q26: 109600 | R26: =G26*$P$1 -> 145152
A27: =A26+1 -> 22 | B27: КАЗАНЬ РЕАЛ ЭСТЕЙТ ООО | C27: Benetton | D27: 1 | E27: 703840.2 | F27: =E27*$F$1 -> 682724.99 | G27: =VLOOKUP(B27,[1]Лист_1!$A$1:$G$65536,7,0) -> 1033029.2 | H27: =G27-F27 -> 350304.18 | I27: =E27*$I$1 -> 682724.99 | J27: 800000 | K27: =J27-I27 -> 117275.01 | L27: 891469.01 | N27: =E27*$N$1 -> 739032.21 | O27: 723546 | P27: =E27*$P$1 -> 760147.42 | Q27: 905207.01 | R27: =G27*$P$1 -> 1115671.5 | S27: =VLOOKUP(B27,[2]Лист_1!$A$1:$C$65536,3,0) -> 817175.02 | T27: =I27*$T$1 -> 634934.24 | U27: 861405.01 | V27: =E27*$V$1 -> 682724.99 | W27: =VLOOKUP(B27,[3]Лист_1!$A$5:$F$55,4,0) -> 1010565 | X27: 50528.26 | Y27: =E27*$Y$1 -> 696801.8 | Z27: 852152.51 | AB27: =E27*$AB$1 -> 781262.62 | AC27: =VLOOKUP(B27,[7]Лист_1!$A$3:$E$57,4,0) -> 950575.01 | AD27: =E27*$AD$1 -> 802377.83 | AE27: =VLOOKUP(B27,[4]Лист_1!$A$5:$D$59,3,0) -> 782920.01 | AF27: =E27*$AF$1 -> 823493.03 | AG27: =VLOOKUP(B27,[5]Лист_1!$A$3:$C$50,3,0) -> 839710.01 | AH27: =G27*$AF$1 -> 1208644.1 | AI27: =VLOOKUP(B27,[29]Лист_1!$A$5:$C$67,3,0) -> 790700
A28: =A27+1 -> 23 | B28: КАПИТАЛ ГРУП ООО | C28: Capital group | D28: 3 | E28: 134250 | F28: =E28*$F$1 -> 130222.5 | G28: =VLOOKUP(B28,[1]Лист_1!$A$1:$G$65536,7,0) -> 98150 | H28: =G28-F28 -> -32072.5 | I28: =E28*$I$1 -> 130222.5 | J28: 90000 | K28: =J28-I28 -> -40222.5 | L28: 103057.5 | N28: =E28*$N$1 -> 140962.5 | O28: 117200 | P28: =E28*$P$1 -> 144990 | Q28: 192750 | R28: =G28*$P$1 -> 106002 | S28: =VLOOKUP(B28,[2]Лист_1!$A$1:$C$65536,3,0) -> 117200 | T28: =I28*$T$1 -> 121106.93 | U28: 69900 | V28: =E28*$V$1 -> 130222.5 | W28: =VLOOKUP(B28,[3]Лист_1!$A$5:$F$55,4,0) -> 145450 | X28: =VLOOKUP(B28,[3]Лист_1!$A$5:$D$54,3,0) -> 7272.5 | Y28: =E28*$Y$1 -> 132907.5 | Z28: =VLOOKUP(B28,[6]Лист_1!$C$5:$E$64,3,0) -> 188150 | AB28: =E28*$AB$1 -> 149017.5 | AC28: =VLOOKUP(B28,[7]Лист_1!$A$3:$E$57,4,0) -> 93550 | AD28: =E28*$AD$1 -> 153045 | AE28: =VLOOKUP(B28,[4]Лист_1!$A$5:$D$59,3,0) -> 158848 | AF28: =E28*$AF$1 -> 157072.5 | AG28: =VLOOKUP(B28,[5]Лист_1!$A$3:$C$50,3,0) -> 93550 | AH28: =G28*$AF$1 -> 114835.5 | AI28: =VLOOKUP(B28,[29]Лист_1!$A$5:$C$67,3,0) -> 319272
A29: =A28+1 -> 24 | B29: КАРШЕРИНГ РУССИЯ ПАО | C29: Делимобиль | D29: 5 | E29: 143845.83 | F29: =E29*$F$1 -> 139530.46 | G29: =VLOOKUP(B29,[1]Лист_1!$A$1:$G$65536,7,0) -> 72325 | H29: =G29-F29 -> -67205.458 | I29: =E29*$I$1 -> 139530.46 | J29: 120000 | K29: =J29-I29 -> -19530.458 | L29: 126525 | N29: =E29*$N$1 -> 151038.13 | O29: 90150 | P29: =E29*$P$1 -> 155353.5 | Q29: 94900 | R29: =G29*$P$1 -> 78111 | S29: =VLOOKUP(B29,[2]Лист_1!$A$1:$C$65536,3,0) -> 53950 | T29: =I29*$T$1 -> 129763.33 | U29: 56500 | V29: =E29*$V$1 -> 139530.46 | W29: =VLOOKUP(B29,[3]Лист_1!$A$5:$F$55,4,0) -> 126375 | X29: =VLOOKUP(B29,[3]Лист_1!$A$5:$D$54,3,0) -> 6318.75 | Y29: =E29*$Y$1 -> 142407.38 | Z29: =VLOOKUP(B29,[6]Лист_1!$C$5:$E$64,3,0) -> 127600 | AB29: =E29*$AB$1 -> 159668.88 | AC29: =VLOOKUP(B29,[7]Лист_1!$A$3:$E$57,4,0) -> 194400 | AD29: =E29*$AD$1 -> 163984.25 | AE29: =VLOOKUP(B29,[4]Лист_1!$A$5:$D$59,3,0) -> 148500 | AF29: =E29*$AF$1 -> 168299.62 | AG29: =VLOOKUP(B29,[5]Лист_1!$A$3:$C$50,3,0) -> 135900 | AH29: =G29*$AF$1 -> 84620.25 | AI29: =VLOOKUP(B29,[29]Лист_1!$A$5:$C$67,3,0) -> 75600
A30: =A29+1 -> 25 | B30: КИНОПОИСК ООО | C30: Яндекс | D30: 5 | E30: 311316.67 | F30: =E30*$F$1 -> 301977.17 | G30: =VLOOKUP(B30,[1]Лист_1!$A$1:$G$65536,7,0) -> 203000 | H30: =G30-F30 -> -98977.167 | I30: =E30*$I$1 -> 301977.17 | J30: 200000 | K30: =J30-I30 -> -101977.17 | L30: 248700 | N30: =E30*$N$1 -> 326882.5 | O30: 206300 | P30: =E30*$P$1 -> 336222 | Q30: 348200 | R30: =G30*$P$1 -> 219240 | S30: =VLOOKUP(B30,[2]Лист_1!$A$1:$C$65536,3,0) -> 312500 | T30: =I30*$T$1 -> 280838.77 | U30: 349300 | V30: =E30*$V$1 -> 301977.17 | W30: =VLOOKUP(B30,[3]Лист_1!$A$5:$F$55,4,0) -> 600600.8 | X30: =VLOOKUP(B30,[3]Лист_1!$A$5:$D$54,3,0) -> 30030.04 | Y30: =E30*$Y$1 -> 308203.5 | Z30: 371900 | AB30: =E30*$AB$1 -> 345561.5 | AC30: =VLOOKUP(B30,[7]Лист_1!$A$3:$E$57,4,0) -> 396400 | AD30: =E30*$AD$1 -> 354901 | AE30: 243904.76 | AF30: =E30*$AF$1 -> 364240.5 | AG30: 244700 | AH30: =G30*$AF$1 -> 237510 | AI30: =VLOOKUP(B30,[29]Лист_1!$A$5:$C$67,3,0) -> 169350
A31: =A30+1 -> 26 | B31: КНАУФ ГИПС ООО | C31: Knauf | E31: 26669.167 | F31: =E31*$F$1 -> 25869.092 | H31: =G31-F31 -> -25869.092 | I31: =E31*$I$1 -> 25869.092 | K31: =J31-I31 -> -25869.092 | L31: 27360 | N31: =E31*$N$1 -> 28002.625 | O31: 15620 | P31: =E31*$P$1 -> 28802.7 | R31: =G31*$P$1 -> 0 | V31: =E31*$V$1 -> 25869.092 | W31: =VLOOKUP(B31,[3]Лист_1!$A$5:$F$55,4,0) -> 53210 | X31: =VLOOKUP(B31,[3]Лист_1!$A$5:$D$54,3,0) -> 2660.5 | Y31: =E31*$Y$1 -> 26402.475 | Z31: 37680 | AB31: =E31*$AB$1 -> 29602.775 | AC31: 89290 | AD31: =E31*$AD$1 -> 30402.85 | AE31: =VLOOKUP(B31,[4]Лист_1!$A$5:$D$59,3,0) -> 100435 | AF31: =E31*$AF$1 -> 31202.925 | AG31: =VLOOKUP(B31,[5]Лист_1!$A$3:$C$50,3,0) -> 76789 | AH31: =G31*$AF$1 -> 0 | AI31: =VLOOKUP(B31,[29]Лист_1!$A$5:$C$67,3,0) -> 17746
A32: =A31+1 -> 27 | B32: КОЛЕСА ДАРОМ.РУ ООО | C32: Колёса Даром | E32: 300000 | F32: =E32*$F$1 -> 291000 | G32: =VLOOKUP(B32,[1]Лист_1!$A$1:$G$65536,7,0) -> 285714.29 | H32: =G32-F32 -> -5285.7143 | I32: =E32*$I$1 -> 291000 | J32: 300000 | K32: =J32-I32 -> 9000 | L32: 285714.29 | N32: 300000 | O32: 300000 | P32: 300000 | Q32: 300000 | R32: 300000 | S32: =VLOOKUP(B32,[2]Лист_1!$A$1:$C$65536,3,0) -> 300000 | T32: =I32*$T$1 -> 270630 | U32: 300000 | V32: =E32*$V$1 -> 291000 | W32: =VLOOKUP(B32,[3]Лист_1!$A$5:$F$55,4,0) -> 249600 | X32: =VLOOKUP(B32,[3]Лист_1!$A$5:$D$54,3,0) -> 12480 | Y32: =E32*$Y$1 -> 297000 | Z32: =VLOOKUP(B32,[6]Лист_1!$C$5:$E$64,3,0) -> 288800 | AB32: =E32*$AB$1 -> 333000 | AC32: =VLOOKUP(B32,[7]Лист_1!$A$3:$E$57,4,0) -> 300000 | AD32: =E32*$AD$1 -> 342000 | AE32: =VLOOKUP(B32,[4]Лист_1!$A$5:$D$59,3,0) -> 300000 | AF32: =E32*$AF$1 -> 351000 | AG32: =VLOOKUP(B32,[5]Лист_1!$A$3:$C$50,3,0) -> 300000 | AH32: =G32*$AF$1 -> 334285.71 | AI32: =VLOOKUP(B32,[29]Лист_1!$A$5:$C$67,3,0) -> 300000
A33: =A32+1 -> 28 | B33: КОНДИТЕРСКАЯ ФАБРИКА ПОБЕДА ООО | C33: Победа Вкуса | D33: 3 | E33: 114875 | F33: =E33*$F$1 -> 111428.75 | G33: =VLOOKUP(B33,[1]Лист_1!$A$1:$G$65536,7,0) -> 114875 | H33: =G33-F33 -> 3446.25 | I33: =E33*$I$1 -> 111428.75 | J33: 120619 | K33: =J33-I33 -> 9190.25 | L33: 114875 | N33: =E33*$N$1 -> 120618.75 | O33: 119030 | P33: =E33*$P$1 -> 124065 | Q33: 114875 | R33: =G33*$P$1 -> 124065 | S33: =VLOOKUP(B33,[2]Лист_1!$A$1:$C$65536,3,0) -> 139025 | T33: =I33*$T$1 -> 103628.74 | U33: 135455 | V33: =E33*$V$1 -> 111428.75 | W33: =VLOOKUP(B33,[3]Лист_1!$A$5:$F$55,4,0) -> 116436 | X33: =VLOOKUP(B33,[3]Лист_1!$A$5:$D$54,3,0) -> 5821.8 | Y33: =E33*$Y$1 -> 113726.25 | Z33: =VLOOKUP(B33,[6]Лист_1!$C$5:$E$64,3,0) -> 121647 | AB33: =E33*$AB$1 -> 127511.25 | AC33: 86175 | AD33: =E33*$AD$1 -> 130957.5 | AE33: =VLOOKUP(B33,[4]Лист_1!$A$5:$D$59,3,0) -> 139128 | AF33: =E33*$AF$1 -> 134403.75 | AG33: =VLOOKUP(B33,[5]Лист_1!$A$3:$C$50,3,0) -> 84140 | AH33: =G33*$AF$1 -> 134403.75 | AI33: =VLOOKUP(B33,[29]Лист_1!$A$5:$C$67,3,0) -> 108090
A34: =A33+1 -> 29 | B34: КРАСНАЯ ПОЛЯНА НАО | C34: Красная поляна | D34: 3 | E34: 94687 | F34: =E34*$F$1 -> 91846.39 | G34: =VLOOKUP(B34,[1]Лист_1!$A$1:$G$65536,7,0) -> 82998.038 | H34: =G34-F34 -> -8848.3519 | I34: =E34*$I$1 -> 91846.39 | J34: 100000 | K34: =J34-I34 -> 8153.61 | L34: 234952.44 | N34: =E34*$N$1 -> 99421.35 | O34: 112057.5 | P34: =E34*$P$1 -> 102261.96 | R34: =G34*$P$1 -> 89637.881 | S34: =VLOOKUP(B34,[2]Лист_1!$A$1:$C$65536,3,0) -> 286480.59 | T34: =I34*$T$1 -> 85417.143 | U34: 126472 | V34: =E34*$V$1 -> 91846.39 | W34: =VLOOKUP(B34,[3]Лист_1!$A$5:$F$55,4,0) -> 141601.02 | X34: =VLOOKUP(B34,[3]Лист_1!$A$5:$D$54,3,0) -> 7080.051 | Y34: =E34*$Y$1 -> 93740.13 | Z34: =VLOOKUP(B34,[6]Лист_1!$C$5:$E$64,3,0) -> 119417.2 | AB34: =E34*$AB$1 -> 105102.57 | AC34: =VLOOKUP(B34,[7]Лист_1!$A$3:$E$57,4,0) -> 123893 | AD34: =E34*$AD$1 -> 107943.18 | AE34: =VLOOKUP(B34,[4]Лист_1!$A$5:$D$59,3,0) -> 114042.62 | AF34: =E34*$AF$1 -> 110783.79 | AG34: =VLOOKUP(B34,[5]Лист_1!$A$3:$C$50,3,0) -> 119728.12 | AH34: =G34*$AF$1 -> 97107.705 | AI34: =VLOOKUP(B34,[29]Лист_1!$A$5:$C$67,3,0) -> 148190.2
A35: =A34+1 -> 30 | B35: Л'ОРЕАЛЬ АО | C35: CDMO | D35: 1 | E35: 57398 | F35: =E35*$F$1 -> 55676.06 | G35: =VLOOKUP(B35,[1]Лист_1!$A$1:$G$65536,7,0) -> 42565.333 | H35: =G35-F35 -> -13110.727 | I35: =E35*$I$1 -> 55676.06 | J35: 25246 | K35: =J35-I35 -> -30430.06 | L35: 42565.333 | N35: =E35*$N$1 -> 60267.9 | O35: 61086 | P35: =E35*$P$1 -> 61989.84 | Q35: 66610.1 | R35: =E35*$R$1 -> 57971.98 | S35: =VLOOKUP(B35,[2]Лист_1!$A$1:$C$65536,3,0) -> 18521.143 | T35: =I35*$T$1 -> 51778.736 | U35: 42566.143 | V35: =E35*$V$1 -> 55676.06 | W35: =VLOOKUP(B35,[3]Лист_1!$A$5:$F$55,4,0) -> 24044.19 | X35: =VLOOKUP(B35,[3]Лист_1!$A$5:$D$54,3,0) -> 1202.2095 | Y35: =E35*$Y$1 -> 56824.02 | AB35: =E35*$AB$1 -> 63711.78 | AC35: =VLOOKUP(B35,[7]Лист_1!$A$3:$E$57,4,0) -> 45139.267 | AD35: =E35*$AD$1 -> 65433.72 | AE35: =VLOOKUP(B35,[4]Лист_1!$A$5:$D$59,3,0) -> 117090.63 | AF35: =E35*$AF$1 -> 67155.66 | AG35: =VLOOKUP(B35,[5]Лист_1!$A$3:$C$50,3,0) -> 242472.96 | AH35: =G35*$AF$1 -> 49801.44 | AI35: =VLOOKUP(B35,[29]Лист_1!$A$5:$C$67,3,0) -> 119586.44
A36: =A35+1 -> 31 | B36: Майндбокс ООО | C36: Mindbox | D36: 3 | E36: 297190.23 | F36: =E36*$F$1 -> 288274.53 | G36: =VLOOKUP(B36,[1]Лист_1!$A$1:$G$65536,7,0) -> 111254.67 | H36: =G36-F36 -> -177019.86 | I36: =E36*$I$1 -> 288274.53 | J36: 100000 | K36: =J36-I36 -> -188274.53 | L36: 166070 | N36: =E36*$N$1 -> 312049.74
A37: =A36+1 -> 32 | B37: МАРС ООО | C37: Марс - комплексный проект, подписание доков, команда (Давтян, Ерёмин) | E37: 1616671.7 | F37: =E37*$F$1 -> 1568171.5 | G37: =VLOOKUP(B37,[1]Лист_1!$A$1:$G$65536,7,0)+499525 -> 1006325 | H37: =G37-F37 -> -561846.52 | I37: =E37*$I$1 -> 1568171.5 | K37: -208172 | N37: =E37*$N$1 -> 1697505.3 | P37: =E37*$P$1 -> 1746005.4 | R37: =E37*$R$1 -> 1632838.4 | T37: =I37*$T$1 -> 1458399.5 | V37: =E37*$V$1 -> 1568171.5 | Y37: =E37*$Y$1 -> 1600504.9 | AB37: =E37*$AB$1 -> 1794505.6 | AD37: =E37*$AD$1 -> 1843005.7 | AF37: =E37*$AF$1 -> 1891505.8 | AH37: =G37*$AF$1 -> 1177400.2
A38: =A37+1 -> 33 | B38: МАРС ООО | C38: Экосистема | D38: 5 | J38: 120000 | O38: 277050 | Q38: 82000 | R38: =E38*$R$1 -> 0 | S38: 1150600 | T38: =I38*$T$1 -> 0 | U38: 248500 | V38: =E38*$V$1 -> 0 | W38: =[3]Лист_1!$D$35 -> 160500 | X38: 8025 | Z38: 177050 | AC38: 158655 | AD38: =E38*$AD$1 -> 0 | AE38: 128350 | AG38: 215600 | AI38: 484280
A39: =A38+1 -> 34 | B39: РУСКАН АО | C39: Royal Canin | D39: 1 | J39: 500000 | L39: 571650 | O39: 606100 | Q39: 1155200 | R39: =E39*$R$1 -> 0 | S39: 762665 | T39: =I39*$T$1 -> 0 | U39: 562125 | V39: =E39*$V$1 -> 0 | W39: 534650 | Z39: 531200 | AC39: 701025 | AD39: =E39*$AD$1 -> 0 | AE39: =126000+826900 -> 952900 | AG39: 843475 | AI39: =VLOOKUP(B39,[29]Лист_1!$A$5:$C$67,3,0)+1200000 -> 2150970
A40: =A39+1 -> 35 | B40: =B37 -> МАРС ООО | C40: Kinpet | D40: 3 | J40: 540000 | L40: 563246.25 | O40: 638975 | Q40: 476189 | R40: =E40*$R$1 -> 0 | S40: 508975 | T40: =I40*$T$1 -> 0 | U40: 670351 | V40: =E40*$V$1 -> 0 | W40: 635002.5 | X40: 31750.17 | Z40: 454000 | AC40: 591550.07 | AD40: =E40*$AD$1 -> 0 | AE40: 554737.54 | AG40: 525887.54 | AI40: 492850
A41: =A40+1 -> 36 | B41: =B38 -> МАРС ООО | C41: Любимчик | D41: 3 | J41: 200000 | Q41: 327500 | R41: =E41*$R$1 -> 0 | T41: =I41*$T$1 -> 0 | U41: 606464.03 | V41: =E41*$V$1 -> 0 | W41: =[3]Лист_1!$D$34 -> 273117.52 | X41: 13655.9 | Z41: 148165.02 | AC41: 216368 | AD41: =E41*$AD$1 -> 0 | AE41: 210318 | AG41: 762935 | AI41: 671290
A42: =A41+1 -> 37 | B42: МЕТРО КЭШ ЭНД КЕРРИ ООО | C42: Metro | E42: 126618.67 | F42: =E42*$F$1 -> 122820.11 | G42: =VLOOKUP(B42,[1]Лист_1!$A$1:$G$65536,7,0) -> 49982 | H42: =G42-F42 -> -72838.107 | N42: =E42*$N$1 -> 132949.6 | O42: 26876 | P42: =E42*$P$1 -> 136748.16 | Q42: 44276 | R42: =E42*$R$1 -> 127884.85 | T42: =I42*$T$1 -> 0 | U42: 26876 | V42: =E42*$V$1 -> 122820.11 | Y42: =E42*$Y$1 -> 125352.48 | Z42: =VLOOKUP(B42,[6]Лист_1!$C$5:$E$64,3,0) -> 73088 | AB42: =E42*$AB$1 -> 140546.72 | AC42: =VLOOKUP(B42,[7]Лист_1!$A$3:$E$57,4,0) -> 73088 | AD42: =E42*$AD$1 -> 144345.28 | AE42: =VLOOKUP(B42,[4]Лист_1!$A$5:$D$59,3,0) -> 73182 | AF42: =E42*$AF$1 -> 148143.84 | AH42: =G42*$AF$1 -> 58478.94 | AI42: =VLOOKUP(B42,[29]Лист_1!$A$5:$C$67,3,0) -> 3480
A43: =A42+1 -> 38 | B43: МОСКВИЧ АО МАЗ | E43: 605075 | F43: =E43*$F$1 -> 586922.75 | G43: 400000 | H43: =G43-F43 -> -186922.75 | I43: =E43*$I$1 -> 586922.75 | J43: 533000 | K43: =J43-I43 -> -53922.75 | L43: 533000 | N43: =E43*$N$1 -> 635328.75 | O43: 456900 | P43: =E43*$P$1 -> 653481 | Q43: 400000 | R43: =E43*$R$1 -> 611125.75 | S43: 600000 | T43: =I43*$T$1 -> 545838.16 | U43: 49900 | V43: =E43*$V$1 -> 586922.75 | W43: 350000 | X43: 17500 | Y43: =E43*$Y$1 -> 599024.25
A44: =A43+1 -> 39 | B44: Мосурбанфорум | D44: 3 | J44: 127400 | K44: =J44-I44 -> 127400 | P44: =E44*$P$1 -> 0 | T44: =I44*$T$1 -> 0 | V44: =E44*$V$1 -> 0 | Y44: =E44*$Y$1 -> 0 | AD44: =E44*$AD$1 -> 0
A45: =A44+1 -> 40 | B45: МУСА МОТОРС ДЖЕЙ ЭЛ ЭР ООО | C45: БорисХоф | E45: 9033.3333 | F45: =E45*$F$1 -> 8762.3333 | H45: =G45-F45 -> -8762.3333 | I45: =E45*$I$1 -> 8762.3333 | K45: =J45-I45 -> -8762.3333 | N45: =E45*$N$1 -> 9485 | P45: =E45*$P$1 -> 9756 | V45: =E45*$V$1 -> 8762.3333
A46: =A45+1 -> 41 | B46: ОККАМ ИКС ООО | C46: Алроса | D46: 3 | E46: 53491.667 | F46: =E46*$F$1 -> 51886.917 | G46: =VLOOKUP(B46,[1]Лист_1!$A$1:$G$65536,7,0) -> 68750 | H46: =G46-F46 -> 16863.083 | I46: =E46*$I$1 -> 51886.917 | J46: 59050 | K46: =J46-I46 -> 7163.0833 | L46: 72250 | N46: =E46*$N$1 -> 56166.25 | O46: 82700 | P46: =E46*$P$1 -> 57771 | Q46: 69850 | V46: =E46*$V$1 -> 51886.917
A47: =A46+1 -> 42 | B47: ООО «ДЖИЭФЭН КЛАУД ИНТЕРНЕТ СЕРВИСИС» | C47: GFN | D47: 5 | E47: 47886 | F47: =E47*$F$1 -> 46449.42 | G47: =VLOOKUP(B47,[1]Лист_1!$A$1:$G$65536,7,0) -> 21440 | H47: =G47-F47 -> -25009.42 | I47: =E47*$I$1 -> 46449.42 | J47: 35000 | K47: =J47-I47 -> -11449.42 | L47: 65840 | N47: =E47*$N$1 -> 50280.3 | O47: 101240 | P47: =E47*$P$1 -> 51716.88 | Q47: 39100 | R47: =E47*$R$1 -> 48364.86 | S47: =VLOOKUP(B47,[2]Лист_1!$A$1:$C$65536,3,0) -> 81920 | T47: =I47*$T$1 -> 43197.961 | U47: 44760 | V47: =E47*$V$1 -> 46449.42 | W47: =[3]Лист_1!$D$18 -> 13600 | X47: 680 | Y47: =E47*$Y$1 -> 47407.14 | Z47: 25500 | AB47: =E47*$AB$1 -> 53153.46 | AD47: =E47*$AD$1 -> 54590.04 | AF47: =E47*$AF$1 -> 56026.62 | AH47: =G47*$AF$1 -> 25084.8
A48: =A47+1 -> 43 | B48: ООО "Корзинка-6" | C48: Правильная Корзинка | E48: 78360 | F48: =E48*$F$1 -> 76009.2 | H48: =G48-F48 -> -76009.2 | I48: =E48*$I$1 -> 76009.2 | K48: =J48-I48 -> -76009.2 | N48: =E48*$N$1 -> 82278 | P48: =E48*$P$1 -> 84628.8 | V48: =E48*$V$1 -> 76009.2
A49: =A48+1 -> 44 | B49: ООО «СПАДРИМ» | C49: SpaDream | D49: 3 | E49: 130983.33 | F49: =E49*$F$1 -> 127053.83 | G49: =VLOOKUP(B49,[1]Лист_1!$A$1:$G$65536,7,0) -> 71300 | H49: =G49-F49 -> -55753.833 | I49: =E49*$I$1 -> 127053.83 | J49: 91600 | K49: =J49-I49 -> -35453.833 | L49: 119000 | N49: =E49*$N$1 -> 137532.5 | P49: =E49*$P$1 -> 141462 | R49: =E49*$R$1 -> 132293.17 | V49: =E49*$V$1 -> 127053.83
A50: =A49+1 -> 45 | B50: Лупейко Виктор Владимирович | C50: SpaDream | O50: 119150 | Q50: 198350 | R50: =E50*$R$1 -> 0 | S50: =VLOOKUP(B50,[2]Лист_1!$A$1:$C$65536,3,0) -> 236200 | T50: 128324 | U50: 150550 | Y50: =E50*$Y$1 -> 0 | AC50: =VLOOKUP(B50,[7]Лист_1!$A$3:$E$57,4,0) -> 208700 | AD50: =E50*$AD$1 -> 0
A51: =A49+1 -> 45 | B51: ПЕТРОВАКС ФАРМ ООО | C51: Петровакс Фарм | D51: 5 | E51: 458905.33 | F51: =E51*$F$1 -> 445138.17 | G51: =VLOOKUP(B51,[1]Лист_1!$A$1:$G$65536,7,0) -> 513000 | H51: =G51-F51 -> 67861.827 | I51: =E51*$I$1 -> 445138.17 | J51: 480000 | K51: =J51-I51 -> 34861.827 | L51: 516900 | N51: =E51*$N$1 -> 481850.6 | O51: 519200 | P51: =E51*$P$1 -> 495617.76 | Q51: 603700 | R51: =E51*$R$1 -> 463494.39 | S51: =VLOOKUP(B51,[2]Лист_1!$A$1:$C$65536,3,0) -> 465850 | T51: =I51*$T$1 -> 413978.5 | U51: 481400 | V51: =E51*$V$1 -> 445138.17 | W51: =VLOOKUP(B51,[3]Лист_1!$A$5:$F$55,4,0) -> 541600 | X51: =VLOOKUP(B51,[3]Лист_1!$A$5:$D$54,3,0) -> 27080 | Y51: =E51*$Y$1 -> 454316.28 | Z51: 557928 | AB51: =E51*$AB$1 -> 509384.92 | AC51: =VLOOKUP(B51,[7]Лист_1!$A$3:$E$57,4,0) -> 358848 | AD51: =E51*$AD$1 -> 523152.08 | AE51: =VLOOKUP(B51,[4]Лист_1!$A$5:$D$59,3,0) -> 460119 | AF51: =E51*$AF$1 -> 536919.24 | AG51: =VLOOKUP(B51,[5]Лист_1!$A$3:$C$50,3,0) -> 580604 | AH51: =G51*$AF$1 -> 600210 | AI51: =VLOOKUP(B51,[29]Лист_1!$A$5:$C$67,3,0) -> 464834
A52: =A51+1 -> 46 | B52: ПРЕМИУМ ЭСТЕЙТ ООО | C52: Level | D52: 1 | E52: 506698.33 | F52: =E52*$F$1 -> 491497.38 | G52: =VLOOKUP(B52,[1]Лист_1!$A$1:$G$65536,7,0) -> 140747.62 | H52: =G52-F52 -> -350749.76 | I52: =E52*$I$1 -> 491497.38 | J52: 140000 | K52: =J52-I52 -> -351497.38 | L52: 319648.1 | N52: =E52*$N$1 -> 532033.25 | O52: 515599 | P52: =E52*$P$1 -> 547234.2 | Q52: 509946.19 | R52: =E52*$R$1 -> 511765.32 | S52: =VLOOKUP(B52,[2]Лист_1!$A$1:$C$65536,3,0) -> 586208.1 | T52: =I52*$T$1 -> 457092.57 | U52: 711488.57 | V52: =E52*$V$1 -> 491497.38 | W52: =VLOOKUP(B52,[3]Лист_1!$A$5:$F$55,4,0) -> 552060.95 | X52: 27602.14 | Y52: =E52*$Y$1 -> 501631.35 | Z52: 367594.3 | AB52: =E52*$AB$1 -> 562435.15 | AC52: =VLOOKUP(B52,[7]Лист_1!$A$3:$E$57,4,0) -> 511234.29 | AD52: =E52*$AD$1 -> 577636.1 | AE52: =VLOOKUP(B52,[4]Лист_1!$A$5:$D$59,3,0) -> 492378.1 | AF52: =E52*$AF$1 -> 592837.05 | AG52: =VLOOKUP(B52,[5]Лист_1!$A$3:$C$50,3,0) -> 533752.38 | AH52: =G52*$AF$1 -> 164674.71 | AI52: =VLOOKUP(B52,[29]Лист_1!$A$5:$C$67,3,0) -> 367433.81
A53: =A52+1 -> 47 | B53: ПРОФИТАТОР ООО | C53: Кокос | E53: 15600 | F53: =E53*$F$1 -> 15132 | H53: =G53-F53 -> -15132 | I53: =E53*$I$1 -> 15132 | K53: =J53-I53 -> -15132 | N53: =E53*$N$1 -> 16380 | O53: 10400 | P53: =E53*$P$1 -> 16848
A54: =A53+1 -> 48 | B54: Публичное акционерное общество "ПИК - специализированный застройщик" | C54: Пик | D54: 3 | E54: 29037.5 | F54: =E54*$F$1 -> 28166.375 | H54: =G54-F54 -> -28166.375 | I54: =E54*$I$1 -> 28166.375 | J54: 30000 | K54: =J54-I54 -> 1833.625 | L54: 17825 | N54: =E54*$N$1 -> 30489.375 | O54: 21850 | P54: =E54*$P$1 -> 31360.5 | Q54: 10235 | R54: =E54*$R$1 -> 29327.875
A55: =A54+1 -> 49 | B55: ПУЛЬС ООО СК | C55: СК Пульс | E55: 17600 | F55: =E55*$F$1 -> 17072 | H55: =G55-F55 -> -17072 | I55: =E55*$I$1 -> 17072 | K55: =J55-I55 -> -17072 | N55: =E55*$N$1 -> 18480 | P55: =E55*$P$1 -> 19008 | R55: =E55*$R$1 -> 17776
A56: =A55+1 -> 50 | B56: РОСГОССТРАХ ПАО СК | C56: Пульс | O56: 17286 | R56: =E56*$R$1 -> 0 | S56: =VLOOKUP(B56,[2]Лист_1!$A$1:$C$65536,3,0) -> 70714.286 | T56: =I56*$T$1 -> 0 | W56: =VLOOKUP(B56,[3]Лист_1!$A$5:$F$55,4,0) -> 154000 | X56: 7699.99 | Y56: =E56*$Y$1 -> 0 | Z56: =VLOOKUP(B56,[6]Лист_1!$C$5:$E$64,3,0) -> 73857.143 | AC56: =VLOOKUP(B56,[7]Лист_1!$A$3:$E$57,4,0) -> 83285.714 | AD56: =E56*$AD$1 -> 0 | AE56: =VLOOKUP(B56,[4]Лист_1!$A$5:$D$59,3,0) -> 53428.571 | AG56: =VLOOKUP(B56,[5]Лист_1!$A$3:$C$50,3,0) -> 6285.7143
A57: =A55+1 -> 50 | B57: ПРОГРЕСС ГРУПП ООО | G57: =VLOOKUP(B57,[1]Лист_1!$A$1:$G$65536,7,0) -> 27000 | H57: =G57-F57 -> 27000 | I57: =E57*$I$1 -> 0 | K57: =J57-I57 -> 0 | N57: =E57*$N$1 -> 0 | R57: =E57*$R$1 -> 0 | T57: =I57*$T$1 -> 0 | Y57: =E57*$Y$1 -> 0
A58: =A57+1 -> 51 | B58: РОКВУЛ ООО | D58: 1 | E58: 36014 | F58: =E58*$F$1 -> 34933.58 | G58: =VLOOKUP(B58,[1]Лист_1!$A$1:$G$65536,7,0) -> 82302 | H58: =G58-F58 -> 47368.42 | I58: =E58*$I$1 -> 34933.58 | J58: 10000 | K58: =J58-I58 -> -24933.58 | L58: 95348 | N58: =E58*$N$1 -> 37814.7 | O58: 42482 | P58: =E58*$P$1 -> 38895.12 | Q58: 176264 | R58: =E58*$R$1 -> 36374.14 | S58: =VLOOKUP(B58,[2]Лист_1!$A$1:$C$65536,3,0) -> 190586 | T58: =I58*$T$1 -> 32488.229 | U58: 200244 | V58: =E58*$V$1 -> 34933.58 | W58: =VLOOKUP(B58,[3]Лист_1!$A$5:$F$55,4,0) -> 62502 | X58: =VLOOKUP(B58,[3]Лист_1!$A$5:$D$54,3,0) -> 3125.1 | Y58: =E58*$Y$1 -> 35653.86 | Z58: 34166 | AB58: =E58*$AB$1 -> 39975.54 | AC58: =VLOOKUP(B58,[7]Лист_1!$A$3:$E$57,4,0) -> 40106 | AD58: =E58*$AD$1 -> 41055.96 | AE58: =VLOOKUP(B58,[4]Лист_1!$A$5:$D$59,3,0) -> 79860 | AF58: =E58*$AF$1 -> 42136.38 | AG58: =VLOOKUP(B58,[5]Лист_1!$A$3:$C$50,3,0) -> 107756 | AH58: =G58*$AF$1 -> 96293.34 | AI58: =VLOOKUP(B58,[29]Лист_1!$A$5:$C$67,3,0) -> 45452
A59: =A58+1 -> 52 | B59: РУТА АО | C59: labquest.ru | D59: 1 | E59: 282678.75 | F59: =E59*$F$1 -> 274198.39 | G59: =VLOOKUP(B59,[1]Лист_1!$A$1:$G$65536,7,0) -> 248600 | H59: =G59-F59 -> -25598.388 | I59: =E59*$I$1 -> 274198.39 | J59: 300000 | K59: =J59-I59 -> 25801.612 | L59: 286800 | N59: =E59*$N$1 -> 296812.69 | O59: 348000 | P59: =E59*$P$1 -> 305293.05 | Q59: 374550 | R59: =E59*$R$1 -> 285505.54 | S59: =VLOOKUP(B59,[2]Лист_1!$A$1:$C$65536,3,0) -> 140950 | T59: =I59*$T$1 -> 255004.5 | U59: 148300 | V59: =E59*$V$1 -> 274198.39 | W59: =VLOOKUP(B59,[3]Лист_1!$A$5:$F$55,4,0) -> 64820 | X59: =VLOOKUP(B59,[3]Лист_1!$A$5:$D$54,3,0) -> 3241 | Y59: =E59*$Y$1 -> 279851.96 | AC59: =VLOOKUP(B59,[7]Лист_1!$A$3:$E$57,4,0) -> 102977 | AD59: =E59*$AD$1 -> 322253.77 | AE59: =VLOOKUP(B59,[4]Лист_1!$A$5:$D$59,3,0) -> 8250 | AF59: =E59*$AF$1 -> 330734.14 | AG59: =VLOOKUP(B59,[5]Лист_1!$A$3:$C$50,3,0) -> 22980 | AH59: =G59*$AF$1 -> 290862 | AI59: 150000
A60: =A59+1 -> 53 | B60: СЗ БИЗНЕС ПАРК ОСТАНКИНО ООО | C60: Пионер | D60: 1 | E60: 25929.167 | F60: =E60*$F$1 -> 25151.292 | G60: =VLOOKUP(B60,[1]Лист_1!$A$1:$G$65536,7,0) -> 28470 | H60: =G60-F60 -> 3318.7083 | I60: =E60*$I$1 -> 25151.292 | J60: 100000 | K60: -53400 | L60: 20950 | N60: =E60*$N$1 -> 27225.625 | O60: 156179 | P60: =E60*$P$1 -> 28003.5 | Q60: 120672 | R60: =E60*$R$1 -> 26188.458 | Y60: =E60*$Y$1 -> 25669.875 | Z60: 108601 | AB60: =E60*$AB$1 -> 28781.375 | AC60: =VLOOKUP(B60,[7]Лист_1!$A$3:$E$57,4,0) -> 44213 | AD60: =E60*$AD$1 -> 29559.25
A61: =A60+1 -> 54 | B61: СЗ ЛАЙФ ПАВЕЛЕЦКАЯ АО | C61: Пионер | E61: 83183.333 | F61: =E61*$F$1 -> 80687.833 | G61: =VLOOKUP(B61,[1]Лист_1!$A$1:$G$65536,7,0) -> 70400 | H61: =G61-F61 -> -10287.833 | I61: =E61*$I$1 -> 80687.833 | L61: 130005 | N61: =E61*$N$1 -> 87342.5 | P61: =E61*$P$1 -> 89838 | R61: =E61*$R$1 -> 84015.167 | Y61: =E61*$Y$1 -> 82351.5 | AB61: =E61*$AB$1 -> 92333.5 | AC61: =VLOOKUP(B61,[7]Лист_1!$A$3:$E$57,4,0) -> 87101 | AD61: =E61*$AD$1 -> 94829 | AE61: 164966 | AF61: =E61*$AF$1 -> 97324.5 | AG61: =VLOOKUP(B61,[5]Лист_1!$A$3:$C$50,3,0) -> 66228 | AH61: =G61*$AF$1 -> 82368 | AI61: 136329
A62: =A61+1 -> 55 | B62: СЗ ПИОНЕР-1 ООО | C62: Пионер | E62: 31804.167 | F62: =E62*$F$1 -> 30850.042 | G62: =VLOOKUP(B62,[1]Лист_1!$A$1:$G$65536,7,0) -> 68495 | H62: =G62-F62 -> 37644.958 | I62: =E62*$I$1 -> 30850.042 | L62: 20950 | N62: =E62*$N$1 -> 33394.375 | P62: =E62*$P$1 -> 34348.5 | R62: =E62*$R$1 -> 32122.208 | U62: 121535 | V62: 147142 | W62: 90875 | X62: 4543.75 | Y62: =E62*$Y$1 -> 31486.125 | AB62: =E62*$AB$1 -> 35302.625 | AC62: =VLOOKUP(B62,[7]Лист_1!$A$3:$E$57,4,0) -> 25740 | AD62: =E62*$AD$1 -> 36256.75 | AG62: =VLOOKUP(B62,[5]Лист_1!$A$3:$C$50,3,0) -> 26197
A63: =A62+1 -> 56 | B63: СЗ ШИФТ ООО | C63: Пионер | E63: 17300 | F63: =E63*$F$1 -> 16781 | H63: =G63-F63 -> -16781 | I63: =E63*$I$1 -> 16781 | L63: 25779 | N63: =E63*$N$1 -> 18165 | P63: =E63*$P$1 -> 18684 | R63: =E63*$R$1 -> 17473 | S63: 116938 | T63: =I63*$T$1 -> 15606.33 | Y63: =E63*$Y$1 -> 17127 | AB63: =E63*$AB$1 -> 19203 | AD63: =E63*$AD$1 -> 19722
A64: =A63+1 -> 57 | B64: САМОЛЕТ-ГОСТЕПРИИМСТВО ООО | S64: =34200+9614.35 -> 43814.35 | T64: =I64*$T$1 -> 0 | U64: 11400 | Y64: =E64*$Y$1 -> 0 | AE64: =VLOOKUP(B64,[4]Лист_1!$A$5:$D$59,3,0) -> 17100 | AI64: =VLOOKUP(B64,[29]Лист_1!$A$5:$C$67,3,0) -> 11400
A65: =A64+1 -> 58 | B65: ТЕХНОНИКОЛЬ-СТРОИТЕЛЬНЫЕ СИСТЕМЫ ООО | C65: Технониколь | E65: 147325 | F65: =E65*$F$1 -> 142905.25 | H65: =G65-F65 -> -142905.25 | I65: =E65*$I$1 -> 142905.25 | K65: =J65-I65 -> -142905.25 | L65: 114300 | N65: =E65*$N$1 -> 154691.25 | O65: 118350 | P65: =E65*$P$1 -> 159111 | Q65: 197150 | R65: =E65*$R$1 -> 148798.25 | S65: =VLOOKUP(B65,[2]Лист_1!$A$1:$C$65536,3,0) -> 162250 | T65: =I65*$T$1 -> 132901.88 | Y65: =E65*$Y$1 -> 145851.75
A66: =A65+1 -> 59 | B66: ФГБУК "Государственный академический Большой театр России" | C66: Большой театр | D66: 5 | E66: 17250 | F66: =E66*$F$1 -> 16732.5 | G66: =VLOOKUP(B66,[1]Лист_1!$A$1:$G$65536,7,0) -> 18975 | H66: =G66-F66 -> 2242.5 | I66: =E66*$I$1 -> 16732.5 | J66: 18975 | K66: =J66-I66 -> 2242.5 | L66: 21086.667 | N66: =E66*$N$1 -> 18112.5 | O66: 21086.667 | P66: =E66*$P$1 -> 18630 | Q66: 21086.667 | R66: =E66*$R$1 -> 17422.5 | S66: =VLOOKUP(B66,[2]Лист_1!$A$1:$C$65536,3,0) -> 21086.667 | T66: =I66*$T$1 -> 15561.225 | U66: 25605.238 | V66: =E66*$V$1 -> 16732.5 | W66: =[3]Лист_1!$D$15 -> 15061.905 | X66: 753.1 | Y66: =E66*$Y$1 -> 17077.5 | Z66: 6845.24 | AB66: =E66*$AB$1 -> 19147.5 | AC66: 15061.9 | AD66: =E66*$AD$1 -> 19665 | AE66: 22593 | AF66: =E66*$AF$1 -> 20182.5 | AG66: 30123.81 | AH66: =G66*$AF$1 -> 22200.75 | AI66: 22592.86
A67: =A66+1 -> 60 | B67: ФЕРСТ ДАТА ООО | C67: Beko, Indesit, Grundig, Hotpoint | E67: 214326.67 | F67: =E67*$F$1 -> 207896.87 | H67: =G67-F67 -> -207896.87 | I67: =E67*$I$1 -> 207896.87 | K67: =J67-I67 -> -207896.87 | N67: 0 | O67: 19333.333
A68: =A67+1 -> 61 | B68: ХЕНДЭ МОТОР СНГ ООО | C68: Hyundai | D68: 1 | E68: 30763.333 | F68: =E68*$F$1 -> 29840.433 | G68: =VLOOKUP(B68,[1]Лист_1!$A$1:$G$65536,7,0) -> 15100 | H68: =G68-F68 -> -14740.433 | I68: =E68*$I$1 -> 29840.433 | J68: 10000 | K68: =J68-I68 -> -19840.433 | L68: 62440 | N68: =E68*$N$1 -> 32301.5 | O68: 35300 | P68: =E68*$P$1 -> 33224.4 | Q68: 51500 | R68: =E68*$R$1 -> 31070.967 | S68: =VLOOKUP(B68,[2]Лист_1!$A$1:$C$65536,3,0) -> 42069 | T68: =I68*$T$1 -> 27751.603 | U68: 48180 | V68: =E68*$V$1 -> 29840.433 | W68: =VLOOKUP(B68,[3]Лист_1!$A$5:$F$55,4,0) -> 34570 | X68: =VLOOKUP(B68,[3]Лист_1!$A$5:$D$54,3,0) -> 1728.5 | Y68: =E68*$Y$1 -> 30455.7 | Z68: =VLOOKUP(B68,[6]Лист_1!$C$5:$E$64,3,0) -> 42040 | AB68: =E68*$AB$1 -> 34147.3 | AC68: =VLOOKUP(B68,[7]Лист_1!$A$3:$E$57,4,0) -> 22200 | AD68: =E68*$AD$1 -> 35070.2 | AF68: =E68*$AF$1 -> 35993.1 | AH68: =G68*$AF$1 -> 17667 | AI68: =VLOOKUP(B68,[29]Лист_1!$A$5:$C$67,3,0) -> 18630
A69: =A68+1 -> 62 | B69: Циммер Евгения Владимировна | C69: аврора 24 | E69: 16876.5 | F69: =E69*$F$1 -> 16370.205 | H69: =G69-F69 -> -16370.205 | I69: =E69*$I$1 -> 16370.205 | K69: =J69-I69 -> -16370.205 | N69: =E69*$N$1 -> 17720.325 | P69: =E69*$P$1 -> 18226.62
A70: =A69+1 -> 63 | B70: ЮМАНИ ООО НКО | L70: 1447.5 | R70: =E70*$R$1 -> 0 | T70: =I70*$T$1 -> 0 | Y70: =E70*$Y$1 -> 0 | AD70: =E70*$AD$1 -> 0
A71: =A70+1 -> 64 | B71: ЯНДЕКС МУЗЫКА ООО | C71: Яндекс | D71: 5 | E71: 229800 | F71: =E71*$F$1 -> 222906 | G71: =VLOOKUP(B71,[1]Лист_1!$A$1:$G$65536,7,0) -> 54500 | H71: =G71-F71 -> -168406 | I71: =E71*$I$1 -> 222906 | J71: 200000 | K71: =J71-I71 -> -22906 | L71: 92400 | N71: =E71*$N$1 -> 241290 | O71: 221900 | P71: =E71*$P$1 -> 248184 | Q71: 135200 | R71: =E71*$R$1 -> 232098 | S71: =VLOOKUP(B71,[2]Лист_1!$A$1:$C$65536,3,0) -> 168800 | T71: =I71*$T$1 -> 207302.58 | U71: 85500 | V71: =E71*$V$1 -> 222906 | W71: =VLOOKUP(B71,[3]Лист_1!$A$5:$F$55,4,0) -> 128000 | X71: =VLOOKUP(B71,[3]Лист_1!$A$5:$D$54,3,0) -> 6400 | Y71: =E71*$Y$1 -> 227502 | Z71: 161400 | AB71: =E71*$AB$1 -> 255078 | AC71: =VLOOKUP(B71,[7]Лист_1!$A$3:$E$57,4,0) -> 158600 | AD71: =E71*$AD$1 -> 261972 | AE71: 265285.71 | AF71: =E71*$AF$1 -> 268866 | AG71: 238200 | AH71: =G71*$AF$1 -> 63765 | AI71: =VLOOKUP(B71,[29]Лист_1!$A$5:$C$67,3,0) -> 278000
A72: =A71+1 -> 65 | B72: ЮМАК ООО | C72: Umac | S72: =VLOOKUP(B72,[2]Лист_1!$A$1:$C$65536,3,0) -> 91588.267 | T72: =I72*$T$1 -> 0 | Y72: =E72*$Y$1 -> 0 | AD72: =E72*$AD$1 -> 0
A73: =A72+1 -> 66 | B73: РЭКФОРК ООО | C73: Linde | S73: =VLOOKUP(B73,[2]Лист_1!$A$1:$C$65536,3,0) -> 145714.29 | T73: =I73*$T$1 -> 0 | Y73: =E73*$Y$1 -> 0 | AD73: =E73*$AD$1 -> 0 | AI73: =VLOOKUP(B73,[29]Лист_1!$A$5:$C$67,3,0) -> 284952.38
A74: =A73+1 -> 67 | B74: МОБИЛЬНАЯ КАРТА ООО НКО | C74: Цупис | V74: 200000 | W74: 242321.55 | X74: 12116.03 | Y74: 200000 | Z74: 201584.06 | AC74: =VLOOKUP(B74,[7]Лист_1!$A$3:$E$57,4,0) -> 93375.314 | AD74: =E74*$AD$1 -> 0
A75: =A74+1 -> 68 | B75: ООО "РА "СА Медиа" | C75: Алроса | S75: 132250 | T75: =I75*$T$1 -> 0 | U75: 59050 | W75: 59050 | X75: 0 | Y75: =E75*$Y$1 -> 0 | AD75: =E75*$AD$1 -> 0 | AI75: 128150
A76: =A75+1 -> 69 | B76: ЛАБОРАТОРИЯ КАСПЕРСКОГО АО | C76: Лаборатория касперского | AI76: =VLOOKUP(B76,[29]Лист_1!$A$5:$C$67,3,0) -> 187200
A77: =A76+1 -> 70 | B77: ИП Гришин | C77: Феотон | U77: 128600 | Y77: =E77*$Y$1 -> 0 | AD77: =E77*$AD$1 -> 0
E78: =SUM(E4:E71) -> 10479531 | F78: =SUM(F4:F71) -> 10165146 | G78: =SUM(G4:G71) -> 8477722.7 | H78: =SUM(H4:H71) -> -1687422.8 | I78: =SUM(I4:I71) -> 10216230 | J78: =SUM(J4:J71) -> 8050890 | K78: =SUM(K4:K71) -> -2165270.7 | L78: 8583947.3 | N78: =SUM(N4:N71) -> 10764749 | O78: 8987414.3 | P78: =SUM(P4:P71) -> 10375632 | Q78: =SUM(Q4:Q71) -> 9814327.9 | R78: =SUM(R4:R71) -> 9896769.5 | S78: =SUM(S4:S75) -> 9934360.9 | T78: =SUM(T4:T71) -> 8064280 | U78: =SUM(U4:U77) -> 8150692.4 | V78: =SUM(V4:V42) -> 6143136.6 | W78: =SUM(W4:W77) -> 8346684.2 | Y78: =SUM(Y4:Y42) -> 6050394.4 | Z78: =SUM(Z4:Z77) -> 7048368.3 | AB78: =SUM(AB4:AB42) -> 6172100 | AC78: =SUM(AC4:AC77) -> 7264562 | AD78: =SUM(AD4:AD42) -> 5936962.8 | AE78: =SUM(AE4:AE77) -> 7420532.8 | AF78: =SUM(AF4:AF42) -> 5998703.8 | AG78: =SUM(AG4:AG77) -> 7546009.7 | AH78: =SUM(AH4:AH42) -> 6075227.9 | AI78: =SUM(AI4:AI77) -> 9479767.7
C79: Сокращение чека по проектам | G79: =COUNT(G4:G71) -> 43 | H79: =H12+H15+H21+H29+H30+H36+H37+H43+H52+H65+H67+H71+H48 -> -2709301.5 | K79: =K7+K11+K15+K21+K26+K30+K37++K48+K52+K58+K65+K67 -> -1767560.1 | L79: 43
C80: Количество проектов | F80: =COUNT(F4:F71) -> 53 | G80: =COUNT(G4:G71) -> 43 | I80: =COUNT(I4:I71) -> 55 | L80: 43 | O80: 45 | Q80: =COUNT(Q4:Q71) -> 40 | S80: =COUNT(S4:S71) -> 37 | U80: =COUNT(U4:U75) -> 37 | W80: =COUNT(W4:W77) -> 36 | Z80: =COUNT(Z4:Z77) -> 35 | AC80: =COUNT(AC4:AC77) -> 36 | AE80: =COUNT(AE4:AE77) -> 34 | AG80: =COUNT(AG4:AG77) -> 31 | AI80: =COUNT(AI4:AI77) -> 36
C81: Средний чек | F81: =F78/F80 -> 191795.2 | G81: =G78/G80 -> 197156.34 | I81: =I78/I80 -> 185749.64 | L81: 199593.02 | O81: 199720.32 | Q81: =Q78/Q80 -> 245358.2 | S81: =S78/S80 -> 268496.24 | U81: =U78/U80 -> 220288.99 | W81: =W78/W80 -> 231852.34 | Z81: =Z78/Z80 -> 201381.95 | AC81: =AC78/AC80 -> 201793.39 | AE81: =AE78/AE80 -> 218250.97 | AG81: =AG78/AG80 -> 243419.67 | AI81: =AI78/AI80 -> 263326.88
C83: НОВЫЕ ПРОЕКТЫ ЕМС | L83: 176800 | O83: 380485 | Q83: =SUM(Q84:Q125) -> 685695.48 | S83: =SUM(S84:S125) -> 364342 | U83: =SUM(U84:U125) -> 604575.51 | W83: =SUM(W84:W125) -> 1674336.2 | Z83: =SUM(Z84:Z125) -> 2783075.5 | AC83: =SUM(AC84:AC125) -> 2940865.3 | AE83: =SUM(AE84:AE125) -> 3410570.7 | AG83: =SUM(AG84:AG125) -> 2909900 | AI83: =SUM(AI84:AI125) -> 4739674
A84: 1 | B84: Эпл Даймонд | C84: Эпл Даймонд | J84: 30000
A85: =A84+1 -> 2 | B85: Лаборатория касперского | C85: Лаборатория касперского | J85: 16380
A86: =A85+1 -> 3 | B86: ЛИДЕРЫ МНЕНИЙ ООО | L86: 76800
A87: =A86+1 -> 4 | B87: АЙТИБ ООО | C87: hostkey | O87: 96915 | Q87: 188763 | S87: =VLOOKUP(B87,[2]Лист_1!$A$1:$C$65536,3,0) -> 93263 | U87: 106180 | W87: =VLOOKUP(B87,[3]Лист_1!$A$5:$F$54,4,0) -> 124050 | X87: =VLOOKUP(B87,[3]Лист_1!$A$5:$D$54,3,0) -> 6202.5 | Z87: 159790 | AC87: =VLOOKUP(B87,[7]Лист_1!$A$3:$E$56,4,0) -> 106180 | AE87: =VLOOKUP(B87,[4]Лист_1!$A$5:$D$59,3,0) -> 106180 | AG87: =VLOOKUP(B87,[5]Лист_1!$A$3:$C$50,3,0) -> 106180 | AI87: =VLOOKUP(B87,[29]Лист_1!$A$5:$C$68,3,0) -> 177625.8
A88: =A87+1 -> 5 | B88: БЕКО ООО | C88: Grundig | O88: 67900 | Q88: 20700
A89: =A88+1 -> 6 | B89: НПФ ГАЗФОНД ПЕНСИОННЫЕ НАКОПЛЕНИЯ АО | C89: Газфонд | O89: 23786 | Z89: 75013.86 | AC89: =VLOOKUP(B89,[7]Лист_1!$A$3:$E$56,4,0) -> 59132.381 | AE89: =VLOOKUP(B89,[4]Лист_1!$A$5:$D$59,3,0) -> 33065.238 | AG89: =VLOOKUP(B89,[5]Лист_1!$A$3:$C$50,3,0) -> 45419.524
A90: =A89+1 -> 7 | B90: ЦИФРОВОЙ СЕРВИС ООО | C90: PEDANT.RU | O90: 26667
A91: =A90+1 -> 8 | B91: ООО "СЗ "РЕЗЕДЕНЦИЯ РОЩИНО" | C91: Рощино | O91: 139775 | Q91: 98083
A92: =A91+1 -> 9 | B92: ООО "ЭСТРЕЛЬ" | C92: Thai rooms | O92: 25442
A93: =A92+1 -> 10 | B93: СРП ГРУПП ООО | Q93: 265277.33 | S93: =VLOOKUP(B93,[2]Лист_1!$A$1:$C$65536,3,0) -> 109779 | U93: 128545.51 | W93: =VLOOKUP(B93,[3]Лист_1!$A$5:$F$54,4,0)+213800 -> 456404.91 | X93: =VLOOKUP(B93,[3]Лист_1!$A$5:$D$54,3,0) -> 12130.246 | AG93: =VLOOKUP(B93,[5]Лист_1!$A$3:$C$50,3,0) -> 131906.71
A94: =A93+1 -> 11 | B94: КЛЕВЕР-МЕДИА-ГРУПП ООО | Q94: 70757.143
A95: =A94+1 -> 12 | B95: ШУЕВ НИКОЛАЙ СЕРГЕЕВИЧ ИП | C95: Kusto | Q95: 42115 | AC95: 144222
A96: =A95+1 -> 13 | B96: НОВАРТИС ФАРМА ООО | S96: =VLOOKUP(B96,[2]Лист_1!$A$1:$C$65536,3,0) -> 41300 | U96: 41300 | W96: =VLOOKUP(B96,[3]Лист_1!$A$5:$F$54,4,0) -> 93316.505 | X96: =VLOOKUP(B96,[3]Лист_1!$A$5:$D$54,3,0) -> 4665.8252 | Z96: 29500 | AC96: =VLOOKUP(B96,[7]Лист_1!$A$3:$E$56,4,0)+92200 -> 139550 | AE96: =VLOOKUP(B96,[4]Лист_1!$A$5:$D$59,3,0) -> 85190 | AG96: =VLOOKUP(B96,[5]Лист_1!$A$3:$C$50,3,0) -> 88435 | AI96: =VLOOKUP(B96,[29]Лист_1!$A$5:$C$68,3,0) -> 92815
A97: =A96+1 -> 14 | B97: ЦЕНТР ПКС ООО | W97: =VLOOKUP(B97,[3]Лист_1!$A$5:$F$54,4,0) -> 37906 | X97: =VLOOKUP(B97,[3]Лист_1!$A$5:$D$54,3,0) -> 1895.3
A98: =A97+1 -> 15 | B98: ЦЕМЕНТУМ ЦЕНТР ООО | S98: 120000 | W98: =VLOOKUP(B98,[3]Лист_1!$A$5:$F$54,4,0) -> 211754.15 | X98: =VLOOKUP(B98,[3]Лист_1!$A$5:$D$54,3,0) -> 10587.708 | Z98: 187269.78 | AC98: =VLOOKUP(B98,[7]Лист_1!$A$3:$E$56,4,0) -> 189305.48 | AE98: =VLOOKUP(B98,[4]Лист_1!$A$5:$D$59,3,0) -> 157959.8 | AG98: =VLOOKUP(B98,[5]Лист_1!$A$3:$C$50,3,0) -> 125109.37 | AI98: =VLOOKUP(B98,[29]Лист_1!$A$5:$C$68,3,0) -> 143392.69
A99: =A98+1 -> 16 | B99: Анциферов Денис Иванович | C99: Нильсон Авто | Z99: 134340
A100: =A99+1 -> 17 | B100: Мидиан ООО | C100: Гудгейм | Z100: 101518 | AG100: =VLOOKUP(B100,[5]Лист_1!$A$3:$C$50,3,0) -> 119880.95 | AI100: =VLOOKUP(B100,[29]Лист_1!$A$5:$C$68,3,0) -> 10411.429
A101: =A100+1 -> 18 | B101: ЭМДЖИКОМ ООО | C101: Снежная королева | Z101: 190476.19 | AI101: =VLOOKUP(B101,[29]Лист_1!$A$5:$C$68,3,0) -> 492938.65
...

Sheet База расходы
I1: Текущий курс
G2: 1 | H2: 101 | I2: 104 | J2: 35.61
A3: Источник затрат | B3: Расшифровка услуги | C3: Наименование поставщика | D3: Юр. лицо поставщика | E3: Оплата мес. пропорционально году с конвертацией в руб. | F3: Оплата год/ конвертация в руб. | G3: Оплата, руб/мес | H3: Оплата, $/мес | I3: Оплата,€/мес | J3: Оплата, ₾/мес | K3: Итого | L3: ЯНВАРЬ | M3: ИТОГО ЯНВАРЬ | N3: ФЕВРАЛЬ | O3: ИТОГО ФЕВРАЛЬ | P3: МАРТ | Q3: ИТОГО МАРТ | R3: АПРЕЛЬ | S3: ИТОГО АПРЕЛЬ | T3: МАЙ | U3: ИТОГО МАЙ | V3: ИЮНЬ | W3: ИТОГО ИЮНЬ | X3: ИЮЛЬ | Y3: ИТОГО ИЮЛЬ | Z3: АВГУСТ | AA3: ИТОГО АВГУСТ | AB3: СЕНТЯБРЬ | AC3: ИТОГО СЕНТЯБРЬ | AD3: ОКТЯБРЬ | AE3: ИТОГО ОКТЯБРЬ | AF3: НОЯБРЬ | AG3: ИТОГО НОЯБРЬ | AH3: ДЕКАБРЬ | AI3: ИТОГО ДЕКАБРЬ
A4: ПО организационные офис | B4: для всех | C4: Яндекс | D4: ЯНДЕКС ООО | E4: =G4 -> 25000 | F4: =E4*12 -> 300000 | G4: 25000 | K4: =SUM(G4:G24) -> 240568.95 | L4: 23817.61 | M4: =SUM(L4:L24) -> 197214.95 | N4: =23232.97+2.69 -> 23235.66 | O4: =SUM(N4:N24) -> 281809.81 | P4: =24017.93+2.98 -> 24020.91 | Q4: =SUM(P4:P24) -> 299050.64 | R4: =24421.09+2.88 -> 24423.97 | S4: =SUM(R4:R24) -> 264785.72 | T4: 42226.23 | U4: =SUM(T4:T24) -> 157722.3 | V4: =40671.51+3.11 -> 40674.62 | W4: =SUM(V4:V24) -> 70543.94 | X4: 41336 | Y4: =SUM(X4:X24) -> 61345.82 | Z4: =42768+3.21 -> 42771.21 | AA4: =SUM(Z4:Z24) -> 142293.33 | AB4: 38978 | AC4: =SUM(AB4:AB24) -> 148400.12 | AD4: 40469.3 | AE4: =SUM(AD4:AD24) -> 109991.42 | AF4: =39665+3.11 -> 39668.11 | AG4: =SUM(AF4:AF24) -> 383672.56 | AH4: 39346.76 | AI4: =SUM(AH4:AH24) -> 228482.64
B5: для всех | C5: Планфикс | D5: ООО "Сфера" | E5: 80000 | F5: =E5*12 -> 960000 | G5: 80000 | L5: 75720 | N5: 75720 | P5: 75720 | R5: 75720 | T5: 75720 | V5: 9268.8
B6: для всех | D6: ООО "Цифровое облако" | X6: 5000 | Z6: 80000 | AB6: 50000 | AD6: 50000 | AF6: 53894.44 | AH6: 78582.93
B7: для всех | C7: Дискорд | D7: Дискорд | E7: =G7 -> 1008.99 | F7: =E7*12 -> 12107.88 | G7: =H7*H2 -> 1008.99 | H7: 9.99 | L7: 0 | N7: 968.13 | P7: 890.51 | R7: 0 | T7: 0 | V7: 0 | X7: 0 | Z7: 0 | AB7: 0 | AD7: 0 | AF7: 0 | AH7: 0
B8: для всех | C8: пинтест | D8: СКБ-СОФТ | AF8: 125000 | AH8: 0
B9: для всех | C9: EmailMaker | D9: БЛОЧНЫЙ РЕДАКТОР ООО | E9: =F9/12 -> 6800 | F9: 81600 | G9: =E9 -> 6800 | L9: 6800 | N9: 6800 | P9: 6800 | R9: 6800 | T9: 20400 | V9: 0 | X9: 0 | Z9: 6800 | AB9: 6800 | AD9: 6800 | AF9: 6800 | AH9: 6800
B10: онлайн-доска | C10: Miro | D10: Miro | E10: =G10 -> 3030 | F10: =E10*12 -> 36360 | G10: =H10*H2 -> 3030 | H10: 30 | L10: 1942.6 | N10: 3131.45 | P10: 906.73 | T10: 1594.2 | V10: 1.2 | X10: 1594.2 | Z10: 5617.8 | AB10: 5617.8 | AD10: 5617.8 | AF10: 4117.6 | AH10: 1639.8
B11: Нейросеть | C11: Chat GPT | D11: Chat GPT | E11: =G11 -> 2020 | F11: =E11*12 -> 24240 | G11: =H11*H2 -> 2020 | H11: 20 | L11: 1956.2 | N11: 1728.8 | P11: =1782.8+1644.83+1710 -> 5137.63 | R11: =1558.38 -> 1558.38 | T11: =1536.34 -> 1536.34 | V11: =1646.82+1646.82 -> 3293.64 | X11: 3282.09 | Z11: 3630.27 | AB11: 3630.27 | AD11: 3630.27 | AF11: 5414.44 | AH11: 5359.69
B12: нейросеть по созданию картинок | C12: Midjourney | D12: Midjourney | E12: =G12 -> 2424 | F12: =E12*12 -> 29088 | G12: =H12*H2 -> 2424 | H12: 24 | L12: 0 | N12: 0 | P12: 0 | R12: 0 | T12: 0 | V12: 1882.08 | X12: 1882.08 | Z12: 1882.08 | AB12: 1882.08 | AD12: 1882.08 | AF12: 1882.08 | AH12: 1882.08
B13: платформа д/проведения онлайн-встречь | C13: zoom д/Вани | D13: zoom | E13: =G13 -> 1786.69 | F13: =E13*12 -> 21440.28 | G13: =H13*H2 -> 1786.69 | H13: 17.69 | L13: 0 | N13: 0 | P13: 0 | R13: 0 | T13: 0 | V13: 1572.32 | X13: 0 | Z13: 1590.77 | AB13: 1590.77 | AD13: 1590.77 | AF13: =1682.2+926.49 -> 2608.69 | AH13: 1671.78
B14: база данных | C14: ноушн д/Вани | D14: Notion | E14: =G14 -> 1273.61 | F14: =E14*12 -> 15283.32 | G14: =H14*H2 -> 1273.61 | H14: 12.61 | L14: 0 | N14: 0 | P14: 0 | R14: 0 | T14: 0 | V14: 0 | X14: 0 | Z14: 0 | AB14: 0 | AD14: 0 | AF14: 0 | AH14: 0
B15: для всех | C15: GOOGLE | D15: GOOGLE | E15: =G15 -> 1008.99 | F15: =E15*12 -> 12107.88 | G15: =H15*H2 -> 1008.99 | H15: 9.99 | L15: =1023.11+970.33 -> 1993.44 | N15: 880.82 | P15: 841.06 | R15: 0 | T15: 796.3 | V15: 783.42 | X15: 782.52 | Z15: 0 | AB15: 0 | AD15: 0 | AF15: 812.49 | AH15: 798.5
B16: биллинг Лидплана | C16: Прайсплан | D16: ЭДМИН ООО | E16: =F16/12 -> 3216.6667 | F16: 38600 | G16: =E16 -> 3216.6667
C17: Майндбокс | L17: 1.2 | N17: 1.2 | P17: 1.2 | R17: 1.2 | T17: =1.2+500 -> 501.2 | V17: 1.2 | X17: 1.2 | Z17: 1.2 | AB17: 1.2 | AD17: 1.2 | AF17: 1.2 | AH17: 1.2
B18: Сертификат 1-С Битрикс | C18: Савкин Т.А. ИП | D18: Савкин Т.А. ИП | N18: =43128/12 -> 3594 | P18: 0 | R18: 0 | T18: 0 | V18: 0 | X18: 0 | Z18: 0 | AB18: 39900 | AD18: 0 | AF18: 134000 | AH18: 91580
B19: для Вани | D19: папдл нет/крафтдокс | T19: 948.03 | V19: 0 | X19: 0 | Z19: 0 | AB19: 0 | AD19: 0 | AF19: 0 | AH19: 0
C20: Битрикс | G20: 100000 | L20: 75000 | N20: 150459.75 | P20: 169740 | R20: 128965.5
D21: Центр развития экономики | R21: 14000
C22: прочие сервисы карта | AF22: 9473.51 | AH22: 819.9
B23: сервис Monk | D23: нал | N23: 1290 | P23: 992.6 | R23: 0 | T23: 0 | V23: 0 | X23: 0 | Z23: 0 | AB23: 0 | AD23: 0 | AF23: 0 | AH23: 0
B24: агрегатор мессенджеров | C24: chat2desk | D24: ИТ Проспект ООО | E24: =G24 -> 13000 | F24: =E24*12 -> 156000 | G24: 13000 | L24: 9983.9 | N24: 14000 | P24: 14000 | R24: 13316.67 | T24: 14000 | V24: 13066.66 | X24: 7467.73 | Z24: 0 | AB24: 0 | AD24: 0 | AF24: 0 | AH24: 0
A25: ПО организационные HR | B25: объявления на сайте | C25: Хэдхантер | D25: "Хэдхантер" ООО | E25: =G25 -> 20000 | F25: =E25*12 -> 240000 | G25: 20000 | K25: =SUM(G25:G32) -> 73313.983 | L25: =7198.52+1585 -> 8783.52 | M25: =SUM(L25:L32) -> 53182.73 | N25: 9796 | O25: =SUM(N25:N32) -> 53987.95 | P25: 10314 | Q25: =SUM(P25:P32) -> 54369.34 | R25: 44490 | S25: =SUM(R25:R32) -> 86956.67 | T25: =1585+5273+6912 -> 13770 | U25: =SUM(T25:T32) -> 56236.67 | V25: 11033 | W25: =SUM(V25:V32) -> 53499.67 | X25: 27086 | Y25: =SUM(X25:X32) -> 52852.67 | Z25: 21092 | AA25: =SUM(Z25:Z32) -> 275349.44 | AB25: 29176 | AC25: =SUM(AB25:AB32) -> 308433.44 | AD25: 22147 | AE25: =SUM(AD25:AD32) -> 51404.44 | AF25: 25712 | AG25: =SUM(AF25:AF32) -> 55089.39 | AH25: 13056 | AI25: =SUM(AH25:AH32) -> 42366.57
B26: конструктор сайтов | C26: Тильда | D26: ТИЛЬДА ПАБЛИШИНГ ООО | E26: =G26 -> 1000 | F26: =G26*12 -> 12000 | G26: 1000 | L26: 0 | N26: 0 | P26: 0 | R26: 0 | T26: 0 | V26: 0 | X26: 0 | Z26: 0 | AB26: 0 | AD26: 0 | AF26: 0 | AH26: 0
B27: сервис обратной связи | C27: Раиса | D27: ПРАВОВЕД.РУ ЛАБ ООО | E27: =G27 -> 16666.66 | F27: =E27*12 -> 199999.92 | G27: 16666.66 | L27: 16666.66 | N27: 16666.67 | P27: 16666.67 | R27: 16666.67 | T27: 16666.67 | V27: 16666.67 | X27: 16666.67 | Z27: 16666.67 | AB27: 16666.67 | AD27: 16666.67 | AF27: 16666.67 | AH27: 16666.67
B28: платформа автоматизации найма | C28: Хантфлоу | D28: ХАНФЛОУ ООО | E28: =G28 -> 9100 | F28: =E28*12 -> 109200 | G28: 9100 | L28: 9100 | N28: 9100 | P28: 9100 | R28: 9100 | T28: 9100 | V28: 9100 | X28: 9100 | Z28: 11000 | AB28: 11000 | AD28: 11000 | AF28: 11000 | AH28: 11000
B29: платформа д/обучения, база знаний | C29: Кампус | D29: ТЕОРИИ ОТ ПРАКТИКОВ ООО | E29: =G29 -> 16700 | F29: =E29*12 -> 200400 | G29: 16700 | L29: 16700 | N29: 16700 | P29: 16700 | R29: 16700 | T29: 16700 | V29: 16700
B30: аутсорс-поиск | D30: ИП Скворцова | Z30: 225000 | AB30: 250000 | AD30: 0 | AF30: 0 | AH30: 0
B31: тестирование | C31: ПИФ | D31: ЭКОПСИ ТЕКНОЛОДЖИС ООО | E31: =G31 -> 8333.3333 | F31: 100000 | G31: =F31/12 -> 8333.3333 | L31: 0 | N31: 0 | P31: 0 | R31: 0 | T31: 0 | V31: 0 | X31: 0 | Z31: 0 | AB31: 0 | AD31: 0 | AF31: 0 | AH31: 0
B32: платформа д/онлайнконференций | C32: Zoom (HR) | D32: Zoom (HR) | E32: =H32*H2 -> 1513.99 | F32: =E32*12 -> 18167.88 | G32: =E32 -> 1513.99 | H32: 14.99 | L32: 1932.55 | N32: 1725.28 | P32: 1588.67 | R32: 0 | T32: 0 | V32: 0 | X32: 0 | Z32: 1590.77 | AB32: 1590.77 | AD32: 1590.77 | AF32: 1710.72 | AH32: 1643.9
A33: Сервисы отдела продаж | B33: Лицензия АМО ЦРМ | C33: АМО ЦРМ | D33: Абрамов Михаил Владимирович ИП | E33: =G33 -> 7303.66 | F33: =E33*12 -> 87643.92 | G33: 7303.66 | K33: =SUM(G33:G41) -> 39437.683 | L33: 7303.66 | M33: =SUM(L33:L41) -> 12061.66 | N33: 7303.66 | O33: =SUM(N33:N41) -> 11288.94 | P33: 5994 | Q33: =SUM(P33:P41) -> 13414.97 | R33: 5994 | S33: =SUM(R33:R41) -> 13389.71 | T33: 5994 | U33: =SUM(T33:T41) -> 20127.48 | V33: 5994 | W33: =SUM(V33:V41) -> 48356.26 | X33: 5994 | Y33: =SUM(X33:X41) -> 10401.33 | Z33: 5994 | AA33: =SUM(Z33:Z41) -> 23299.64 | AB33: 5994 | AC33: =SUM(AB33:AB41) -> 10468.21 | AD33: 5994 | AE33: =SUM(AD33:AD41) -> 11370.08 | AF33: =20388/7 -> 2912.5714 | AG33: =SUM(AF33:AF41) -> 7579.0614 | AH33: =20388/7 -> 2912.5714 | AI33: =SUM(AH33:AH41) -> 7249.0114
B34: дополнение к АМО | C34: Почтовик | D34: Команда Ф5 ООО | E34: =G34 -> 1794 | F34: 21528 | G34: =F34/12 -> 1794 | L34: 0 | N34: 0 | P34: 0 | R34: 0 | T34: 0 | V34: 0 | X34: 0 | Z34: 0 | AB34: 0 | AD34: 0 | AF34: 0 | AH34: 0
B35: телефония | C35: Сипуини | D35: СИПУНИ РУС ООО | E35: =G35 -> 953.33333 | F35: 11440 | G35: =F35/12 -> 953.33333 | L35: 0 | N35: 0 | P35: 0 | R35: 0 | T35: 0 | V35: 0 | X35: 0 | Z35: 0 | AB35: 0 | AD35: 900
B36: телефония | C36: Сансим | D36: САНСИМ АО | E36: =G36 -> 1400 | F36: =E36*12 -> 16800 | G36: 1400 | L36: 1565.45 | N36: 1000 | P36: 1582.3 | R36: =587.99 -> 587.99 | T36: =642.26+1000+510+3.88+1200 -> 3356.14 | V36: 1529.94 | X36: 1576.81 | Z36: =1599.27 -> 1599.27 | AB36: 1623.44 | AD36: 1625.31 | AF36: 1798.81 | AH36: 1683.43
B37: тенд. площадка | C37: Тендеры и закупки | D37: Тендеры и закупки | E37: =G37 -> 1200 | F37: =E37*12 -> 14400 | G37: 1200 | L37: 1260 | N37: 1260 | P37: 1260 | R37: 1260 | T37: 1260 | V37: 1260 | X37: 1260 | Z37: 1260 | AB37: 1260 | AD37: 1260 | AF37: 1260 | AH37: 1260
B38: тендерные площадки | C38: Ростендер/Бидзаар | D38: тендерные площадки | E38: =G38 -> 25000 | F38: =E38*12 -> 300000 | G38: 25000 | L38: 0 | N38: 0 | P38: 2990 | R38: 0 | T38: 0 | V38: 0 | X38: 0 | Z38: 12855.6 | AB38: 0 | AD38: 0 | AF38: 0 | AH38: 0
D39: Савкин ИП | R39: 4000 | T39: 8000 | V39: 8000 | X39: 0 | Z39: 0 | AB39: 0 | AD39: 0 | AF39: 0 | AH39: 0
B40: конференции | D40: СОБЫТИЕ ООО | V40: 30000 | X40: 0 | Z40: 0 | AB40: 0 | AD40: 0 | AF40: 0 | AH40: 0
B41: платформа д/онлайнконференций | C41: Zoom (продажи) | D41: Zoom (продажи) | E41: =H41*H2 -> 1786.69 | F41: =E41*12 -> 21440.28 | G41: =E41 -> 1786.69 | H41: 17.69 | L41: 1932.55 | N41: 1725.28 | P41: 1588.67 | R41: 1547.72 | T41: 1517.34 | V41: 1572.32 | X41: 1570.52 | Z41: 1590.77 | AB41: 1590.77 | AD41: 1590.77 | AF41: 1607.68 | AH41: 1393.01
A42: Сервисы маркетинг | B42: сервис для создания лендингов | C42: Webflow | D42: Маркетинг | E42: =G42 -> 5757 | F42: =E42*12 -> 69084 | G42: =H42*H2 -> 5757 | H42: 57 | K42: =SUM(G42:G50) -> 50034.5 | L42: 5696.01 | M42: =SUM(L42:L50) -> 97982.42 | N42: 2468.76 | O42: =SUM(N42:N50) -> 97507.4 | P42: =2585.06+4798.83 -> 7383.89 | Q42: =SUM(P42:P50) -> 184149.33 | R42: 4624.98 | S42: =SUM(R42:R50) -> 125505.85 | T42: 4543.47 | U42: =SUM(T42:T50) -> 106595.61 | V42: 0 | W42: =SUM(V42:V50) -> 112481.96 | X42: 4464.81 | Y42: =SUM(X42:X50) -> 167727.54 | Z42: 0 | AA42: =SUM(Z42:Z50) -> 227290.68 | AB42: 0 | AC42: =SUM(AB42:AB50) -> 103265.17 | AD42: 0 | AE42: =SUM(AD42:AD50) -> 103132.99 | AF42: 0 | AG42: =SUM(AF42:AF50) -> 116417.95 | AH42: 0 | AI42: =SUM(AH42:AH50) -> 83019.31
B43: сервис сквозной аналитики | C43: Ройстат | E43: =G43 -> 14277.5 | F43: 171330 | G43: =F43/12 -> 14277.5 | L43: 0 | N43: 0 | P43: 0 | R43: 0 | T43: 0 | V43: 0 | X43: 0 | Z43: 0 | AB43: 0 | AD43: 0 | AF43: 0 | AH43: 0
B44: контекстная реклама | D44: ИП Токмаков | E44: =G44 -> 30000 | F44: =E44*12 -> 360000 | G44: 30000 | L44: 30000 | N44: 33000 | P44: 33000 | R44: 49150 | T44: 33000 | V44: 33000 | X44: 33000 | Z44: 33000 | AB44: 33000 | AD44: 33000 | AF44: 33000 | AH44: 33000
D45: нал | N45: 3400 | P45: 0 | R45: 0 | T45: 0 | V45: 0 | X45: 0 | Z45: 0 | AB45: 0 | AD45: 0 | AF45: 0 | AH45: 0
D46: События ООО | Z46: 25920 | AB46: 0 | AD46: 0 | AF46: 0 | AH46: 0
B47: платформа для конференции | D47: ПФ СКБ Контур АО | AB47: 20025 | AD47: 20025 | AF47: 0 | AH47: 0
B48: командировочные на конференции | Z48: 68059.6 | AB48: 0 | AD48: 0 | AF48: 0 | AH48: 0
D49: 101 ООО | L49: 18891.98 | N49: 0 | P49: 4448.64 | R49: 0 | T49: 317.65 | V49: 342.8 | X49: 262.73 | Z49: 311.08 | AB49: 240.17 | AD49: 107.99 | AF49: 98.2 | AH49: 19.31
C50: Яндекс | D50: ЯНДЕКС ООО | E50: =G50 -> 0 | F50: =E50*12 -> 0 | G50: 0 | L50: 43394.43 | N50: 58638.64 | P50: 139316.8 | R50: 71730.87 | T50: =18734.49+50000 -> 68734.49 | V50: 79139.16 | X50: 130000 | Z50: 100000 | AB50: 50000 | AD50: 50000 | AF50: =50000+33319.75 -> 83319.75 | AH50: 50000
A51: Административные расходы | B51: аренда офис | D51: ИП Кучава | E51: =G51 -> 411008 | F51: =E51*12 -> 4932096 | G51: 411008 | K51: =SUM(G51:G64) -> 643649 | L51: 411008 | M51: =SUM(L51:L64) -> 566158.86 | N51: 411008 | O51: =SUM(N51:N64) -> 622366.06 | P51: 411008 | Q51: =SUM(P51:P64) -> 638092.4 | R51: 411008 | S51: =SUM(R51:R64) -> 621885.38 | T51: 411008 | U51: =SUM(T51:T64) -> 513195.26 | V51: 411008 | W51: =SUM(V51:V64) -> 547861.2 | X51: 411008 | Y51: =SUM(X51:X64) -> 567140.73 | Z51: 411008 | AA51: =SUM(Z51:Z64) -> 564510.12 | AB51: 411008 | AC51: =SUM(AB51:AB64) -> 537482.37 | AD51: 411008 | AE51: =SUM(AD51:AD64) -> 573186.34 | AF51: 411008 | AG51: =SUM(AF51:AF64) -> 522320.27 | AH51: 411008 | AI51: =SUM(AH51:AH64) -> 608810.71
B52: субаренда | D52: БЛОЧНЫЙ РЕДАКТОР ООО | T52: -40043.59 | V52: -40043.59 | X52: -40043.59 | Z52: -40043.59 | AB52: -40043.59 | AD52: -40043.59 | AF52: -40043.59 | AH52: -40043.59
B53: коммунальные платежи | D53: ИП Кучава | E53: =G53 -> 80000 | F53: =E53*12 -> 960000 | G53: 80000 | L53: =11262.48+58037.48 -> 69299.96 | N53: =16509.29+63423.3 -> 79932.59 | P53: =65227.29+23313.77 -> 88541.06 | R53: =13504.85+60460.08 -> 73964.93 | T53: =16438.44 -> 16438.44 | V53: 57597.86 | X53: 58737.66 | Z53: =11270.6+49031 -> 60301.6 | AB53: 57112.31 | AD53: 60326.08 | AF53: =21257.66 -> 21257.66 | AH53: 142769.26
B54: интернет | D54: Эр-Телеком | E54: =G54 -> 18315 | F54: =G54*12 -> 219780 | G54: 18315 | L54: 18315 | N54: 18315 | P54: 18315 | R54: 22161.15 | T54: 22161.15 | V54: 22161.15 | X54: 22161.15 | Z54: 22161.15 | AB54: 22161.15 | AD54: 22161.15 | AF54: 22161.15 | AH54: 22161.15
B55: охрана | D55: Рефлекс-КБ | E55: =G55 -> 4326 | F55: =E55*12 -> 51912 | G55: 4326 | L55: 4328 | N55: 4328 | P55: 4328 | R55: 4328 | T55: 4326 | V55: =4326+1877 -> 6203 | X55: 4326 | Z55: 4326 | AB55: 4326 | AD55: 4326 | AF55: 4326 | AH55: 4326
B56: хостинг | D56: Хостинг вашего успеха | E56: =G56 -> 20000 | F56: =E56*12 -> 240000 | G56: 20000 | L56: =16754.81+595 -> 17349.81 | N56: =595+84.02 -> 679.02 | P56: =595+18796.48+369.9+2449 -> 22210.38 | R56: =18639.35+595+7842.9 -> 27077.25 | T56: =369.9+18943.37+4762 -> 24075.27 | V56: =18667.77+595 -> 19262.77 | X56: =18728.26+369.9+595 -> 19693.16 | Z56: =595+18882.66+264.21 -> 19741.87 | AB56: 18862.36 | AD56: =19208.15+115.16+5796 -> 25119.31 | AF56: =18757.23 -> 18757.23 | AH56: =18715.89+119 -> 18834.89
B57: курьерская служба | D57: КС Холдинговая компания | E57: 30000 | F57: =E57*12 -> 360000 | G57: 30000 | L57: 12282.6 | N57: =12939.3+7032.3 -> 19971.6 | P57: =9563.4+12742.95 -> 22306.35 | R57: =6873.9+3516.15 -> 10390.05 | T57: =4313.1+3984.75 -> 8297.85
B58: курьерская служба | D58: СДЭК ВОРЛДВАЙД ООО | V58: 16915 | X58: 24139.63 | Z58: =20970+620 -> 21590 | AB58: 15090 | AD58: 21270 | AF58: 11680 | AH58: 18625
B59: телефония | E59: =G59 -> 6000 | F59: =E59*12 -> 72000 | G59: 6000 | L59: =2000+778 -> 2778 | N59: =1580+778 -> 2358 | P59: =1580+778 -> 2358 | R59: =778+650+1730 -> 3158 | T59: =1892+650 -> 2542 | V59: =1730+650 -> 2380 | X59: =661.4 -> 661.4 | Z59: =11.4+662.25 -> 673.65 | AB59: =1550+11.4+657 -> 2218.4 | AD59: =1550+11.4+680 -> 2241.4 | AF59: =1100 -> 1100 | AH59: 1125
B60: вода в офис | D60: Товарный двор пивоваренной компании | E60: =G60 -> 5000 | F60: =E60*12 -> 60000 | G60: 5000 | L60: 5000 | N60: 5000 | P60: 3000 | R60: 6000 | T60: =2500+3000 -> 5500 | V60: 3000 | X60: 3000 | Z60: 2500 | AB60: 6000 | AD60: 3500 | AF60: 3000 | AH60: 3000
E61: =G61 -> 36000 | F61: =E61*12 -> 432000 | G61: 36000 | L61: 0 | N61: 0 | P61: 0 | R61: 0 | T61: 0 | V61: 0 | X61: 0 | Z61: 0 | AB61: 0 | AD61: 0 | AF61: 0 | AH61: 0
B62: почтовые расходы | D62: Почта РФ | E62: =G62 -> 3000 | F62: =E62*12 -> 36000 | G62: 3000 | L62: 90.5 | N62: =317+1174 -> 1491 | P62: 2024.32 | R62: 0 | T62: 0 | V62: 0 | X62: 0 | Z62: 0 | AB62: 500 | AD62: 500 | AF62: 0 | AH62: 0
B63: расходы офис | D63: нал | E63: =G63 -> 30000 | F63: =E63*12 -> 360000 | G63: 30000 | L63: 25706.99 | N63: =6568+21464.85 -> 28032.85 | P63: =4519.5+27981.79 -> 32501.29 | R63: =20718+11580 -> 32298 | T63: =25078.5+6061.64 -> 31140.14 | V63: =4070.84+15691.17+3915 -> 23677.01 | X63: =20548.8+5000+10158.52 -> 35707.32 | Z63: 34501.44 | AB63: =700+9797.74 -> 10497.74 | AD63: 35027.99 | AF63: =6619+32704.82 -> 39323.82
B64: клининг | D64: нал | E64: 0 | F64: 0 | G64: 0 | N64: 51250 | P64: 31500 | R64: 31500 | T64: 27750 | V64: 25700 | X64: 27750 | Z64: 27750 | AB64: 29750 | AD64: 27750 | AF64: 29750 | AH64: 27005
A65: Сервисы для клиентов | B65: платим за клиентов, включаем им в счета с комиссией | D65: Майндбокс, С2D тд | E65: =G65 -> 350000 | F65: =E65*12 -> 4200000 | G65: 350000 | K65: =SUM(G65:G81) -> 359200 | L65: 0 | M65: =SUM(L65:L81) -> 275506 | N65: 117600 | O65: =SUM(N65:N81) -> 456478.08 | P65: =99600+18000 -> 117600 | Q65: =SUM(P65:P81) -> 442465.03 | R65: =99600+18000 -> 117600 | S65: =SUM(R65:R81) -> 438348.99 | T65: 99600 | U65: =SUM(T65:T81) -> 531254.8 | V65: 99600 | W65: =SUM(V65:V81) -> 331854.9 | X65: 99600 | Y65: =SUM(X65:X81) -> 274269.75 | Z65: =100800 -> 100800 | AA65: =SUM(Z65:Z81) -> 291764.95 | AB65: =100800 -> 100800 | AC65: =SUM(AB65:AB81) -> 335755.31 | AD65: =100800 -> 100800 | AE65: =SUM(AD65:AD81) -> 372266.93 | AF65: 102620.89 | AG65: =SUM(AF65:AF81) -> 419277.35 | AH65: 102771.84 | AI65: =SUM(AH65:AH81) -> 290575.54
D66: Юнисендер Смарт (для Москвича) | E66: =G66 -> 9200 | F66: =E66*12 -> 110400 | G66: 9200 | L66: 81600 | N66: 25760 | P66: 12880 | R66: 12880 | T66: 12880 | V66: 12880 | X66: 12880 | Z66: 12880 | AB66: 12880 | AD66: 12880 | AF66: 12880 | AH66: 12880
C67: Для Москвича | D67: АЙДИДЖИТАЛ ООО | T67: =10455+7916.95 -> 18371.95 | V67: 7916.95 | X67: 7916.95 | Z67: 7916.95 | AB67: 7916.95 | AD67: 7916.95 | AF67: 7916.95 | AH67: 7916.95
C68: Лидплан | D68: ПИСЬМО ООО | E68: =G68 -> 0 | F68: =E68*12 -> 0 | G68: 0 | L68: 157218 | N68: 196017.5 | P68: 202012.91 | R68: 160681.5 | T68: 290086.13 | V68: 143065.15 | X68: 80850 | Z68: 87204 | AB68: 66281.25 | AD68: 60000 | AF68: =168361.9-AD68+33380.9 -> 141742.8 | AH68: 33380.9
C69: Блочный редактор | L69: 3800 | N69: 0 | P69: 0 | R69: 0 | T69: 0 | V69: 0 | X69: 0 | Z69: 0 | AB69: 0 | AD69: 0 | AF69: 0 | AH69: 0
B70: для Рояла | D70: МЭДТЕСТ ООО | AD70: 3000 | AF70: 0 | AH70: 0
B71: для Акувью | C71: сервис Voximplant | D71: ФАСТКОМ ООО | AF71: 24288 | AH71: 3921.45
D72: Сизикова | R72: 3395.99 | AD72: 25039.58 | AF72: 9805.73 | AH72: 0
B73: для Бенеттон | D73: Турусов | AD73: 55952 | AF73: 0 | AH73: 0
B74: для Шашлыкофф | D74: Радист онлайн | X74: 4000 | Z74: 10800
D75: Миро для самолета | T75: 7719.36 | V75: 0 | X75: 0 | Z75: 0 | AB75: 0 | AD75: 0 | AF75: 0 | AH75: 0
D76: ВЕБФОРМ ООО | P76: 17500 | R76: 0 | T76: 0 | V76: 0 | X76: 0 | Z76: 0 | AB76: 0 | AD76: 0 | AF76: 0 | AH76: 0
C77: серв. Для сервье | D77: ДЕВИНО ОНЛАЙН ООО | E77: =G77 -> 0 | F77: =E77*12 -> 0 | G77: 0 | L77: 11300 | N77: 559 | P77: 0 | R77: 0 | T77: 0 | V77: 0 | X77: 0 | Z77: 0 | AB77: 0 | AD77: 0 | AF77: 0 | AH77: 0
C78: Таймвеб клауд | Z78: 1100 | AB78: 910.71 | AD78: 1040 | AF78: 0 | AH78: 0
B79: артлист для Здравсити | N79: 1545.58 | P79: 1416.12 | R79: =14263.5 -> 14263.5 | T79: 27501.36
B80: QR-код | C80: сервис для Рояла | AF80: 44145.78 | AH80: 0
C81: серв. Для петровакса | D81: Жеринова Ульяна Юрьевна ИП | E81: =G81 -> 0 | F81: =E81*12 -> 0 | G81: 0 | L81: 21588 | N81: 114996 | P81: 91056 | R81: 129528 | T81: 75096 | V81: 68392.8 | X81: 69022.8 | Z81: 71064 | AB81: 146966.4 | AD81: 105638.4 | AF81: 75877.2 | AH81: 129704.4
A82: Сервисы финансы | B82: мобильная связь для поддержания грузинской сим-карты | D82: GeoCell | E82: 334.9 | F82: =E82*12 -> 4018.8 | G82: =J82*J2 -> 356.1 | J82: 10 | K82: =SUM(G82:G92) -> 22190.067 | M82: =SUM(L82:L92) -> 17331.898 | O82: =SUM(N82:N92) -> 20816.627 | P82: 60.54 | Q82: =SUM(P82:P92) -> 20738.027 | R82: 0 | S82: =SUM(R82:R92) -> 20623.207 | T82: 0 | U82: =SUM(T82:T92) -> 97109.607 | V82: 0 | W82: =SUM(V82:V92) -> 105772.03 | X82: 0 | Y82: =SUM(X82:X92) -> 88067.947 | Z82: 0 | AA82: =SUM(Z82:Z92) -> 92067.947 | AB82: 0 | AC82: =SUM(AB82:AB92) -> 90208.667 | AD82: 0 | AE82: =SUM(AD82:AD92) -> 90765 | AF82: 0 | AG82: =SUM(AF82:AF92) -> 90765 | AH82: 0 | AI82: =SUM(AH82:AH92) -> 90765
B83: Ежегодный платеж за обслуживание Грузинской карты | D83: Credo | E83: =G83 -> 194.96667 | F83: 2339.6 | G83: =F83/12 -> 194.96667 | J83: 5.42 | L83: =4670.54/12 -> 389.21167 | N83: 0 | P83: 0 | R83: 0 | T83: 0 | V83: 0 | X83: 0 | Z83: 0 | AB83: 0 | AD83: 0 | AF83: 0 | AH83: 0
D84: Астрал | E84: =G84 -> 0 | F84: =E84*12 -> 0 | G84: 0
B85: бух. обслуживание груз. ИП | E85: =G85 -> 11918 | F85: =E85*12 -> 143016 | G85: =H85*H2 -> 11918 | H85: 118 | L85: 11935.02 | N85: 11783.96 | P85: =10679.76+965.06 -> 11644.82 | R85: =10120.99+983.55 -> 11104.54 | T85: 9590.94 | V85: =10309.36+144 -> 10453.36 | X85: 9549.28 | Z85: 9549.28 | AB85: 0 | AD85: 0 | AF85: 0 | AH85: 0
B86: бух. обслуживание | C86: Профит | D86: ИП Жильцов | T86: 69000 | V86: 69000 | X86: 69000 | Z86: 73000 | AB86: 73000 | AD86: 73000 | AF86: 73000 | AH86: 73000
B87: 1 с обслуживание | D87: ЮниСофт | E87: =G87 -> 3221 | F87: =E87*12 -> 38652 | G87: 3221 | L87: =60092/12 -> 5007.6667 | N87: =60092/12 -> 5007.6667 | P87: =60092/12 -> 5007.6667 | R87: =60092/12+486 -> 5493.6667 | T87: =60092/12+486 -> 5493.6667 | V87: =60092/12+486 -> 5493.6667 | X87: =60092/12+486 -> 5493.6667 | Z87: =60092/12+486 -> 5493.6667 | AB87: =60092/12+486 -> 5493.6667 | AD87: 8850 | AF87: 8850 | AH87: 8850
B88: 1 с - личный кабинет | C88: спросить у Светы | D88: АКСИОМА-СОФТ ООО | E88: =G88 -> 2500 | F88: =E88*12 -> 30000 | G88: 2500 | V88: 16800 | AB88: 2800
B89: База знаний кадровое дело-Света | D89: ООО "АКТИОН-ПРЕСС" | E89: =F89/12 -> 1000 | F89: 12000 | G89: =E89 -> 1000
B90: ЭДО | C90: Тензор | D90: ООО "Компания "Тензор" | T90: 9000
B91: управленческая отчетность | D91: Адеск | AB91: 4890 | AD91: 4890 | AF91: 4890 | AH91: 4890
B92: ЭДО | C92: Диадок | D92: СКБ Контур | E92: =G92 -> 3000 | F92: =E92*12 -> 36000 | G92: 3000 | N92: 4025 | P92: 4025 | R92: 4025 | T92: 4025 | V92: 4025 | X92: 4025 | Z92: 4025 | AB92: 4025 | AD92: 4025 | AF92: 4025 | AH92: 4025
A93: Сервисы CS | B93: для создания прототипов сайтов или приложений, иллюстраций и векторной графики | C93: Figma | D93: Figma | E93: =G93 -> 25250 | F93: =E93*12 -> 303000 | G93: =H93*H2 -> 25250 | H93: 250 | K93: =SUM(G93:G100) -> 53227 | L93: =25250+499.65 -> 25749.65 | M93: =SUM(L93:L100) -> 28195.6 | N93: =25250+440.85 -> 25690.85 | O93: =SUM(N93:N100) -> 28022.24 | P93: =25250+420.95 -> 25670.95 | Q93: =SUM(P93:P100) -> 27810.31 | R93: =25250 -> 25250 | S93: =SUM(R93:R100) -> 27316.16 | T93: =25250 -> 25250 | U93: =SUM(T93:T100) -> 35999.32 | V93: =25250 -> 25250 | W93: =SUM(V93:V100) -> 26997.74 | X93: =25250 -> 25250 | Y93: =SUM(X93:X100) -> 26424.95 | Z93: =25250 -> 25250 | AA93: =SUM(Z93:Z100) -> 34490.2 | AB93: =25250 -> 25250 | AC93: =SUM(AB93:AB100) -> 34490.2 | AD93: =25250 -> 25250 | AE93: =SUM(AD93:AD100) -> 34490.2 | AF93: =243599.62/12 -> 20299.968 | AG93: =SUM(AF93:AF100) -> 23619.258 | AH93: =243599.62/12 -> 20299.968 | AI93: =SUM(AH93:AH100) -> 51887.438
C94: Ламбда тест | D94: Ламбда тест | E94: =G94 -> 909 | F94: =G94*12 -> 10908 | G94: =H94*H2 -> 909 | H94: 9 | L94: 917.23 | N94: 872.19 | P94: 802.26 | R94: 774.81 | T94: 727.74 | V94: 571.44
B95: для создания заметок и текстовых документов, списков дел, баз данных, таблиц, канбан-досок, баз знаний, ведения проектов и совместной работы. | C95: Notion | D95: Notion | E95: =G95 -> 3030 | F95: =E95*12 -> 36360 | G95: =H95*H2 -> 3030 | H95: 30
B96: платформа видеосвязи для асинхронной работы, позволяет записывать изображение с экрана и веб-камеры | C96: Loom | D96: Loom | E96: =G96 -> 1515 | F96: =E96*12 -> 18180 | G96: =H96*H2 -> 1515 | H96: 15 | L96: 1528.72 | N96: 1459.2 | P96: 1337.1 | R96: 1291.35 | T96: 1212.9 | V96: 1176.3 | X96: 1174.95 | Z96: 0 | AB96: 0 | AD96: 0 | AF96: 0 | AH96: 0
B97: файлообменник | C97: Bitbucket (Атлассиан) | D97: Bitbucket (Атлассиан) | E97: =G97 -> 2424 | F97: =E97*12 -> 29088 | G97: =H97*H2 -> 2424 | H97: 24
D98: Phaser | T98: 8808.68 | V98: 0 | X98: 0 | Z98: 0 | AB98: 0 | AD98: 0 | AF98: 0 | AH98: 0
B99: компания, предоставляющая стоковые фотографии, видеоматериалы, музыку и инструменты редактирования. | C99: Freepik | D99: Freepik | AF99: 3319.29 | AH99: 3686.27
B100: компания, предоставляющая стоковые фотографии, видеоматериалы, музыку и инструменты редактирования. | C100: Shutterstock | D100: Shutterstock | E100: =G100 -> 20099 | F100: =E100*12 -> 241188 | G100: =H100*H2 -> 20099 | H100: 199 | L100: 0 | N100: 0 | P100: 0 | R100: 0 | T100: 0 | V100: 0 | X100: 0 | Z100: 9240.2 | AB100: 9240.2 | AD100: 9240.2 | AF100: 0 | AH100: 27901.2
...

Sheet База расходы зп
V1: ПЛАН
G2: ПЛАН | O2: ФАКТ | V2: 2025
A3: РАСШИФРОВКА | B3: ПОДРАЗДЕЛЕНИЕ | C3: ДОЛЖНОСТЬ | D3: Штатных единиц | E3: Нижняя зарплатная вилка грейда | F3: Нижняя зарплатная вилка грейда | G3: Верхняя зарплатная вилка | H3: зпл с налогами с ФОТ за шт. ед. | I3: ФОТ с налогами | J3: ИТОГО | K3: произв/непроизв | L3: произв/непроизв % | M3: Штатных единиц | N3: зпл на руки за шт. ед. | O3: зпл на руки | P3: зпл с налогами с ФОТ за шт. ед. | Q3: зпл с налогами с ФОТ | R3: ФОТ с налогами | S3: ИТОГО | T3: произв/непроизв | U3: произв/непроизв % | V3: ИТОГО
A4: НЕПРОИЗВОДСТВЕННЫЕ СОТРУДНИКИ | B4: УПР | C4: Генерадьный директор | D4: 1 | G4: 870135 | H4: =G4/0.87+G4/0.87*7.8% -> 1078167.3 | I4: 1078167 | J4: 1078167 | K4: =J4+J7+J12+J13+J17+J20+J27 -> 3289155 | L4: =K4*L53/K53 -> 33.455272 | M4: 1 | N4: =O4/M4 -> 870135 | O4: 870135 | P4: =Q4/M4 -> 1078167 | Q4: 1078167 | R4: =SUM(Q4:Q6) -> 1078167 | S4: =SUM(R4:R6) -> 1078167 | T4: =S4+S7+S12+S13+S17+S20+J27 -> 3289155 | U4: =T4*U53/T53 -> 40.214598 | V4: =R4 -> 1078167
C5: Исполнительный директор | D5: 1 | M5: 1
C6: Финансовый директор | D6: 1 | M6: 1
B7: БУХГАЛТЕРИЯ | C7: Руководитель отдела бухгалтерского и налогового учета | D7: 1 | G7: 100000 | H7: =G7/0.87+G7/0.87*7.8% -> 123908.05 | I7: =D7*H7 -> 123908.05 | J7: =SUM(I7:I11) -> 434272.92 | M7: 1 | N7: =O7/M7 -> 100000 | O7: 100000 | P7: =Q7/M7 -> 123908.05 | Q7: =O7/0.87+O7/0.87*7.8% -> 123908.05 | R7: =SUM(Q7:Q11) -> 434272.92 | S7: =SUM(R7:R11) -> 434272.92 | V7: =S7 -> 434272.92
C8: Заместитель генерального директора по общим вопросам | D8: 1 | G8: 90480 | H8: =G8/0.87+G8/0.87*7.8% -> 112112 | I8: =D8*H8 -> 112112 | M8: 1 | N8: =O8/M8 -> 90480 | O8: 90480 | P8: =Q8/M8 -> 112112 | Q8: =O8/0.87+O8/0.87*7.8% -> 112112
C9: Бухгалтер по первичной документации | D9: 1 | G9: 60000 | H9: =G9/0.87+G9/0.87*7.8% -> 74344.828 | I9: =D9*H9 -> 74344.828 | M9: 1 | N9: =O9/M9 -> 60000 | O9: 60000 | P9: =Q9/M9 -> 74344.828 | Q9: =O9/0.87+O9/0.87*7.8% -> 74344.828
C10: Менеджер по документообороту | D10: 1 | G10: 50000 | H10: =G10/0.87+G10/0.87*7.8% -> 61954.023 | I10: =D10*H10 -> 61954.023 | M10: 1 | N10: =O10/M10 -> 50000 | O10: 50000 | P10: =Q10/M10 -> 61954.023 | Q10: =O10/0.87+O10/0.87*7.8% -> 61954.023
C11: Юрист | D11: 1 | G11: 50000 | H11: =G11/0.87+G11/0.87*7.8% -> 61954.023 | I11: =D11*H11 -> 61954.023 | M11: 1 | N11: =O11/M11 -> 50000 | O11: 50000 | P11: 50000 | Q11: =O11/0.87+O11/0.87*7.8% -> 61954.023
B12: ФИНАНСЫ | C12: Финансовый менеджер проектов | D12: 1 | G12: 60000 | H12: =G12/0.87+G12/0.87*7.8% -> 74344.828 | I12: =D12*H12 -> 74344.828 | J12: =I12 -> 74344.828 | M12: 1 | N12: =O12/M12 -> 60000 | O12: 60000 | P12: =Q12/M12 -> 74344.828 | Q12: =O12/0.87+O12/0.87*7.8% -> 74344.828 | R12: =Q12 -> 74344.828 | S12: =R12 -> 74344.828 | V12: =S12 -> 74344.828
B13: HR | C13: Директор по персоналу | D13: 1 | G13: 140070 | H13: =G13/0.87+G13/0.87*7.8% -> 173558 | I13: =D13*H13 -> 173558 | J13: =SUM(I13:I16) -> 324808.83 | M13: 1 | N13: =O13/M13 -> 140070 | O13: 140070 | P13: =Q13/M13 -> 173558 | Q13: =O13/0.87+O13/0.87*7.8% -> 173558 | R13: =SUM(Q13:Q16) -> 324808.83 | S13: =SUM(R13:R16) -> 324808.83 | V13: =S13 -> 324808.83
C14: Менеджер по подбору и адаптации персонала | D14: 1 | G14: 47067 | H14: =G14/0.87+G14/0.87*7.8% -> 58319.8 | I14: =D14*H14 -> 58319.8 | M14: 1 | N14: =O14/M14 -> 47067 | O14: 47067 | P14: =Q14/M14 -> 58319.8 | Q14: =O14/0.87+O14/0.87*7.8% -> 58319.8
C15: HR | D15: 1 | G15: 75000 | H15: =G15/0.87+G15/0.87*7.8% -> 92931.034 | I15: =D15*H15 -> 92931.034 | M15: 1 | N15: =O15/M15 -> 75000 | O15: 75000 | P15: =Q15/M15 -> 92931.034 | Q15: =O15/0.87+O15/0.87*7.8% -> 92931.034
C16: Рекрутер | D16: 1 | H16: =G16/0.87+G16/0.87*7.8% -> 0 | I16: =D16*H16 -> 0 | M16: 0 | P16: 0 | Q16: =O16/0.87+O16/0.87*7.8% -> 0
B17: АП | C17: Помощник руководителя | D17: 1 | G17: 60030 | H17: =G17/0.87+G17/0.87*7.8% -> 74382 | I17: =D17*H17 -> 74382 | J17: =SUM(I17:I19) -> 122417.43 | M17: 1 | N17: =O17/M17 -> 60030 | O17: 60030 | P17: =Q17/M17 -> 74382 | Q17: =O17/0.87+O17/0.87*7.8% -> 74382 | R17: =SUM(Q17:Q19) -> 122417.43 | S17: =SUM(R17:R19) -> 122417.43 | V17: =S17 -> 122417.43
C18: Оператор ПК | D18: 1 | G18: 8765 | H18: =G18/0.87+G18/0.87*7.8% -> 10860.54 | I18: =D18*H18 -> 10860.54 | M18: 1 | N18: =O18/M18 -> 8765 | O18: 8765 | P18: =Q18/M18 -> 10860.54 | Q18: =O18/0.87+O18/0.87*7.8% -> 10860.54
C19: Системный администратор | D19: 1 | G19: 30002 | H19: =G19/0.87+G19/0.87*7.8% -> 37174.892 | I19: =D19*H19 -> 37174.892 | M19: 1 | N19: =O19/M19 -> 30002 | O19: 30002 | P19: =Q19/M19 -> 37174.892 | Q19: =O19/0.87+O19/0.87*7.8% -> 37174.892
B20: МАРКЕТИНГ | C20: Директор по маркетингу | D20: 1 | G20: 140070 | H20: =G20/0.87+G20/0.87*7.8% -> 173558 | I20: =D20*H20 -> 173558 | J20: =SUM(I20:I26) -> 753186.29 | M20: 1 | N20: =O20/M20 -> 140070 | O20: 140070 | P20: =Q20/M20 -> 173558 | Q20: =O20/0.87+O20/0.87*7.8% -> 173558 | R20: =SUM(Q20:Q26) -> 753186.29 | S20: =SUM(R20:R26) -> 753186.29 | V20: =S20 -> 753186.29
C21: Главный редактор блога | D21: 1 | G21: 80040 | H21: =G21/0.87+G21/0.87*7.8% -> 99176 | I21: =D21*H21 -> 99176 | M21: 1 | N21: =O21/M21 -> 80040 | O21: 80040 | P21: =Q21/M21 -> 99176 | Q21: =O21/0.87+O21/0.87*7.8% -> 99176
C22: Ведущий редактор блога | D22: 1 | G22: 110000 | H22: =G22/0.87+G22/0.87*7.8% -> 136298.85 | I22: =D22*H22 -> 136298.85 | M22: 1 | N22: =O22/M22 -> 110000 | O22: 110000 | P22: =Q22/M22 -> 136298.85 | Q22: =O22/0.87+O22/0.87*7.8% -> 136298.85
C23: Ведущий маркетолог | D23: 1 | G23: 80000 | H23: =G23/0.87+G23/0.87*7.8% -> 99126.437 | I23: =D23*H23 -> 99126.437 | M23: 1 | N23: =O23/M23 -> 80000 | O23: 80000 | P23: =Q23/M23 -> 99126.437 | Q23: =O23/0.87+O23/0.87*7.8% -> 99126.437
C24: Ведущий веб-дизайнер интернет-проектов | D24: 1 | G24: 83955 | H24: =G24/0.87+G24/0.87*7.8% -> 104027 | I24: =D24*H24 -> 104027 | M24: 1 | N24: =O24/M24 -> 83955 | O24: 83955 | P24: =Q24/M24 -> 104027 | Q24: =O24/0.87+O24/0.87*7.8% -> 104027
C25: Автор контент-статей для блога | D25: 1 | G25: 24000 | H25: 24000 | I25: =D25*H25 -> 24000 | M25: 1 | N25: =O25/M25 -> 24000 | O25: 24000 | P25: 24000 | Q25: 24000
C26: PR | D26: 1 | G26: 110000 | H26: 117000 | I26: =D26*H26 -> 117000 | M26: 1 | N26: =O26/M26 -> 110000 | O26: 110000 | P26: 117000 | Q26: 117000
B27: ПРОДАЖИ | C27: Руководитель отдела продаж | D27: 1 | F27: 150000 | G27: 150075 | H27: =G27/0.87+G27/0.87*7.8% -> 185955 | I27: =D27*H27 -> 185955 | J27: =SUM(I27:I31) -> 501957.69 | M27: 1 | N27: =O27/M27 -> 150075 | O27: 150075 | P27: =Q27/M27 -> 185955 | Q27: =O27/0.87+O27/0.87*7.8% -> 185955 | R27: =SUM(Q27:Q31) -> 328486.43 | S27: =SUM(R27:R31) -> 328486.43 | V27: =J27 -> 501957.69
C28: Ведущий менеджер продаж | D28: 1 | F28: 75000 | G28: 75000 | H28: =G28/0.87+G28/0.87*7.8% -> 92931.034 | I28: =D28*H28 -> 92931.034 | M28: 0 | Q28: =O28/0.87+O28/0.87*7.8% -> 0
C29: Старший менеджер продаж | D29: 1 | F29: 65000 | G29: 65000 | H29: =G29/0.87+G29/0.87*7.8% -> 80540.23 | I29: =D29*H29 -> 80540.23 | M29: 0 | Q29: =O29/0.87+O29/0.87*7.8% -> 0
C30: Менеджер продаж | D30: 1 | F30: 55000 | G30: 55000 | H30: =G30/0.87+G30/0.87*7.8% -> 68149.425 | I30: =D30*H30 -> 68149.425 | M30: 1 | N30: =O30/M30 -> 55000 | O30: 55000 | P30: =Q30/M30 -> 68149.425 | Q30: =O30/0.87+O30/0.87*7.8% -> 68149.425
C31: Координатор отдела продаж | D31: 1 | F31: 60000 | G31: 60030 | H31: =G31/0.87+G31/0.87*7.8% -> 74382 | I31: =D31*H31 -> 74382 | M31: 1 | N31: =O31/M31 -> 60030 | O31: 60030 | P31: =Q31/M31 -> 74382 | Q31: =O31/0.87+O31/0.87*7.8% -> 74382
A32: ПРОИЗВОДСТВЕННЫЕ СОТРУДНИКИ | B32: МЕНЕДЖЕРЫ | C32: Senior-эксперт тимлид | D32: 3 | F32: 100000 | G32: 130000 | H32: =G32/0.87+G32/0.87*7.8% -> 161080.46 | I32: =D32*H32 -> 483241.38 | J32: =SUM(I32:I36) -> 2973793.1 | K32: =J32+J37+J38+J41+J46+J50 -> 6542344.8 | L32: =K32*L53/K53 -> 66.544728 | M32: 3 | N32: =O32/M32 -> 113390 | O32: =113390*3 -> 340170 | P32: =Q32/M32 -> 140499.33 | Q32: =O32/0.87+O32/0.87*7.8% -> 421498 | R32: =SUM(Q32:Q36) -> 1969613.8 | S32: =SUM(R32:R36) -> 1969613.8 | T32: =S32+S37+S38+S41+S46+S50 -> 4889852.6 | U32: =T32*U53/T53 -> 59.785402 | V32: =S32 -> 1969613.8
C33: Senior-эксперт | D33: 2 | F33: 80000 | G33: 130000 | H33: =G33/0.87+G33/0.87*7.8% -> 161080.46 | I33: =D33*H33 -> 322160.92 | M33: 2 | N33: =O33/M33 -> 110055 | O33: 220110 | P33: =Q33/M33 -> 136367 | Q33: =O33/0.87+O33/0.87*7.8% -> 272734
C34: Миддл | D34: 14 | F34: 60000 | G34: 100000 | H34: =G34/0.87+G34/0.87*7.8% -> 123908.05 | I34: =D34*H34 -> 1734712.6 | M34: 8 | N34: =O34/M34 -> 76342.5 | O34: 610740 | P34: =Q34/M34 -> 94594.5 | Q34: =O34/0.87+O34/0.87*7.8% -> 756756
C35: Джун | D35: 5 | F35: 50000 | G35: 70000 | H35: =G35/0.87+G35/0.87*7.8% -> 86735.632 | I35: =D35*H35 -> 433678.16 | M35: 8 | N35: =O35/M35 -> 48567.75 | O35: 388542 | P35: =Q35/M35 -> 60179.35 | Q35: =O35/0.87+O35/0.87*7.8% -> 481434.8
C36: Стажер | D36: 0 | F36: 35000 | G36: 50000 | H36: =G36/0.87+G36/0.87*7.8% -> 61954.023 | I36: =D36*H36 -> 0 | M36: 1 | N36: =O36/M36 -> 30015 | O36: 30015 | P36: =Q36/M36 -> 37191 | Q36: =O36/0.87+O36/0.87*7.8% -> 37191
B37: МАРТЕХ | C37: Технический менеджер интернет-проектов | D37: 3 | F37: 55000 | G37: 120000 | H37: =G37/0.87+G37/0.87*7.8% -> 148689.66 | I37: =D37*H37 -> 446068.97 | J37: =I37 -> 446068.97 | M37: 3 | N37: =O37/M37 -> 85115 | O37: 255345 | P37: =Q37/M37 -> 105464.33 | Q37: =O37/0.87+O37/0.87*7.8% -> 316393 | R37: =Q37 -> 316393 | S37: =R37 -> 316393 | V37: =S37 -> 316393
B38: АНАЛИТИКИ | C38: Руководитель отдела аналитики-Senior | D38: 1 | F38: 80000 | G38: 110000 | H38: =G38/0.87+G38/0.87*7.8% -> 136298.85 | I38: =D38*H38 -> 136298.85 | J38: =SUM(I38:I40) -> 297379.31 | M38: 1 | N38: =O38/M38 -> 100050 | O38: 100050 | P38: =Q38/M38 -> 123970 | Q38: =O38/0.87+O38/0.87*7.8% -> 123970 | R38: =SUM(Q38:Q40) -> 260337 | S38: =SUM(R38:R40) -> 260337 | V38: =S38 -> 260337
C39: Старший аналитик-миддл | D39: 1 | F39: 50000 | G39: 70000 | H39: =G39/0.87+G39/0.87*7.8% -> 86735.632 | I39: =D39*H39 -> 86735.632 | M39: 1 | N39: =O39/M39 -> 60030 | O39: 60030 | P39: =Q39/M39 -> 74382 | Q39: =O39/0.87+O39/0.87*7.8% -> 74382
C40: Веб-аналитик-джун | D40: 1 | F40: 40000 | G40: 60000 | H40: =G40/0.87+G40/0.87*7.8% -> 74344.828 | I40: =D40*H40 -> 74344.828 | M40: 1 | N40: =O40/M40 -> 50025 | O40: 50025 | P40: =Q40/M40 -> 61985 | Q40: =O40/0.87+O40/0.87*7.8% -> 61985
B41: ДИЗАЙНЕРЫ | C41: Арт директор Senior-эксперт | D41: 1 | F41: 100000 | G41: 120000 | H41: =G41/0.87+G41/0.87*7.8% -> 148689.66 | I41: =D41*H41 -> 148689.66 | J41: =SUM(I41:I45) -> 1685149.4 | M41: 1 | N41: =O41/M41 -> 130065 | O41: 130065 | P41: =Q41/M41 -> 161161 | Q41: =O41/0.87+O41/0.87*7.8% -> 161161 | R41: =SUM(Q41:Q45) -> 1254567.7 | S41: =SUM(R41:R45) -> 1254567.7 | V41: =S41 -> 1254567.7
C42: Senior-эксперт тимлид | D42: 1 | F42: 100000 | G42: 140000 | H42: =G42/0.87+G42/0.87*7.8% -> 173471.26 | I42: =D42*H42 -> 173471.26 | M42: 1 | N42: =O42/M42 -> 115014 | O42: 115014 | P42: =Q42/M42 -> 142511.6 | Q42: =O42/0.87+O42/0.87*7.8% -> 142511.6
C43: Senior-эксперт | D43: 3 | F43: 80000 | G43: 140000 | H43: =G43/0.87+G43/0.87*7.8% -> 173471.26 | I43: =D43*H43 -> 520413.79 | M43: 2 | N43: =O43/M43 -> 81127.5 | O43: =[8]расшифровка!D79+[8]расшифровка!D78 -> 162255 | P43: =Q43/M43 -> 100523.5 | Q43: =O43/0.87+O43/0.87*7.8% -> 201047
C44: Миддл | D44: 6 | F44: 50000 | G44: 90000 | H44: =G44/0.87+G44/0.87*7.8% -> 111517.24 | I44: =D44*H44 -> 669103.45 | M44: 6 | N44: =O44/M44 -> 66694.167 | O44: =[8]расшифровка!D80+[8]расшифровка!D81+[8]расшифровка!D88+[8]расшифровка!D87+[8]расшифровка!D84+[8]расшифровка!D89 -> 400165 | P44: =Q44/M44 -> 82639.439 | Q44: =O44/0.87+O44/0.87*7.8% -> 495836.63
C45: Джун | D45: 2 | F45: 40000 | G45: 70000 | H45: =G45/0.87+G45/0.87*7.8% -> 86735.632 | I45: =D45*H45 -> 173471.26 | M45: 3 | N45: =O45/M45 -> 68333.333 | O45: =[8]расшифровка!D86+[8]расшифровка!D85+[8]расшифровка!D83 -> 205000 | P45: =Q45/M45 -> 84670.498 | Q45: =O45/0.87+O45/0.87*7.8% -> 254011.49
B46: КОНТЕНТ | C46: Senior-эксперт тимлид | D46: 1 | F46: 80000 | G46: 100000 | H46: =G46/0.87+G46/0.87*7.8% -> 123908.05 | I46: =D46*H46 -> 123908.05 | J46: =SUM(I46:I49) -> 768229.89 | M46: 1 | N46: =O46/M46 -> 95260 | O46: =[8]расшифровка!D94 -> 95260 | P46: =Q46/M46 -> 118034.8 | Q46: =O46/0.87+O46/0.87*7.8% -> 118034.8 | R46: =SUM(Q46:Q49) -> 753206.03 | S46: =SUM(R46:R49) -> 753206.03 | V46: =S46 -> 753206.03
C47: Senior-эксперт редактор | D47: 1 | F47: 70000 | G47: 90000 | H47: =G47/0.87+G47/0.87*7.8% -> 111517.24 | I47: =D47*H47 -> 111517.24 | M47: 1 | N47: =O47/M47 -> 80040 | O47: =[8]расшифровка!D95 -> 80040 | P47: =Q47/M47 -> 99176 | Q47: =O47/0.87+O47/0.87*7.8% -> 99176
C48: Копирайтер/корректор-миддл | D48: 1 | F48: 50000 | G48: 70000 | H48: =G48/0.87+G48/0.87*7.8% -> 86735.632 | I48: =D48*H48 -> 86735.632 | M48: 1 | N48: =O48/M48 -> 70035 | O48: =[8]расшифровка!D97 -> 70035 | P48: =Q48/M48 -> 86779 | Q48: =O48/0.87+O48/0.87*7.8% -> 86779
C49: Копирайтер/корректор-джун | D49: 6 | F49: 40000 | G49: 60000 | H49: =G49/0.87+G49/0.87*7.8% -> 74344.828 | I49: =D49*H49 -> 446068.97 | M49: 8 | N49: =O49/M49 -> 45317.5 | O49: =[8]расшифровка!D98+[8]расшифровка!D99+[8]расшифровка!D100+[8]расшифровка!D101+[8]расшифровка!D102+[8]расшифровка!D103+[8]расшифровка!D106+[8]расшифровка!D107 -> 362540 | P49: =Q49/M49 -> 56152.029 | Q49: =O49/0.87+O49/0.87*7.8% -> 449216.23
B50: ВЕРСТКА | C50: HTML-верстальщик Senior-эксперт тимлид | D50: 1 | F50: 80000 | G50: 100000 | H50: =G50/0.87+G50/0.87*7.8% -> 123908.05 | I50: =D50*H50 -> 123908.05 | J50: =SUM(I50:I52) -> 371724.14 | M50: 1 | N50: =O50/M50 -> 100000 | O50: =[8]расшифровка!D113 -> 100000 | P50: =Q50/M50 -> 123908.05 | Q50: =O50/0.87+O50/0.87*7.8% -> 123908.05 | R50: =SUM(Q50:Q52) -> 335735.05 | S50: =SUM(R50:R52) -> 335735.05 | V50: =S50 -> 335735.05
C51: HTML-верстальщик Senior-эксперт | D51: 1 | F51: 60000 | G51: 80000 | H51: =G51/0.87+G51/0.87*7.8% -> 99126.437 | I51: =D51*H51 -> 99126.437 | M51: 1 | N51: =O51/M51 -> 60465 | O51: =[8]расшифровка!D115 -> 60465 | P51: =Q51/M51 -> 74921 | Q51: =O51/0.87+O51/0.87*7.8% -> 74921
C52: HTML-верстальщик миддл | D52: 2 | F52: 40000 | G52: 60000 | H52: =G52/0.87+G52/0.87*7.8% -> 74344.828 | I52: =D52*H52 -> 148689.66 | M52: 2 | N52: =O52/M52 -> 55245 | O52: =[8]расшифровка!D116+[8]расшифровка!D117 -> 110490 | P52: =Q52/M52 -> 68453 | Q52: =O52/0.87+O52/0.87*7.8% -> 136906
I53: ИТОГО | J53: =SUM(J4:J52) -> 9831499.8 | K53: =K32+K4 -> 9831499.8 | L53: 100 | R53: ИТОГО | S53: =SUM(S4:S52) -> 8005536.3 | T53: =T32+T4 -> 8179007.6 | U53: 100 | V53: =SUM(V4:V52) -> 8179007.6
A54: CS | B54: КРЕАТИВНАЯ КОМАНДА | C54: Руководитель отдела веб-дизайна | D54: 1 | F54: 100000 | G54: 100050 | H54: =G54/0.87+G54/0.87*7.8% -> 123970 | I54: =D54*H54 -> 123970 | J54: =SUM(I54:I57) -> 1059475.7 | K54: =J54 -> 1059475.7 | L54: 8 | M54: 1 | N54: =O54/M54 -> 100050 | O54: 100050 | P54: =Q54/M54 -> 123970 | Q54: =O54/0.87+O54/0.87*7.8% -> 123970 | R54: =SUM(Q54:Q57) -> 1010757.6 | S54: =SUM(R54:R57) -> 1010757.6 | T54: =S54 -> 1010757.6 | U54: 100 | V54: =T54 -> 1010757.6
C55: Разработчик Senior-эксперт | D55: 3 | F55: 80000 | G55: 95000 | H55: =G55/0.87+G55/0.87*7.8% -> 117712.64 | I55: =D55*H55 -> 353137.93 | M55: 3 | N55: 118442.67 | O55: 355328 | P55: 146759.99 | Q55: 440279.98
C56: Менеджер проектов | D56: 3 | F56: 80000 | G56: 110000 | H56: =G56/0.87+G56/0.87*7.8% -> 136298.85 | I56: =D56*H56 -> 408896.55 | M56: 3 | N56: 81780 | O56: 245340 | P56: 101332 | Q56: 303996
C57: Senior-эксперт креативных идей | D57: 1 | F57: 80000 | G57: 140000 | H57: =G57/0.87+G57/0.87*7.8% -> 173471.26 | I57: =D57*H57 -> 173471.26 | M57: 1 | N57: 115014 | O57: 115014 | P57: 142511.6 | Q57: 142511.6
A58: ИТОГО | K58: =K53+K54 -> 10890976 | T58: =T53+T54 -> 9189765.2
A60: МЕНЕДЖЕРЫ | B60: Senior-эксперт тимлид | C60: 3 | F60: 140000 | G60: =F60/0.87+F60/0.87*7.8% -> 173471.26 | H60: =C60*G60 -> 520413.79 | I60: =SUM(H60:H64) -> 3035747.1 | J60: 300000 | K60: =C60*J60 -> 900000
B61: Senior-эксперт | C61: 2 | F61: 140000 | G61: =F61/0.87+F61/0.87*7.8% -> 173471.26 | H61: =C61*G61 -> 346942.53 | J61: 800000 | K61: =C61*J61 -> 1600000
B62: Миддл | C62: 14 | F62: 100000 | G62: =F62/0.87+F62/0.87*7.8% -> 123908.05 | H62: =C62*G62 -> 1734712.6 | J62: 800000 | K62: =C62*J62 -> 11200000
B63: Джун | C63: 5 | F63: 70000 | G63: =F63/0.87+F63/0.87*7.8% -> 86735.632 | H63: =C63*G63 -> 433678.16 | J63: 600000 | K63: =C63*J63 -> 3000000
B64: Стажер | C64: 0 | F64: 50000 | G64: =F64/0.87+F64/0.87*7.8% -> 61954.023 | H64: =C64*G64 -> 0 | J64: 450000
K65: =SUM(K60:K64) -> 16700000
A66: ПЛАН | E66: ФАКТ
A67: Выручка итого | B67: =B68+B76+B79 -> 18800000 | E67: Выручка итого | F67: 0 | G67: ПЛАН ФОТ НА 2025 ГОД
A68: Выручка ЕМС | B68: =K65 -> 16700000 | C68: =B68 -> 16700000 | D68: % | E68: Выручка ЕМС | F68: =SUM(O60:O64) -> 0 | G68: 1 | H68: % | I68: 2 | J68: 3 | K68: 4 | L68: 5 | M68: 6 | N68: 7 | O68: 8 | P68: 9 | Q68: 10 | R68: 11 | S68: 12
A69: произв | B69: =K32 -> 6542344.8 | C69: =SUM(C70:C75)+SUM(C77:C78) -> 7601820.6 | D69: =B69/B68*100 -> 39.175718 | E69: произв | G69: =SUM(G70:G75)+SUM(G77:G78) -> 5900610.2 | I69: =SUM(I70:I78) -> 6031703.2 | J69: =SUM(J70:J78) -> 6169698.4 | K69: =SUM(K70:K78) -> 6312299.8 | L69: =SUM(L70:L78) -> 6459672 | M69: =SUM(M70:M78) -> 6611985.6 | N69: =SUM(N70:N78) -> 6769417.5 | O69: =SUM(O70:O78) -> 6932151 | P69: =SUM(P70:P78) -> 7100376.2 | ... S69: =SUM(S70:S78) -> 7640008.7
A70: в т.ч. менедж. | C70: =J32 -> 2973793.1 | D70: =C70/$C$68*100 -> 17.807144 | E70: в т.ч. менедж. | G70: =R32 -> 1969613.8 | H70: =(C70-G70)/G70*100 -> 50.983564 | I70: =G70+G70*($H$70/13)% -> 2046858.4 | J70: =I70+I70*($H$70/13)% -> 2127132.3 | K70: =J70+J70*($H$70/13)% -> 2210554.5 | L70: =K70+K70*($H$70/13)% -> 2297248.3 | M70: =L70+L70*($H$70/13)% -> 2387342 | N70: =M70+M70*($H$70/13)% -> 2480969.1 | O70: =N70+N70*($H$70/13)% -> 2578268.1 | P70: =O70+O70*($H$70/13)% -> 2679382.9 | Q70: =P70+P70*($H$70/13)% -> 2784463.3 | ... S70: =R70+R70*($H$70/13)% -> 3007148.8
A71: в т.ч. мартех | C71: =J37 -> 446068.97 | D71: =C71/$C$68*100 -> 2.6710716 | E71: в т.ч. мартех | G71: =R37 -> 316393 | H71: =(C71-G71)/G71*100 -> 40.985725 | I71: =G71+G71*($H$71/13)% -> 326368.07 | J71: =I71+I71*($H$71/13)% -> 336657.64 | K71: =J71+J71*($H$71/13)% -> 347271.6 | L71: =K71+K71*($H$71/13)% -> 358220.2 | M71: =L71+L71*($H$71/13)% -> 369513.98 | N71: =M71+M71*($H$71/13)% -> 381163.83 | O71: =N71+N71*($H$71/13)% -> 393180.96 | P71: =O71+O71*($H$71/13)% -> 405576.97 | Q71: =P71+P71*($H$71/13)% -> 418363.79 | ... S71: =R71+R71*($H$71/13)% -> 445159.55
A72: в т.ч. дизайнеры | C72: =J41 -> 1685149.4 | D72: =C72/$C$68*100 -> 10.090715 | E72: в т.ч. дизайнеры | G72: =R41 -> 1254567.7 | H72: =(C72-G72)/G72*100 -> 34.32112 | I72: =G72+G72*($H$72/13)% -> 1287689.4 | J72: =I72+I72*($H$72/12)% -> 1324518.5 | K72: =J72+J72*($H$72/12)% -> 1362401 | L72: =K72+K72*($H$72/12)% -> 1401366.9 | M72: =L72+L72*($H$72/12)% -> 1441447.3 | N72: =M72+M72*($H$72/12)% -> 1482674.1 | O72: =N72+N72*($H$72/12)% -> 1525079.9 | P72: =O72+O72*($H$72/12)% -> 1568698.6 | Q72: =P72+P72*($H$72/12)% -> 1613564.9 | ... S72: =R72+R72*($H$72/12)% -> 1707183.7
A73: в т.ч. верстальщики | C73: =J50 -> 371724.14 | D73: =C73/$C$68*100 -> 2.225893 | E73: в т.ч. верстальщики | G73: =R50 -> 335735.05 | H73: =(C73-G73)/G73*100 -> 10.719492 | I73: =G73+G73*($H$73/12)% -> 338734.14 | J73: =I73+I73*($H$73/13)% -> 341527.26 | K73: =J73+J73*($H$73/13)% -> 344343.41 | L73: =K73+K73*($H$73/13)% -> 347182.79 | M73: =L73+L73*($H$73/13)% -> 350045.57 | N73: =M73+M73*($H$73/13)% -> 352931.97 | O73: =N73+N73*($H$73/13)% -> 355842.16 | P73: =O73+O73*($H$73/13)% -> 358776.35 | Q73: =P73+P73*($H$73/13)% -> 361734.73 | ... S73: =R73+R73*($H$73/13)% -> 367724.89
A74: в т.ч. авторы | C74: =J46 -> 768229.89 | D74: =C74/$C$68*100 -> 4.600179 | E74: в т.ч. авторы | G74: =R46 -> 753206.03 | H74: =(C74-G74)/G74*100 -> 1.9946535 | I74: =G74+G74*($H$74/13)% -> 754361.72 | J74: =I74+I74*($H$74/13)% -> 755519.17 | K74: =J74+J74*($H$74/13)% -> 756678.4 | L74: =K74+K74*($H$74/13)% -> 757839.41 | M74: =L74+L74*($H$74/13)% -> 759002.2 | N74: =M74+M74*($H$74/13)% -> 760166.77 | O74: =N74+N74*($H$74/13)% -> 761333.13 | P74: =O74+O74*($H$74/13)% -> 762501.28 | Q74: =P74+P74*($H$74/13)% -> 763671.23 | ... S74: =R74+R74*($H$74/13)% -> 766016.5
A75: в т.ч. аналитики | C75: =J38 -> 297379.31 | D75: =C75/$C$68*100 -> 1.7807144 | E75: в т.ч. аналитики | G75: =R38 -> 260337 | H75: =(C75-G75)/G75*100 -> 14.2286 | I75: =G75+G75*($H$75/13)% -> 263186.41 | J75: =I75+I75*($H$75/13)% -> 266067 | K75: =J75+J75*($H$75/13)% -> 268979.13 | L75: =K75+K75*($H$75/13)% -> 271923.13 | M75: =L75+L75*($H$75/13)% -> 274899.34 | N75: =M75+M75*($H$75/13)% -> 277908.14 | O75: =N75+N75*($H$75/13)% -> 280949.86 | P75: =O75+O75*($H$75/13)% -> 284024.88 | Q75: =P75+P75*($H$75/13)% -> 287133.56 | ... S75: =R75+R75*($H$75/13)% -> 293453.35
A76: Выручка CS | B76: 2000000 | D76: =D77+D78 -> 52.973787 | E76: Выручка CS | F76: 0
A77: Управление CS | C77: =I54+I57 -> 297441.26 | D77: =C77/B76*100 -> 14.872063 | E77: Управление CS | G77: =Q54+Q57 -> 266481.6 | H77: =(C77-G77)/G77*100 -> 11.617937 | I77: =G77+G77*($H$77/13)% -> 268863.11 | J77: =I77+I77*($H$77/13)% -> 271265.91 | K77: =J77+J77*($H$77/13)% -> 273690.18 | L77: =K77+K77*($H$77/13)% -> 276136.11 | M77: =L77+L77*($H$77/13)% -> 278603.91 | N77: =M77+M77*($H$77/13)% -> 281093.75 | O77: =N77+N77*($H$77/13)% -> 283605.85 | P77: =O77+O77*($H$77/13)% -> 286140.4 | Q77: =P77+P77*($H$77/13)% -> 288697.61 | ... S77: =R77+R77*($H$77/13)% -> 293880.77
A78: Дизайнеры, менеджеры | C78: =I56+I55 -> 762034.48 | D78: =C78/B76*100 -> 38.101724 | E78: Дизайнеры, менеджеры | G78: =Q55+Q56 -> 744275.98 | H78: =(C78-G78)/G78*100 -> 2.3860102 | I78: =G78+G78*($H$78/13)% -> 745642.02 | J78: =I78+I78*($H$78/13)% -> 747010.57 | K78: =J78+J78*($H$78/13)% -> 748381.62 | L78: =K78+K78*($H$78/13)% -> 749755.2 | M78: =L78+L78*($H$78/13)% -> 751131.29 | N78: =M78+M78*($H$78/13)% -> 752509.91 | O78: =N78+N78*($H$78/13)% -> 753891.06 | P78: =O78+O78*($H$78/13)% -> 755274.75 | Q78: =P78+P78*($H$78/13)% -> 756660.98 | ... S78: =R78+R78*($H$78/13)% -> 759441.06
A79: Выручка Monk | B79: 100000 | C79: 100000 | E79: Выручка Monk | F79: 0 | G79: 0
A80: непроизв | B80: =K4 -> 3289155 | D80: =B80/$B$67*100 -> 17.495505 | E80: непроизв | G80: =T4 -> 3289155
A81: общие затраты | B81: 2000000 | D81: =B81/$C$68*100 -> 11.976048 | E81: общие затраты | G81: 2000000
A82: налоги | B82: =B67*D82/100 -> 752000 | D82: 4 | E82: налоги
A83: чистая прибыль | B83: =B68+B76+B79-B69-B80-B81-B82-C77-C78 -> 5157024.4 | D83: =B83/$C$68*100 -> 30.880386 | E83: чистая прибыль | F83: =F68+F76+F79-F69-F80-F81-F82-G77-G78 -> -1010757.6
A88: =Фин.модель!D9 -> 12422914 | B88: =Фин.модель!F9 -> 12630400 | C88: =Фин.модель!H9 -> 16723253 | D88: =Фин.модель!J9 -> 15989617 | E88: =Фин.модель!L9 -> 15585393 | F88: =Фин.модель!N9 -> 14875072 | G88: =Фин.модель!P9 -> 15830169 | H88: =Фин.модель!R9 -> 16353370 | I88: =Фин.модель!T9 -> 17801453 | J88: =Фин.модель!V9 -> 18362765 | K88: =Фин.модель!X9 -> 19010717 | L88: =Фин.модель!Z9 -> 19367215
A89: =$B$67-A88 -> 6377086.3 | B89: =$B$67-B88 -> 6169599.6 | C89: =$B$67-C88 -> 2076747.1 | D89: =$B$67-D88 -> 2810382.6 | E89: =$B$67-E88 -> 3214607 | F89: =$B$67-F88 -> 3924928.4 | G89: =$B$67-G88 -> 2969830.7 | H89: =$B$67-H88 -> 2446629.6 | ... L89: =$B$67-L88 -> -567215.48
G92: З/пл на руки | H92: Налоги с ФОТ
A94: HR | B94: 1 | C94: Масько Анастасия Александровна | D94: Оплата труда сотрудников обслуживающих подразделений | E94: ЗП HR команды | F94: 1 | G94: =VLOOKUP(C94,'[9]2025'!$A$10:$C$97,2,0) -> 47033.85 | H94: =VLOOKUP(C94,'[9]2025'!$A$10:$C$97,3,0) -> 11305.84
A95: АП | B95: 1 | C95: Ильин Константин Иванович | D95: Оплата труда сотрудников обслуживающих подразделений | E95: ЗП административного персонала | F95: 1 | G95: =VLOOKUP(C95,'[9]2025'!$A$10:$C$97,2,0) -> 8765.25 | H95: =VLOOKUP(C95,'[9]2025'!$A$10:$C$97,3,0) -> 2095.6
A96: АП | B96: 1 | C96: Илья | D96: Оплата труда сотрудников обслуживающих подразделений | E96: ЗП административного персонала | F96: 1 | G96: 50000
A97: АП | B97: 1 | C97: Кириченко Виктория Николаевна | D97: Оплата труда сотрудников обслуживающих подразделений | E97: ЗП административного персонала | F97: 1 | G97: =VLOOKUP(C97,'[9]2025'!$A$10:$C$97,2,0) -> 58290 | H97: =VLOOKUP(C97,'[9]2025'!$A$10:$C$97,3,0) -> 13936
A98: АП | B98: 1 | C98: Марилова Ольга Сергеевна | D98: Оплата труда сотрудников обслуживающих подразделений | E98: ЗП административного персонала | F98: 1 | G98: =VLOOKUP(C98,'[9]2025'!$A$10:$C$97,2,0) -> 60030 | H98: =VLOOKUP(C98,'[9]2025'!$A$10:$C$97,3,0) -> 14352
A99: АП | B99: 1 | C99: Маркова Светлана Геннадьевна | D99: Оплата труда сотрудников обслуживающих подразделений | E99: ЗП административного персонала | F99: 1 | G99: =VLOOKUP(C99,'[9]2025'!$A$10:$C$97,2,0) -> 91572 | H99: =VLOOKUP(C99,'[9]2025'!$A$10:$C$97,3,0) -> 20540
A100: АП | B100: 1 | C100: Пикулина София Владимировна | D100: Оплата труда сотрудников обслуживающих подразделений | E100: ЗП административного персонала | F100: 1 | G100: =VLOOKUP(C100,'[9]2025'!$A$10:$C$97,2,0) -> 50025 | H100: =VLOOKUP(C100,'[9]2025'!$A$10:$C$97,3,0) -> 11960
A101: АП | B101: 1 | C101: Пискунова Надежда Константиновна | D101: Оплата труда сотрудников обслуживающих подразделений | E101: ЗП административного персонала | F101: 1 | G101: =VLOOKUP(C101,'[9]2025'!$A$10:$C$97,2,0) -> 107746 | H101: =VLOOKUP(C101,'[9]2025'!$A$10:$C$97,3,0) -> 16224
A102: АП | B102: 1 | C102: Сафоничев Александр Павлович | D102: Оплата труда сотрудников обслуживающих подразделений | E102: ЗП административного персонала | F102: 1 | G102: =VLOOKUP(C102,'[9]2025'!$A$10:$C$97,2,0) -> 120007.8 | H102: =VLOOKUP(C102,'[9]2025'!$A$10:$C$97,3,0) -> 28691.52
A103: АП | B103: 1 | C103: Федярова Карина Сергеевна | D103: Оплата труда сотрудников обслуживающих подразделений | E103: ЗП административного персонала | F103: 1 | G103: =VLOOKUP(C103,'[9]2025'!$A$10:$C$97,2,0) -> 60030 | H103: =VLOOKUP(C103,'[9]2025'!$A$10:$C$97,3,0) -> 14352
A104: все | B104: 1 | C104: Аблов Андрей Дмитриевич | D104: Оплата труда производственного подразделения | E104: Заработная плата Мартех специалисты | F104: 1 | G104: =VLOOKUP(C104,'[9]2025'!$A$10:$C$97,2,0) -> 100050 | H104: =VLOOKUP(C104,'[9]2025'!$A$10:$C$97,3,0) -> 23920
A105: все | B105: 1 | C105: Абрамова Екатерина Владимировна | D105: Оплата труда производственного подразделения | E105: Заработная плата Мартех специалисты | F105: 1 | G105: =VLOOKUP(C105,'[9]2025'!$A$10:$C$97,2,0) -> 110021.85 | H105: =VLOOKUP(C105,'[9]2025'!$A$10:$C$97,3,0) -> 26365.04
A106: все | B106: 1 | C106: Андреева Валентина Юрьевна | D106: Оплата труда производственного подразделения | E106: Заработная плата Менеджеров/маркетологов | F106: 1 | G106: =VLOOKUP(C106,'[9]2025'!$A$10:$C$97,2,0) -> 90011.85 | H106: =VLOOKUP(C106,'[9]2025'!$A$10:$C$97,3,0) -> 21581.04 | I106: миддл
A107: все | B107: 1 | C107: Балабанова Евгения Юрьевна | D107: Оплата труда производственного подразделения | E107: Заработная плата Дизайнеры (Creative Soldiers) | F107: 1 | G107: =VLOOKUP(C107,'[9]2025'!$A$10:$C$97,2,0) -> 60394 | H107: =VLOOKUP(C107,'[9]2025'!$A$10:$C$97,3,0) -> 13988
A108: все | B108: 1 | C108: Баландина Наталия Владимировна | D108: Оплата труда производственного подразделения | E108: Заработная плата Редакции | F108: 1 | G108: =VLOOKUP(C108,'[9]2025'!$A$10:$C$97,2,0) -> 18470.729 | H108: =VLOOKUP(C108,'[9]2025'!$A$10:$C$97,3,0) -> 2025.1858
...

Sheet Фин.модель сокр.
B2: Выручка за год план | C2: =D7+E7+F7+G7+H7+I7+J7+K7+L7+M7+N7+O7 -> 1.9495234e+08
B3: Чистая прибыль за год план | C3: =O24 -> 53778632
B4: Рентабельность по чистой прибыли | C4: =C3/C2 -> 0.27585528
D5: план | E5: план | F5: план | G5: план | H5: план | I5: план | J5: план | K5: план | L5: план | M5: план | N5: план | O5: план | P5: итого план
B6: Периоды | D6: 1 | E6: 2 | F6: 3 | G6: 4 | H6: 5 | I6: 6 | J6: 7 | K6: 8 | L6: 9 | M6: 10 | N6: 11 | O6: 12 | P6: TOTAL
B7: Выручка всего | D7: =Фин.модель!D9 -> 12422914 | E7: =Фин.модель!F9 -> 12630400 | F7: =Фин.модель!H9 -> 16723253 | G7: =Фин.модель!J9 -> 15989617 | H7: =Фин.модель!L9 -> 15585393 | I7: =Фин.модель!N9 -> 14875072 | J7: =Фин.модель!P9 -> 15830169 | K7: =Фин.модель!R9 -> 16353370 | L7: =Фин.модель!T9 -> 17801453 | M7: =Фин.модель!V9 -> 18362765 | N7: =Фин.модель!X9 -> 19010717 | O7: =Фин.модель!Z9 -> 19367215 | P7: =SUM(D7:O7) -> 1.9495234e+08
B8: БЛОК ПРОДАЖ, лиды | D8: =Фин.модель!D10 -> 38.70614 | E8: =Фин.модель!F10 -> 38.70614 | F8: =Фин.модель!H10 -> 38.70614 | G8: =Фин.модель!J10 -> 54.495614 | H8: =Фин.модель!L10 -> 54.495614 | I8: =Фин.модель!N10 -> 54.495614 | J8: =Фин.модель!P10 -> 76.535088 | K8: =Фин.модель!R10 -> 70.285088 | L8: =Фин.модель!T10 -> 70.285088 | M8: =Фин.модель!V10 -> 86.074561 | N8: =Фин.модель!X10 -> 86.074561 | O8: =Фин.модель!Z10 -> 86.074561 | P8: =SUM(D8:O8) -> 754.93421
B9: ИТОГО ПРОДАЖ-ПЛАН total, руб. | D9: =Фин.модель!D35 -> 875000 | E9: =Фин.модель!F35 -> 875000 | F9: =Фин.модель!H35 -> 3035000 | G9: =Фин.модель!J35 -> 3230000 | H9: =Фин.модель!L35 -> 3230000 | I9: =Фин.модель!N35 -> 3230000 | J9: =Фин.модель!P35 -> 15527000 | K9: =Фин.модель!R35 -> 3527000 | L9: =Фин.модель!T35 -> 3527000 | M9: =Фин.модель!V35 -> 3839300 | N9: =Фин.модель!X35 -> 3839300 | O9: =Фин.модель!Z35 -> 3839300 | P9: =SUM(D9:O9) -> 48573900
B10: Прямые расходы | D10: =Фин.модель!D58 -> -6250610.2 | E10: =Фин.модель!F58 -> -6337829.8 | F10: =Фин.модель!H58 -> -6381703.2 | G10: =Фин.модель!J58 -> -6381703.1 | H10: =Фин.модель!L58 -> -6381703.1 | I10: =Фин.модель!N58 -> -6381703.1 | J10: =Фин.модель!P58 -> -6381703.1 | K10: =Фин.модель!R58 -> -6381703.1 | L10: =Фин.модель!T58 -> -7282151 | M10: =Фин.модель!V58 -> -7450376.2 | N10: =Фин.модель!X58 -> -7624290.1 | O10: =Фин.модель!Z58 -> -7804096.9 | P10: =SUM(D10:O10) -> -81039573
B11: Валовая прибыль | D11: =Фин.модель!D70 -> 6172303.5 | E11: =Фин.модель!F70 -> 6292570.6 | F11: =Фин.модель!H70 -> 10341550 | G11: =Фин.модель!J70 -> 9607914.3 | H11: =Фин.модель!L70 -> 9203689.9 | I11: =Фин.модель!N70 -> 8493368.5 | J11: =Фин.модель!P70 -> 9448466.2 | K11: =Фин.модель!R70 -> 9971667.3 | L11: =Фин.модель!T70 -> 10519302 | M11: =Фин.модель!V70 -> 10912389 | N11: =Фин.модель!X70 -> 11386427 | O11: =Фин.модель!Z70 -> 11563119 | P11: =SUM(D11:O11) -> 1.1391277e+08
B12: Рентабельность по валовой прибыли,%% | D12: =D11/D7 -> 0.4968483 | E12: =E11/E7 -> 0.49820832 | F12: =F11/F7 -> 0.61839343 | G12: =G11/G7 -> 0.60088457 | H12: =H11/H7 -> 0.59053306 | I12: =I11/I7 -> 0.57098001 | J12: =J11/J7 -> 0.59686451 | K12: =K11/K7 -> 0.60976221 | ... P12: =P11/P7 -> 0.58431085
B14: Косвенные расходы | D14: =Фин.модель!D73 -> -4434898.3 | E14: =Фин.модель!F73 -> -4693431.3 | F14: =Фин.модель!H73 -> -4763938.3 | G14: =Фин.модель!J73 -> -4744130.1 | H14: =Фин.модель!L73 -> -5028216.1 | I14: =Фин.модель!N73 -> -4714037.4 | J14: =Фин.модель!P73 -> -4659825 | K14: =Фин.модель!R73 -> -4673951.5 | L14: =Фин.модель!T73 -> -4713049.7 | M14: =Фин.модель!V73 -> -4728205.1 | N14: =Фин.модель!X73 -> -5290699.8 | O14: =Фин.модель!Z73 -> -5350325.3 | P14: =SUM(D14:O14) -> -57794708
B15: Административные расходы | D15: =Фин.модель!D74 -> -3101044.2 | E15: =Фин.модель!F74 -> -3261873.9 | F15: =Фин.модель!H74 -> -3238245.3 | G15: =Фин.модель!J74 -> -3235310.8 | H15: =Фин.модель!L74 -> -3528693.9 | I15: =Фин.модель!N74 -> -3230852.6 | J15: =Фин.модель!P74 -> -3154673 | K15: =Фин.модель!R74 -> -3156765.8 | L15: =Фин.модель!T74 -> -3162558.1 | M15: =Фин.модель!V74 -> -3164803.4 | N15: =Фин.модель!X74 -> -3712395.2 | O15: =Фин.модель!Z74 -> -3763821.2 | P15: =SUM(D15:O15) -> -39711037
B16: Коммерческие расходы | D16: =Фин.модель!D95 -> -1333854.1 | E16: =Фин.модель!F95 -> -1431557.4 | F16: =Фин.модель!H95 -> -1525693 | G16: =Фин.модель!J95 -> -1508819.4 | H16: =Фин.модель!L95 -> -1499522.2 | I16: =Фин.модель!N95 -> -1483184.8 | J16: =Фин.модель!P95 -> -1505152.1 | K16: =Фин.модель!R95 -> -1517185.7 | L16: =Фин.модель!T95 -> -1550491.6 | M16: =Фин.модель!V95 -> -1563401.8 | N16: =Фин.модель!X95 -> -1578304.7 | O16: =Фин.модель!Z95 -> -1586504.1 | P16: =SUM(D16:O16) -> -18083671
B17: Расходы всего | D17: =D10+D14 -> -10685508 | E17: =E10+E14 -> -11031261 | F17: =F10+F14 -> -11145642 | G17: =G10+G14 -> -11125833 | H17: =H10+H14 -> -11409919 | I17: =I10+I14 -> -11095740 | J17: =J10+J14 -> -11041528 | K17: =K10+K14 -> -11055655 | ... O17: =O10+O14 -> -13154422 | P17: =SUM(D17:O17) -> -1.3883428e+08
B18: Операционная прибыль(EBITDA) | D18: =D11+D14 -> 1737405.2 | E18: =E11+E14 -> 1599139.3 | F18: =F11+F14 -> 5577611.4 | G18: =G11+G14 -> 4863784.2 | H18: =H11+H14 -> 4175473.8 | I18: =I11+I14 -> 3779331.1 | J18: =J11+J14 -> 4788641.2 | K18: =K11+K14 -> 5297715.8 | ... O18: =O11+O14 -> 6212793.2 | P18: =P7+P17 -> 56118060
B19: Рентабельность по Операционной прибыли,%% | D19: =D18/D7 -> 0.13985489 | E19: =E18/E7 -> 0.12661034 | F19: =F18/F7 -> 0.33352431 | G19: =G18/G7 -> 0.3041839 | H19: =H18/H7 -> 0.26790943 | I19: =I18/I7 -> 0.25407146 | J19: =J18/J7 -> 0.30250095 | K19: =K18/K7 -> 0.32395254 | ... O19: =O18/O7 -> 0.32078918
B21: Налоги | C21: 0.012 | D21: =-D7*$C$21 -> -149074.96 | E21: =-E7*$C$21 -> -151564.81 | F21: =-F7*$C$21 -> -200679.03 | G21: =-G7*$C$21 -> -191875.41 | H21: =-H7*$C$21 -> -187024.72 | I21: =-I7*$C$21 -> -178500.86 | J21: =-J7*$C$21 -> -189962.03 | K21: =-K7*$C$21 -> -196240.44 | ... O21: =-O7*$C$21 -> -232406.59 | P21: =SUM(D21:O21) -> -2339428.1
B22: Чистая прибыль | D22: =D7+D17+D21 -> 1588330.3 | E22: =E7+E17+E21 -> 1447574.5 | F22: =F7+F17+F21 -> 5376932.3 | G22: =G7+G17+G21 -> 4671908.8 | H22: =H7+H17+H21 -> 3988449.1 | I22: =I7+I17+I21 -> 3600830.2 | J22: =J7+J17+J21 -> 4598679.2 | K22: =K7+K17+K21 -> 5101475.4 | ... O22: =O7+O17+O21 -> 5980386.7 | P22: =SUM(D22:O22) -> 53778632
B23: Рентабельность по ЧП,%% | D23: =D22/D7 -> 0.12785489 | E23: =E22/E7 -> 0.11461034 | F23: =F22/F7 -> 0.32152431 | G23: =G22/G7 -> 0.2921839 | H23: =H22/H7 -> 0.25590943 | I23: =I22/I7 -> 0.24207146 | J23: =J22/J7 -> 0.29050095 | K23: =K22/K7 -> 0.31195254 | ... P23: =P22/P7 -> 0.27585528
B24: Чистая прибыль накопленным итогом | D24: =D22 -> 1588330.3 | E24: =D24+E22 -> 3035904.8 | F24: =E24+F22 -> 8412837.1 | G24: =F24+G22 -> 13084746 | H24: =G24+H22 -> 17073195 | I24: =H24+I22 -> 20674025 | J24: =I24+J22 -> 25272704 | K24: =J24+K22 -> 30374180 | L24: =K24+L22 -> 35966815 | ... O24: =N24+O22 -> 53778632 | P24: =O24 -> 53778632

Sheet Выручка тех. с новых клиентов
A1: Название проекта | B1: Месяца | N1: Итого
B2: 1 | C2: 2 | D2: 3 | E2: 4 | F2: 5 | G2: 6 | H2: 7 | I2: 8 | J2: 9 | K2: 10 | L2: 11 | M2: 12
A3: Калькулятор-металла.рф | B3: 113652 | C3: 117663 | D3: 77092 | E3: 77092 | F3: 77092 | G3: 77092 | H3: 77092 | I3: 77092 | J3: 77092 | K3: 77092 | L3: 77092 | M3: 77092 | N3: 1 002 235₽
A4: Яндекс Плюс | B4: 563250 | C4: 563250 | D4: 563250 | E4: 563250 | F4: 563250 | G4: 563250 | H4: 563250 | I4: 563250 | J4: 563250 | K4: 563250 | L4: 563250 | M4: 563250 | N4: 6 759 000₽
A5: Экспобанк | B5: 515975 | C5: 320730 | D5: 320730 | E5: 320730 | F5: 205450 | G5: 205450 | H5: 205450 | I5: 205450 | J5: 205450 | K5: 205450 | L5: 205450 | M5: 205450 | N5: 3 121 765₽
A6: Grundig | B6: 747600 | C6: 747 600 ₽ | D6: 269200 | E6: 269200 | F6: 269200 | G6: 182300 | H6: 182300 | I6: 182300 | J6: 182300 | K6: 182300 | L6: 182300 | M6: 182300 | N6: 3 312 350₽
A7: ACUVUE | B7: 1100000 | C7: 1100000 | D7: 1100000 | E7: 1100000 | F7: 1100000 | G7: 1100000 | H7: 1100000 | I7: 1100000 | J7: 1100000 | K7: 1100000 | L7: 1100000 | M7: 1100000 | N7: =SUM(B7:M7) -> 13200000
A8: Итого ежемесячно | B8: =SUM(B3:B7) -> 3040477 | C8: =SUM(C3:C7) -> 2101643 | D8: =SUM(D3:D7) -> 2330272 | E8: =SUM(E3:E7) -> 2330272 | F8: =SUM(F3:F7) -> 2214992 | G8: =SUM(G3:G7) -> 2128092 | H8: =SUM(H3:H7) -> 2128092 | I8: =SUM(I3:I7) -> 2128092 | ... M8: =SUM(M3:M7) -> 2128092 | N8: =SUM(B8:M8) -> 26914300

Sheet план-факт
A1: План-факт анализ выручки за 2024 год
A4: Показатель, руб. | B4: План | C4: Факт | D4: Абсолютное отклонение | E4: Относительное отклонение | F4: План Q | G4: Факт Q | H4: Абсолютное отклонение Q | I4: Относительное отклонение Q?%
A5: Январь | B5: =[20]Фин.модель!D7 -> 13555008 | C5: 14973705 | D5: =C5-B5 -> 1418697.4 | E5: =IF((OR(ISERROR(C5/B5-1),AND(B5<0,C5>0),AND(B5>0,C5<0))),"-",(C5-B5)/ABS(B5)) -> 0.10466223 | F5: =B5+B6+B7 -> 46252884 | G5: =C5+C6+C7 -> 44848431 | H5: =G5-F5 -> -1404452.9 | I5: =H5/F5 -> -0.030364656
A6: Февраль | B6: =[20]Фин.модель!F7 -> 15930971 | C6: 13523999 | D6: =C6-B6 -> -2406971.7 | E6: =IF((OR(ISERROR(C6/B6-1),AND(B6<0,C6>0),AND(B6>0,C6<0))),"-",(C6-B6)/ABS(B6)) -> -0.15108757
A7: Март | B7: =[20]Фин.модель!H7 -> 16766906 | C7: 16350727 | D7: =C7-B7 -> -416178.55 | E7: =IF((OR(ISERROR(C7/B7-1),AND(B7<0,C7>0),AND(B7>0,C7<0))),"-",(C7-B7)/ABS(B7)) -> -0.024821429
A8: Апрель | B8: =[20]Фин.модель!N7 -> 17222232 | C8: =Фин.модель!#REF! -> #REF! | D8: =C8-B8 -> #REF! | E8: =IF((OR(ISERROR(C8/B8-1),AND(B8<0,C8>0),AND(B8>0,C8<0))),"-",(C8-B8)/ABS(B8)) -> #REF! | F8: =B8+B9+B10 -> 52962691 | G8: =C8+C9+C10 -> #REF! | H8: =G8-F8 -> #REF! | I8: =H8/F8 -> #REF!
A9: Май | B9: =[20]Фин.модель!O7 -> 17812049 | C9: =Фин.модель!#REF! -> #REF! | D9: =C9-B9 -> #REF! | E9: =IF((OR(ISERROR(C9/B9-1),AND(B9<0,C9>0),AND(B9>0,C9<0))),"-",(C9-B9)/ABS(B9)) -> #REF!
A10: Июнь | B10: =[20]Фин.модель!P7 -> 17928410 | C10: =Фин.модель!#REF! -> #REF! | D10: =C10-B10 -> #REF! | E10: =IF((OR(ISERROR(C10/B10-1),AND(B10<0,C10>0),AND(B10>0,C10<0))),"-",(C10-B10)/ABS(B10)) -> #REF!
A11: Июль | B11: =[20]Фин.модель!Q7 -> 18698293 | C11: =Фин.модель!#REF! -> #REF! | D11: =C11-B11 -> #REF! | E11: =IF((OR(ISERROR(C11/B11-1),AND(B11<0,C11>0),AND(B11>0,C11<0))),"-",(C11-B11)/ABS(B11)) -> #REF! | F11: =B11+B12+B13 -> 57379604 | G11: =C11+C12+C13 -> #REF! | H11: =G11-F11 -> #REF! | I11: =H11/F11 -> #REF!
A12: Август | B12: =[20]Фин.модель!R7 -> 19377775 | C12: =Фин.модель!#REF! -> #REF! | D12: =C12-B12 -> #REF! | E12: =IF((OR(ISERROR(C12/B12-1),AND(B12<0,C12>0),AND(B12>0,C12<0))),"-",(C12-B12)/ABS(B12)) -> #REF!
A13: Сентябрь | B13: =[20]Фин.модель!S7 -> 19303536 | C13: =Фин.модель!#REF! -> #REF! | D13: =C13-B13 -> #REF! | E13: =IF((OR(ISERROR(C13/B13-1),AND(B13<0,C13>0),AND(B13>0,C13<0))),"-",(C13-B13)/ABS(B13)) -> #REF!
A14: Октябрь | B14: =[20]Фин.модель!T7 -> 23742786 | C14: =Фин.модель!#REF! -> #REF! | D14: =C14-B14 -> #REF! | E14: =IF((OR(ISERROR(C14/B14-1),AND(B14<0,C14>0),AND(B14>0,C14<0))),"-",(C14-B14)/ABS(B14)) -> #REF! | H14: =G14-F14 -> 0 | I14: =H14-G14 -> 0
A15: Ноябрь | B15: =[20]Фин.модель!U7 -> 22413784 | C15: =Фин.модель!#REF! -> #REF! | D15: =C15-B15 -> #REF! | E15: =IF((OR(ISERROR(C15/B15-1),AND(B15<0,C15>0),AND(B15>0,C15<0))),"-",(C15-B15)/ABS(B15)) -> #REF! | H15: =G15-F15 -> 0 | I15: =H15-G15 -> 0
A16: Декабрь | B16: =[20]Фин.модель!V7 -> 22994072 | H16: =G16-F16 -> 0 | I16: =H16-G16 -> 0
E17: 1.02
A18: Итого | B18: =SUM(B5:B9) -> 81287165 | C18: =SUM(C5:C16) -> #REF! | D18: =I18 -> #REF! | F18: =SUM(F5:F16) -> 1.5659518e+08 | G18: =SUM(G5:G16) -> #REF! | H18: =SUM(H5:H16) -> #REF! | I18: =H18/F18 -> #REF!
A21: План-факт анализ выручки 2023/2024
A24: Показатель, руб. | B24: 2023 | C24: 2024 | D24: Абсолютное отклонение | E24: Относительное отклонение | F24: Q23 | G24: Q24 | H24: Абсолютное отклонение Q | I24: Относительное отклонение Q, %
A25: Январь | B25: 10963181 | C25: 14973705 | D25: =C25-B25 -> 4010524 | E25: =IF((OR(ISERROR(C25/B25-1),AND(B25<0,C25>0),AND(B25>0,C25<0))),"-",(C25-B25)/ABS(B25)) -> 0.36581755 | F25: =B25+B26+B27 -> 34923188 | G25: =C25+C26+C27 -> 44848431 | H25: =G25-F25 -> 9925243 | I25: =H25/F25 -> 0.28420209
A26: Февраль | B26: 12013385 | C26: 13523999 | D26: =C26-B26 -> 1510614 | E26: =IF((OR(ISERROR(C26/B26-1),AND(B26<0,C26>0),AND(B26>0,C26<0))),"-",(C26-B26)/ABS(B26)) -> 0.12574424
A27: Март | B27: 11946622 | C27: 16350727 | D27: =C27-B27 -> 4404105 | E27: =IF((OR(ISERROR(C27/B27-1),AND(B27<0,C27>0),AND(B27>0,C27<0))),"-",(C27-B27)/ABS(B27)) -> 0.36864856
A28: Апрель | B28: 13651167 | C28: =C8 -> #REF! | D28: =C28-B28 -> #REF! | E28: =IF((OR(ISERROR(C28/B28-1),AND(B28<0,C28>0),AND(B28>0,C28<0))),"-",(C28-B28)/ABS(B28)) -> #REF! | F28: =B28+B29+B30 -> 38554029 | G28: =C28+C29+C30 -> #REF! | H28: =G28-F28 -> #REF! | I28: =H28/F28 -> #REF!
A29: Май | B29: 11807584 | C29: =Фин.модель!#REF! -> #REF! | D29: =C29-B29 -> #REF! | E29: =IF((OR(ISERROR(C29/B29-1),AND(B29<0,C29>0),AND(B29>0,C29<0))),"-",(C29-B29)/ABS(B29)) -> #REF!
A30: Июнь | B30: 13095278 | C30: =Фин.модель!#REF! -> #REF! | D30: =C30-B30 -> #REF! | E30: =IF((OR(ISERROR(C30/B30-1),AND(B30<0,C30>0),AND(B30>0,C30<0))),"-",(C30-B30)/ABS(B30)) -> #REF!
A31: Июль | B31: 13801401 | C31: =Фин.модель!#REF! -> #REF! | D31: =C31-B31 -> #REF! | E31: =IF((OR(ISERROR(C31/B31-1),AND(B31<0,C31>0),AND(B31>0,C31<0))),"-",(C31-B31)/ABS(B31)) -> #REF! | F31: =B31+B32+B33 -> 42191943 | G31: =C31+C32+C33 -> #REF! | H31: =G31-F31 -> #REF! | I31: =H31/F31 -> #REF!
A32: Август | B32: 14707554 | C32: =Фин.модель!#REF! -> #REF! | D32: =C32-B32 -> #REF! | E32: =IF((OR(ISERROR(C32/B32-1),AND(B32<0,C32>0),AND(B32>0,C32<0))),"-",(C32-B32)/ABS(B32)) -> #REF!
A33: Сентябрь | B33: 13682988 | C33: =Фин.модель!#REF! -> #REF! | D33: =C33-B33 -> #REF! | E33: =IF((OR(ISERROR(C33/B33-1),AND(B33<0,C33>0),AND(B33>0,C33<0))),"-",(C33-B33)/ABS(B33)) -> #REF!
A34: Октябрь | B34: 15587882 | C34: =Фин.модель!#REF! -> #REF! | D34: =C34-B34 -> #REF! | E34: =IF((OR(ISERROR(C34/B34-1),AND(B34<0,C34>0),AND(B34>0,C34<0))),"-",(C34-B34)/ABS(B34)) -> #REF! | H34: =G34-F34 -> 0 | I34: =H34-G34 -> 0
A35: Ноябрь | B35: 14045645 | C35: =Фин.модель!#REF! -> #REF! | D35: =C35-B35 -> #REF! | E35: =IF((OR(ISERROR(C35/B35-1),AND(B35<0,C35>0),AND(B35>0,C35<0))),"-",(C35-B35)/ABS(B35)) -> #REF! | H35: =G35-F35 -> 0 | I35: =H35-G35 -> 0
A36: Декабрь | B36: =[20]Фин.модель!V27 -> 0 | D36: =C36-B36 -> 0 | E36: =IF((OR(ISERROR(C36/B36-1),AND(B36<0,C36>0),AND(B36>0,C36<0))),"-",(C36-B36)/ABS(B36)) -> - | H36: =G36-F36 -> 0 | I36: =H36-G36 -> 0
E37: 1.02
A38: Итого | B38: =SUM(B25:B36) -> 145302687 | C38: =SUM(C25:C36) -> #REF! | D38: =SUM(D25:D36) -> #REF! | E38: =IF((OR(ISERROR(C38/B38-1),AND(B38<0,C38>0),AND(B38>0,C38<0))),"-",(C38-B38)/ABS(B38)) -> #REF! | F38: =SUM(F25:F36) -> 115669160 | G38: =SUM(G25:G36) -> #REF! | H38: =SUM(H25:H36) -> #REF! | I38: =H38/F38 -> #REF!
A42: План-факт анализ чистой прибыли за 2024 год
A45: Показатель, руб. | B45: План | C45: Факт | D45: Абсолютное отклонение | E45: Относительное отклонение | F45: План Q | G45: Факт Q | H45: Абсолютное отклонение Q | I45: Относительное отклонение Q%
A46: Январь | B46: =[20]Фин.модель!D101 -> 2512470.2 | C46: =[20]Фин.модель!E101 -> 4054553.6 | D46: =C46-B46 -> 1542083.4 | E46: =IF((OR(ISERROR(C46/B46-1),AND(B46<0,C46>0),AND(B46>0,C46<0))),"-",(C46-B46)/ABS(B46)) -> 0.61377183 | F46: =B46+B47+B48 -> 10410597 | G46: =C46+C47+C48 -> 10301296 | H46: =G46-F46 -> -109300.63 | I46: =H46/F46 -> -0.010498979
A47: Февраль | B47: =[20]Фин.модель!F101 -> 3776098.2 | C47: =[20]Фин.модель!G97 -> 1305317.2 | D47: =C47-B47 -> -2470781 | E47: =IF((OR(ISERROR(C47/B47-1),AND(B47<0,C47>0),AND(B47>0,C47<0))),"-",(C47-B47)/ABS(B47)) -> -0.65432116
A48: Март | B48: =[20]Фин.модель!H97 -> 4122028.5 | C48: =[20]Фин.модель!I97 -> 4941425.4 | D48: =C48-B48 -> 819396.95 | E48: =IF((OR(ISERROR(C48/B48-1),AND(B48<0,C48>0),AND(B48>0,C48<0))),"-",(C48-B48)/ABS(B48)) -> 0.19878489
A49: Апрель | B49: 4377603 | C49: =Фин.модель!#REF! -> #REF! | D49: =C49-B49 -> #REF! | E49: =IF((OR(ISERROR(C49/B49-1),AND(B49<0,C49>0),AND(B49>0,C49<0))),"-",(C49-B49)/ABS(B49)) -> #REF! | F49: =B49+B50+B51 -> 11966882 | G49: =C49+C50+C51 -> #REF! | H49: =G49-F49 -> #REF! | I49: =H49/F49 -> #REF!
A50: Май | B50: =Фин.модель!L116 -> 3988449.1 | C50: =Фин.модель!#REF! -> #REF! | D50: =C50-B50 -> #REF! | E50: =IF((OR(ISERROR(C50/B50-1),AND(B50<0,C50>0),AND(B50>0,C50<0))),"-",(C50-B50)/ABS(B50)) -> #REF!
A51: Июнь | B51: =Фин.модель!N112 -> 3600830.2 | C51: =Фин.модель!#REF! -> #REF! | D51: =C51-B51 -> #REF! | E51: =IF((OR(ISERROR(C51/B51-1),AND(B51<0,C51>0),AND(B51>0,C51<0))),"-",(C51-B51)/ABS(B51)) -> #REF!
A52: Июль | B52: =Фин.модель!P116 -> 4598679.2 | C52: =Фин.модель!#REF! -> #REF! | D52: =C52-B52 -> #REF! | E52: =IF((OR(ISERROR(C52/B52-1),AND(B52<0,C52>0),AND(B52>0,C52<0))),"-",(C52-B52)/ABS(B52)) -> #REF! | F52: =B52+B53+B54 -> 15292790 | G52: =C52+C53+C54 -> #REF! | H52: =G52-F52 -> #REF! | I52: =H52/F52 -> #REF!
A53: Август | B53: =Фин.модель!R116 -> 5101475.4 | C53: =Фин.модель!#REF! -> #REF! | D53: =C53-B53 -> #REF! | E53: =IF((OR(ISERROR(C53/B53-1),AND(B53<0,C53>0),AND(B53>0,C53<0))),"-",(C53-B53)/ABS(B53)) -> #REF!
A54: Сентябрь | B54: =Фин.модель!T116 -> 5592635.3 | C54: =Фин.модель!#REF! -> #REF! | D54: =C54-B54 -> #REF! | E54: =IF((OR(ISERROR(C54/B54-1),AND(B54<0,C54>0),AND(B54>0,C54<0))),"-",(C54-B54)/ABS(B54)) -> #REF!
A55: Октябрь | B55: =Фин.модель!V112 -> 5963830.9 | C55: =Фин.модель!#REF! -> #REF! | D55: =C55-B55 -> #REF! | E55: =IF((OR(ISERROR(C55/B55-1),AND(B55<0,C55>0),AND(B55>0,C55<0))),"-",(C55-B55)/ABS(B55)) -> #REF! | H55: =G55-F55 -> 0 | I55: =H55-G55 -> 0
A56: Ноябрь | B56: =Фин.модель!X116 -> 5867598.9 | C56: =Фин.модель!#REF! -> #REF! | D56: =C56-B56 -> #REF! | E56: =IF((OR(ISERROR(C56/B56-1),AND(B56<0,C56>0),AND(B56>0,C56<0))),"-",(C56-B56)/ABS(B56)) -> #REF! | H56: =G56-F56 -> 0 | I56: =H56-G56 -> 0
A57: Декабрь | D57: =C57-B57 -> 0 | E57: =IF((OR(ISERROR(C57/B57-1),AND(B57<0,C57>0),AND(B57>0,C57<0))),"-",(C57-B57)/ABS(B57)) -> - | H57: =G57-F57 -> 0 | I57: =H57-G57 -> 0
E58: 1.02
A59: Итого | B59: =SUM(B46:B57) -> 49501699 | C59: =SUM(C46:C57) -> #REF! | D59: =SUM(D46:D57) -> #REF! | E59: =IF((OR(ISERROR(C59/B59-1),AND(B59<0,C59>0),AND(B59>0,C59<0))),"-",(C59-B59)/ABS(B59)) -> #REF! | F59: =SUM(F46:F57) -> 37670269 | G59: =SUM(G46:G57) -> #REF! | H59: =SUM(H46:H57) -> #REF! | I59: =-H59/F59 -> #REF!
A62: План-факт анализ чистой прибыли 2023-2024 год
A65: Показатель, руб. | B65: 2023 | C65: 2024 | D65: Абсолютное отклонение | E65: Относительное отклонение | F65: Q23 | G65: Q24 | H65: Абсолютное отклонение Q | I65: Относительное отклонение Q%
A66: Январь | B66: -1348454 | C66: =Фин.модель!#REF! -> #REF! | D66: =C66-B66 -> #REF! | E66: =(C66-B66)/ABS(B66) -> #REF! | F66: =B66+B67+B68 -> -2758116 | G66: =C66+C67+C68 -> #REF! | H66: =G66-F66 -> #REF! | I66: =(G66-F66)/ABS(F66) -> #REF!
A67: Февраль | B67: -858874 | C67: =Фин.модель!#REF! -> #REF! | D67: =C67-B67 -> #REF! | E67: =(C67-B67)/ABS(B67) -> #REF!
A68: Март | B68: -550788 | C68: =Фин.модель!#REF! -> #REF! | D68: =C68-B68 -> #REF! | E68: =(C68-B68)/ABS(B68) -> #REF!
A69: Апрель | B69: 3376234 | C69: =Фин.модель!#REF! -> #REF! | D69: =C69-B69 -> #REF! | E69: =IF((OR(ISERROR(C69/B69-1),AND(B69<0,C69>0),AND(B69>0,C69<0))),"-",(C69-B69)/ABS(B69)) -> #REF! | F69: =B69+B70+B71 -> 5920214 | G69: =C69+C70+C71 -> #REF! | H69: =G69-F69 -> #REF! | I69: =H69/F69 -> #REF!
A70: Май | B70: 1742616 | C70: =Фин.модель!#REF! -> #REF! | D70: =C70-B70 -> #REF! | E70: =IF((OR(ISERROR(C70/B70-1),AND(B70<0,C70>0),AND(B70>0,C70<0))),"-",(C70-B70)/ABS(B70)) -> #REF!
A71: Июнь | B71: 801364 | C71: =Фин.модель!#REF! -> #REF! | D71: =C71-B71 -> #REF! | E71: =IF((OR(ISERROR(C71/B71-1),AND(B71<0,C71>0),AND(B71>0,C71<0))),"-",(C71-B71)/ABS(B71)) -> #REF!
A72: Июль | B72: 3016230 | C72: =Фин.модель!#REF! -> #REF! | D72: =C72-B72 -> #REF! | E72: =IF((OR(ISERROR(C72/B72-1),AND(B72<0,C72>0),AND(B72>0,C72<0))),"-",(C72-B72)/ABS(B72)) -> #REF! | F72: =B72+B73+B74 -> 9227515 | G72: =C72+C73+C74 -> #REF! | H72: =G72-F72 -> #REF! | I72: =H72/F72 -> #REF!
A73: Август | B73: 3119988 | C73: =Фин.модель!#REF! -> #REF! | D73: =C73-B73 -> #REF! | E73: =IF((OR(ISERROR(C73/B73-1),AND(B73<0,C73>0),AND(B73>0,C73<0))),"-",(C73-B73)/ABS(B73)) -> #REF!
A74: Сентябрь | B74: 3091297 | C74: =Фин.модель!#REF! -> #REF! | D74: =C74-B74 -> #REF! | E74: =IF((OR(ISERROR(C74/B74-1),AND(B74<0,C74>0),AND(B74>0,C74<0))),"-",(C74-B74)/ABS(B74)) -> #REF!
A75: Октябрь | B75: 4206096 | C75: =Фин.модель!#REF! -> #REF! | D75: =C75-B75 -> #REF! | E75: =IF((OR(ISERROR(C75/B75-1),AND(B75<0,C75>0),AND(B75>0,C75<0))),"-",(C75-B75)/ABS(B75)) -> #REF! | H75: =G75-F75 -> 0 | I75: =H75-G75 -> 0
A76: Ноябрь | B76: 2013181 | C76: =Фин.модель!#REF! -> #REF! | D76: =C76-B76 -> #REF! | E76: =IF((OR(ISERROR(C76/B76-1),AND(B76<0,C76>0),AND(B76>0,C76<0))),"-",(C76-B76)/ABS(B76)) -> #REF! | H76: =G76-F76 -> 0 | I76: =H76-G76 -> 0
A77: Декабрь | D77: =C77-B77 -> 0 | E77: =IF((OR(ISERROR(C77/B77-1),AND(B77<0,C77>0),AND(B77>0,C77<0))),"-",(C77-B77)/ABS(B77)) -> - | H77: =G77-F77 -> 0 | I77: =H77-G77 -> 0
E78: 1.02
A79: Итого | B79: =SUM(B66:B77) -> 18608890 | C79: =SUM(C66:C77) -> #REF! | D79: =SUM(D66:D77) -> #REF! | E79: =IF((OR(ISERROR(C79/B79-1),AND(B79<0,C79>0),AND(B79>0,C79<0))),"-",(C79-B79)/ABS(B79)) -> #REF! | F79: =SUM(F66:F77) -> 12389613 | G79: =SUM(G66:G77) -> #REF! | H79: =SUM(H66:H77) -> #REF! | I79: =H79/F79 -> #REF!
A134: Показатель, млн. руб. | B134: финмодель Q2 | C134: план Q2 | D134: Абсолютное отклонение | E134: Относительное отклонение | F134: финмодельQ2 | G134: планQ2 | H134: Абсолютное отклонение Q | I134: Относительное отклонение Q,%
A135: Апрель | B135: =[20]Фин.модель!N7 -> 17222232 | C135: ='[20]Текущий портфель'!O180 -> 16449479 | D135: =C135-B135 -> -772753 | E135: =IF((OR(ISERROR(C135/B135-1),AND(B135<0,C135>0),AND(B135>0,C135<0))),"-",(C135-B135)/ABS(B135)) -> -0.044869504 | F135: =B135+B136+B137 -> 52962691 | G135: =C135+C136+C137 -> 48419541 | H135: =G135-F135 -> -4543150.5 | I135: =H135/F135 -> -0.085780206
A136: Май | B136: =[20]Фин.модель!O7 -> 17812049 | C136: ='[20]Текущий портфель'!Q180 -> 16123669 | D136: =C136-B136 -> -1688380.5 | E136: =IF((OR(ISERROR(C136/B136-1),AND(B136<0,C136>0),AND(B136>0,C136<0))),"-",(C136-B136)/ABS(B136)) -> -0.094788675
A137: Июнь | B137: =[20]Фин.модель!P7 -> 17928410 | C137: ='[20]Текущий портфель'!S180 -> 15846393 | D137: =C137-B137 -> -2082017 | E137: =IF((OR(ISERROR(C137/B137-1),AND(B137<0,C137>0),AND(B137>0,C137<0))),"-",(C137-B137)/ABS(B137)) -> -0.11612948

Sheet Продажи
D1: ЯНВАРЬ
B2: Mozabrick | D2: 41937
B4: ИТОГО | D4: =SUM(D2:D3) -> 41937
D5: ФЕВРАЛЬ
B6: Мосурбанфорум | D6: 168950
B7: Колеса даром | D7: 3599999.4
B8: Аврора 24 | D8: 725324
B9: Красная поляна | D9: 480589.6
B10: Arlight | D10: 303950
B11: Малоэтажная страна | D11: 184014
B12: Авторы-CS | D12: 140000
B13: Консулпрайм | D13: 458103
B15: ИТОГО | D15: =SUM(D6:D14) -> 6060930
D16: МАРТ
B17: Азбука вкуса | D17: 2000000
B18: Эссити (ZEWA) | D18: 2000000
B19: Делимобиль | D19: 5109905
B21: ИТОГО | D21: =SUM(D17:D20) -> 9109905
D22: АПРЕЛЬ
B23: МАРС- 5 брендов | D23: 12588200
B24: Производительность. Рф | D24: 440000
B26: ИТОГО | D26: =SUM(D23:D25) -> 13028200
D27: ИЮНЬ
B28: Euphoria | D28: 150000
B29: Of.кг | D29: 411660
B31: ИТОГО | D31: =SUM(D28:D30) -> 561660
B34: ВСЕГО | D34: =D15+D4+D21+D26+D31 -> 28802632
A36: ПЛАН | F36: январь | G36: февраль | H36: март | J36: апрель | L36: май | N36: июнь | P36: июль | Q36: август | R36: сентябрь | S36: октябрь | T36: ноябрь | U36: декабрь | V36: январь | W36: февраль | X36: март
D37: смета | E37: выработано | H37: план | I37: факт | J37: план | K37: факт | L37: план | M37: факт | N37: план | O37: факт
A38: EMS | B38: Mozabrick | C38: январь | D38: 41937 | E38: =G38 -> 41937 | G38: =D38 -> 41937
B39: Мосурбанфорум | C39: 27.02. | D39: 168950 | E39: =I39+K39+M39+O39 -> 0 | J39: 168950 | K39: 0
B40: Колеса даром | C40: 26.02. | D40: 3599999.4 | E40: =I40+K40+M40+O40 -> 1200000 | H40: 300000 | I40: 300000 | J40: =$D$40/12 -> 299999.95 | K40: 300000 | L40: =$D$40/12 -> 299999.95 | M40: ='[21]Текущий портфель'!R139 -> 300000 | N40: =$D$40/12 -> 299999.95 | O40: 300000 | P40: =$D$40/12 -> 299999.95 | Q40: =$D$40/12 -> 299999.95 | R40: =$D$40/12 -> 299999.95 | S40: =$D$40/12 -> 299999.95 | T40: =$D$40/12 -> 299999.95 | U40: =$D$40/12 -> 299999.95 | V40: =$D$40/12 -> 299999.95 | W40: =$D$40/12 -> 299999.95
B41: Аврора 24 | C41: 21.02. | D41: 725324 | E41: =I41+K41+M41+O41 -> 134786 | H41: 214350 | J41: 252282 | K41: 134786 | L41: 155166 | M41: ='[21]Текущий портфель'!R137 -> 0 | N41: 126566 | O41: ='Выручка-план'!I124 -> 0
B42: Красная поляна | C42: 15.02. | D42: 480589.6 | E42: =I42+K42+M42 -> 409628 | H42: 146321.6 | I42: 150861 | J42: 66853.6 | K42: 100666 | L42: =J42 -> 66853.6 | M42: ='[21]Текущий портфель'!R132 -> 158101 | N42: =L42 -> 66853.6 | O42: ='Выручка-план'!I119 -> 81898 | P42: =N42 -> 66853.6 | Q42: =P42 -> 66853.6
B43: Arlight | C43: 08.02. | D43: 303950 | E43: =K43+M43+O43 -> 0 | J43: =D43 -> 303950 | K43: 0
B44: Делимобиль | C44: 27.03. | D44: =D19 -> 5109905 | E44: =I44+K44+M44 -> 303258 | J44: 157008 | K44: 157008 | L44: =J44 -> 157008 | M44: ='[21]Текущий портфель'!R142 -> 146250 | N44: =L44 -> 157008 | O44: ='Выручка-план'!I128 -> 50625 | P44: =N44 -> 157008 | Q44: =P44 -> 157008 | R44: =Q44 -> 157008 | S44: =R44 -> 157008 | T44: =S44 -> 157008 | U44: =T44 -> 157008 | V44: =U44 -> 157008 | W44: =V44 -> 157008 | X44: =W44 -> 157008 | Y44: =X44 -> 157008
B45: Москвич | C45: 12.04. | D45: 6250000
B46: Консулпрайм | C46: 19.02. | D46: 458103 | E46: =G46+K46+I46+M46+O46 -> 149416 | G46: 68643 | H46: 163560 | J46: 109407 | K46: 80773 | L46: 77889 | M46: ='[21]Текущий портфель'!R128 -> 0 | O46: ='Выручка-план'!I115 -> 0
A47: CS | B47: Авторы-CS/MONK | C47: 21.02. | D47: 140000 | E47: =K47+M47 -> 150000 | J47: =D47 -> 140000 | K47: 140000 | M47: ='[21]Текущий портфель'!R174+'[21]Текущий портфель'!R187 -> 10000 | O47: 0
B48: Эссити (ZEWA) | C48: 26.03. | D48: =D18 -> 2000000 | E48: =G48+I48+K48+M48 -> 51400 | M48: ='[21]Текущий портфель'!R176 -> 51400
B49: Малоэтажная страна | C49: 07.02. | D49: 184014 | E49: =G49+I49+K49+M49+O49 -> 0 | H49: =D49 -> 184014 | K49: 0
B50: Азбука вкуса | C50: 06.03. | D50: 2000000 | E50: =I50+K50+M50 -> 222100 | H50: =$D$50/12 -> 166666.67 | I50: 41000 | J50: =$D$50/12 -> 166666.67 | K50: 107900 | L50: =$D$50/12 -> 166666.67 | M50: ='[21]Текущий портфель'!R170 -> 73200 | N50: =$D$50/12 -> 166666.67 | O50: ='Выручка-план'!I160 -> 121800 | P50: =$D$50/12 -> 166666.67 | Q50: =$D$50/12 -> 166666.67 | R50: =$D$50/12 -> 166666.67 | S50: =$D$50/12 -> 166666.67 | T50: =$D$50/12 -> 166666.67 | U50: =$D$50/12 -> 166666.67 | V50: =$D$50/12 -> 166666.67 | W50: =$D$50/12 -> 166666.67
B53: ИТОГО | D53: =SUM(D38:D49) -> 19462772 | E53: =SUM(E38:E50) -> 2662525 | F53: 0 | G53: =SUM(G38:G47) -> 110580 | H53: =SUM(H38:H50) -> 1174912.3 | I53: =SUM(I38:I50) -> 491861 | J53: =SUM(J38:J50) -> 1665117.2 | K53: =SUM(K38:K50) -> 1021133 | L53: =SUM(L38:L50) -> 923583.22 | M53: =SUM(M38:M50) -> 738951 | N53: =SUM(N38:N50) -> 817094.22 | O53: =SUM(O38:O52) -> 554323 | P53: =SUM(P38:P50) -> 690528.22 | Q53: =SUM(Q38:Q50) -> 690528.22 | R53: =SUM(R38:R50) -> 623674.62 | S53: =SUM(S38:S50) -> 623674.62 | T53: =SUM(T38:T50) -> 623674.62 | U53: =SUM(U38:U50) -> 623674.62 | V53: =SUM(V38:V50) -> 623674.62 | W53: =SUM(W38:W50) -> 623674.62 | ... AF53: =SUM(AF38:AF50) -> 0
B54: ИСПОЛНЯЕМОСТЬ | E54: =E53/D53 -> 0.13680091 | I54: =I53/H53 -> 0.41863636 | K54: =K53/J53 -> 0.61324992 | M54: =M53/L53 -> 0.80009141 | O54: =O53/N53 -> 0.67840769

Sheet Выручка-план
B2: Юр.лицо | C2: Клиент | D2: факт | E2: факт | F2: факт | G2: факт | H2: факт | I2: факт | J2: факт | K2: =J2 -> факт | L2: факт | M2: факт | N2: факт | O2: 11 мес. | P2: 6 мес | Q2: отток | R2: недополучено
C3: Проекты-текущий портфель EMS | D3: январь | E3: февраль | F3: март | G3: апрель | H3: май | I3: июнь | J3: июль | K3: август | L3: сентябрь | M3: октябрь | N3: ноябрь | O3: средн. значение | P3: средн. значение | Q3: средн за 11 мес. | R3: за 12 мес.
A4: 1 | B4: ЮНИСЕНДЕР СМАРТ ООО | C4: RD Electronics | D4: 478359 | E4: 476950 | F4: 519300 | G4: 519300 | H4: 576649.23 | I4: =VLOOKUP(B4,[22]Лист_1!$A$8:$B$88,2,0) -> 528404.96 | J4: =VLOOKUP(B4,[23]Лист_1!$A$1:$C$65536,3,0) -> 273010.4 | K4: =VLOOKUP(B4,[24]Лист_1!$A$1:$B$65536,2,0) -> 848895.52 | L4: =VLOOKUP(B4,[25]Лист_1!$A$1:$E$65536,5,0) -> 469053.54 | M4: =VLOOKUP(B4,[26]Лист_1!$A$6:$B$71,2,0) -> 821774.71 | N4: =VLOOKUP(B4,[27]ноябрь!$A$1:$B$65536,2,0) -> 759828.03 | O4: =SUM(D4:N4)/11 -> 570138.67 | P4: =SUM(I4:N4)/6 -> 616827.86
A5: =A4+1 -> 2 | B5: ИМПУЛЬС ООО | C5: Amazing Red | D5: 53800 | E5: 195050 | F5: 190050 | G5: 246850 | H5: 174700 | I5: =VLOOKUP(B5,[22]Лист_1!$A$8:$B$88,2,0) -> 246150 | J5: =VLOOKUP(B5,[23]Лист_1!$A$1:$C$65536,3,0) -> 180850 | K5: =VLOOKUP(B5,[24]Лист_1!$A$1:$B$65536,2,0) -> 389900 | L5: =VLOOKUP(B5,[25]Лист_1!$A$1:$E$65536,5,0) -> 436750 | M5: =VLOOKUP(B5,[26]Лист_1!$A$6:$B$71,2,0) -> 385050 | N5: =VLOOKUP(B5,[27]ноябрь!$A$1:$B$65536,2,0) -> 243850 | O5: =SUM(D5:N5)/11 -> 249363.64 | P5: =SUM(I5:N5)/6 -> 313758.33
A6: =A5+1 -> 3 | B6: ООО "РАНДЕВУ" | C6: Rendez vous | D6: 166500 | E6: 0 | F6: 129250 | G6: 0 | H6: 0 | J6: 0 | K6: 0 | L6: 0 | Q6: =SUM(D6:P6)/3 -> 98583.333 | R6: =Q6*9 -> 887250
